Workbook

Sheet June 25
A1: Date | B1: Task Name | C1: Quantity | D1: RE | E1: Total RE | F1: Start Time | G1: End Time | H1: Actual Time taken | I1: Actual End Time | J1: Break Start Time | K1: Break End Time | L1: Total Break time | M1: Comment | N1: Productivity | O1: 0.1875 | P1: Date | Q1: Total RE | R1: Core | S1: Non-Core | T1: Productivity | U1: 0.33333333
A2: 45810 | B2: OGM - Sizing update | C2: 23 | D2: =IFERROR(VLOOKUP($B2,Task!$B$1:$G$70,6,0)," ") -> 0.0055555556 | E2: =IFERROR(D2*C2," ") -> 0.12777778 | F2: 0.35318287 | G2: 0.51381944 | H2: =IF(G2="","", IF(L2=" ",IF(OR(F2=0,G2=0),"",G2-F2),((G2-F2)-L2))) -> 0.11600694 | I2: =IFERROR(IF(L2=" ",(F2+E2),(F2+E2+L2)),"") -> 0.52559028 | L2: 0.04462963 | N2: =IFERROR(E2/H2," ") -> 1.1014666 | O2: 0.73172454 | P2: =IFERROR(__xludf.DUMMYFUNCTION("UNIQUE($A$2:$A$993)"),45810) -> 45810 | Q2: =SUMIF($A:$A,$P2,$E:$E) -> 0.29444444 | R2: =SUMIF($A:$A,$P2,$H:$H) -> 0.26827546 | S2: =IF(OR(R2="",R2>=$U$1)," ",$U$1-R2) -> 0.06505787 | T2: =IFERROR(AVERAGEIF($A:$A,$P2,$N:$N)," ") -> 1.0954421
A3: 45810 | B3: Wholesale Data Enrichment Report | C3: 1 | D3: =IFERROR(VLOOKUP($B3,Task!$B$1:$G$70,6,0)," ") -> 0.020833333 | E3: =IFERROR(D3*C3," ") -> 0.020833333 | F3: =G2 -> 0.51381944 | G3: 0.53293981 | H3: =IF(G3="","", IF(L3=" ",IF(OR(F3=0,G3=0),"",G3-F3),((G3-F3)-L3))) -> 0.01912037 | I3: =IFERROR(IF(L3=" ",(F3+E3),(F3+E3+L3)),"") -> 0.53465278 | N3: =IFERROR(E3/H3," ") -> 1.0895884 | O3: =O2-O1 -> 0.54422454 | P3: =IFERROR(__xludf.DUMMYFUNCTION("""COMPUTED_VALUE"""),45811) -> 45811 | Q3: =IF(SUMIF($A:$A,$P3,$E:$E)=0,"",SUMIF($A:$A,$P3,$E:$E)) -> 0.27638889 | R3: =IF(SUMIF($A:$A,$P3,$H:$H)=0,"",SUMIF($A:$A,$P3,$H:$H)) -> 0.25203704 | S3: =IF(OR(R3="",R3>=$U$1)," ",$U$1-R3) -> 0.081296296 | T3: =IFERROR(AVERAGEIF($A:$A,$P3,$N:$N)," ") -> 1.0873086
A4: 45810 | B4: Nordstrom SQL DATA Dump | C4: 3 | D4: =IFERROR(VLOOKUP($B4,Task!$B$1:$G$70,6,0)," ") -> 0.048611111 | E4: =IFERROR(D4*C4," ") -> 0.14583333 | F4: =G3 -> 0.53293981 | G4: 0.70162037 | H4: =IF(G4="","", IF(L4=" ",IF(OR(F4=0,G4=0),"",G4-F4),((G4-F4)-L4))) -> 0.13314815 | I4: =IFERROR(IF(L4=" ",(F4+E4),(F4+E4+L4)),"") -> 0.71430556 | L4: 0.035532407 | N4: =IFERROR(E4/H4," ") -> 1.0952712 | P4: =IFERROR(__xludf.DUMMYFUNCTION("""COMPUTED_VALUE"""),45812) -> 45812 | Q4: =IF(SUMIF($A:$A,$P4,$E:$E)=0,"",SUMIF($A:$A,$P4,$E:$E)) -> 0.26111111 | R4: =IF(SUMIF($A:$A,$P4,$H:$H)=0,"",SUMIF($A:$A,$P4,$H:$H)) -> 0.23758102 | S4: =IF(OR(R4="",R4>=$U$1)," ",$U$1-R4) -> 0.095752315 | T4: =IFERROR(AVERAGEIF($A:$A,$P4,$N:$N)," ") -> 1.0985125
A5: 45811 | B5: Nordstrom SQL DATA Dump | C5: 2 | D5: =IFERROR(VLOOKUP($B5,Task!$B$1:$G$70,6,0)," ") -> 0.048611111 | E5: =IFERROR(D5*C5," ") -> 0.097222222 | F5: 0.42399306 | G5: 0.52989016 | H5: =IF(G5="","", IF(L5=" ",IF(OR(F5=0,G5=0),"",G5-F5),((G5-F5)-L5))) -> 0.086614699 | I5: =IFERROR(IF(L5=" ",(F5+E5),(F5+E5+L5)),"") -> 0.54049769 | L5: 0.019282407 | N5: =IFERROR(E5/H5," ") -> 1.1224679 | P5: =IFERROR(__xludf.DUMMYFUNCTION("""COMPUTED_VALUE"""),45813) -> 45813 | Q5: =IF(SUMIF($A:$A,$P5,$E:$E)=0,"",SUMIF($A:$A,$P5,$E:$E)) -> 0.32430556 | R5: =IF(SUMIF($A:$A,$P5,$H:$H)=0,"",SUMIF($A:$A,$P5,$H:$H)) -> 0.29510417 | S5: =IF(OR(R5="",R5>=$U$1)," ",$U$1-R5) -> 0.038229167 | T5: =IFERROR(AVERAGEIF($A:$A,$P5,$N:$N)," ") -> 1.0977707
A6: 45811 | B6: Wholesale Data Enrichment Report | C6: 1 | D6: =IFERROR(VLOOKUP($B6,Task!$B$1:$G$70,6,0)," ") -> 0.020833333 | E6: =IFERROR(D6*C6," ") -> 0.020833333 | F6: =G5 -> 0.52989016 | G6: 0.55974537 | H6: =IF(G6="","", IF(L6=" ",IF(OR(F6=0,G6=0),"",G6-F6),((G6-F6)-L6))) -> 0.020121412 | I6: =IFERROR(IF(L6=" ",(F6+E6),(F6+E6+L6)),"") -> 0.56045729 | L6: 0.0097337963 | N6: =IFERROR(E6/H6," ") -> 1.0353813 | P6: =IFERROR(__xludf.DUMMYFUNCTION("""COMPUTED_VALUE"""),45819) -> 45819 | Q6: =IF(SUMIF($A:$A,$P6,$E:$E)=0,"",SUMIF($A:$A,$P6,$E:$E)) -> 0.34722222 | R6: =IF(SUMIF($A:$A,$P6,$H:$H)=0,"",SUMIF($A:$A,$P6,$H:$H)) -> 0.31711219 | S6: =IF(OR(R6="",R6>=$U$1)," ",$U$1-R6) -> 0.016221146 | T6: =IFERROR(AVERAGEIF($A:$A,$P6,$N:$N)," ") -> 1.090918
A7: 45811 | B7: OGM - Sizing update | C7: 12 | D7: =IFERROR(VLOOKUP($B7,Task!$B$1:$G$70,6,0)," ") -> 0.0055555556 | E7: =IFERROR(D7*C7," ") -> 0.066666667 | F7: =G6 -> 0.55974537 | G7: 0.62164352 | H7: =IF(G7="","", IF(L7=" ",IF(OR(F7=0,G7=0),"",G7-F7),((G7-F7)-L7))) -> 0.061898148 | I7: =IFERROR(IF(L7=" ",(F7+E7),(F7+E7+L7)),"") -> 0.62641204 | N7: =IFERROR(E7/H7," ") -> 1.0770381 | P7: =IFERROR(__xludf.DUMMYFUNCTION("""COMPUTED_VALUE"""),45820) -> 45820 | Q7: =IF(SUMIF($A:$A,$P7,$E:$E)=0,"",SUMIF($A:$A,$P7,$E:$E)) -> 0.30833333 | R7: =IF(SUMIF($A:$A,$P7,$H:$H)=0,"",SUMIF($A:$A,$P7,$H:$H)) -> 0.28547454 | S7: =IF(OR(R7="",R7>=$U$1)," ",$U$1-R7) -> 0.047858796 | T7: =IFERROR(AVERAGEIF($A:$A,$P7,$N:$N)," ") -> 1.0979424
A8: 45811 | B8: OGM - Sizing update | C8: =21-C7 -> 9 | D8: =IFERROR(VLOOKUP($B8,Task!$B$1:$G$70,6,0)," ") -> 0.0055555556 | E8: =IFERROR(D8*C8," ") -> 0.05 | F8: =G7 -> 0.62164352 | G8: 0.69668981 | H8: =IF(G8="","", IF(L8=" ",IF(OR(F8=0,G8=0),"",G8-F8),((G8-F8)-L8))) -> 0.046111111 | I8: =IFERROR(IF(L8=" ",(F8+E8),(F8+E8+L8)),"") -> 0.7005787 | L8: 0.028935185 | N8: =IFERROR(E8/H8," ") -> 1.0843373 | P8: =IFERROR(__xludf.DUMMYFUNCTION("""COMPUTED_VALUE"""),45821) -> 45821 | Q8: =IF(SUMIF($A:$A,$P8,$E:$E)=0,"",SUMIF($A:$A,$P8,$E:$E)) -> 0.34444444 | R8: =IF(SUMIF($A:$A,$P8,$H:$H)=0,"",SUMIF($A:$A,$P8,$H:$H)) -> 0.31457176 | S8: =IF(OR(R8="",R8>=$U$1)," ",$U$1-R8) -> 0.018761574 | T8: =IFERROR(AVERAGEIF($A:$A,$P8,$N:$N)," ") -> 1.0923026
A9: 45811 | B9: DAM - Image Approval | C9: 15 | D9: =IFERROR(VLOOKUP($B9,Task!$B$1:$G$70,6,0)," ") -> 0.0027777778 | E9: =IFERROR(D9*C9," ") -> 0.041666667 | F9: =G8 -> 0.69668981 | G9: 0.73398148 | H9: =IF(G9="","", IF(L9=" ",IF(OR(F9=0,G9=0),"",G9-F9),((G9-F9)-L9))) -> 0.037291667 | I9: =IFERROR(IF(L9=" ",(F9+E9),(F9+E9+L9)),"") -> 0.73835648 | N9: =IFERROR(E9/H9," ") -> 1.1173184 | P9: =IFERROR(__xludf.DUMMYFUNCTION("""COMPUTED_VALUE"""),45824) -> 45824 | Q9: =IF(SUMIF($A:$A,$P9,$E:$E)=0,"",SUMIF($A:$A,$P9,$E:$E)) -> 0.33611111 | R9: =IF(SUMIF($A:$A,$P9,$H:$H)=0,"",SUMIF($A:$A,$P9,$H:$H)) -> 0.30585648 | S9: =IF(OR(R9="",R9>=$U$1)," ",$U$1-R9) -> 0.027476852 | T9: =IFERROR(AVERAGEIF($A:$A,$P9,$N:$N)," ") -> 1.0985607
A10: 45812 | B10: OGM - Sizing update | C10: 7 | D10: =IFERROR(VLOOKUP($B10,Task!$B$1:$G$70,6,0)," ") -> 0.0055555556 | E10: =IFERROR(D10*C10," ") -> 0.038888889 | F10: 0.3659375 | G10: 0.40137731 | H10: =IF(G10="","", IF(L10=" ",IF(OR(F10=0,G10=0),"",G10-F10),((G10-F10)-L10))) -> 0.035439815 | I10: =IFERROR(IF(L10=" ",(F10+E10),(F10+E10+L10)),"") -> 0.40482639 | N10: =IFERROR(E10/H10," ") -> 1.097322 | P10: =IFERROR(__xludf.DUMMYFUNCTION("""COMPUTED_VALUE"""),45825) -> 45825 | Q10: =IF(SUMIF($A:$A,$P10,$E:$E)=0,"",SUMIF($A:$A,$P10,$E:$E)) -> 0.32916667 | R10: =IF(SUMIF($A:$A,$P10,$H:$H)=0,"",SUMIF($A:$A,$P10,$H:$H)) -> 0.29856481 | S10: =IF(OR(R10="",R10>=$U$1)," ",$U$1-R10) -> 0.034768519 | T10: =IFERROR(AVERAGEIF($A:$A,$P10,$N:$N)," ") -> 1.1032726
A11: 45812 | B11: Nordstrom SQL DATA Dump | C11: 1 | D11: =IFERROR(VLOOKUP($B11,Task!$B$1:$G$70,6,0)," ") -> 0.048611111 | E11: =IFERROR(D11*C11," ") -> 0.048611111 | F11: =G10 -> 0.40137731 | G11: 0.50587963 | H11: =IF(G11="","", IF(L11=" ",IF(OR(F11=0,G11=0),"",G11-F11),((G11-F11)-L11))) -> 0.044537037 | I11: =IFERROR(IF(L11=" ",(F11+E11),(F11+E11+L11)),"") -> 0.5099537 | L11: 0.059965278 | N11: =IFERROR(E11/H11," ") -> 1.0914761 | P11: =IFERROR(__xludf.DUMMYFUNCTION("""COMPUTED_VALUE"""),45827) -> 45827 | Q11: =IF(SUMIF($A:$A,$P11,$E:$E)=0,"",SUMIF($A:$A,$P11,$E:$E)) -> 0.35 | R11: =IF(SUMIF($A:$A,$P11,$H:$H)=0,"",SUMIF($A:$A,$P11,$H:$H)) -> 0.32015046 | S11: =IF(OR(R11="",R11>=$U$1)," ",$U$1-R11) -> 0.01318287 | T11: =IFERROR(AVERAGEIF($A:$A,$P11,$N:$N)," ") -> 1.0871975
A12: 45812 | B12: DAM - Image Approval | C12: 35 | D12: =IFERROR(VLOOKUP($B12,Task!$B$1:$G$70,6,0)," ") -> 0.0027777778 | E12: =IFERROR(D12*C12," ") -> 0.097222222 | F12: =G11 -> 0.50587963 | G12: 0.61717593 | H12: =IF(G12="","", IF(L12=" ",IF(OR(F12=0,G12=0),"",G12-F12),((G12-F12)-L12))) -> 0.08837963 | I12: =IFERROR(IF(L12=" ",(F12+E12),(F12+E12+L12)),"") -> 0.62601852 | L12: 0.022916667 | N12: =IFERROR(E12/H12," ") -> 1.1000524 | P12: =IFERROR(__xludf.DUMMYFUNCTION("""COMPUTED_VALUE"""),45828) -> 45828 | Q12: =IF(SUMIF($A:$A,$P12,$E:$E)=0,"",SUMIF($A:$A,$P12,$E:$E)) -> 0.27222222 | R12: =IF(SUMIF($A:$A,$P12,$H:$H)=0,"",SUMIF($A:$A,$P12,$H:$H)) -> 0.2503125 | S12: =IF(OR(R12="",R12>=$U$1)," ",$U$1-R12) -> 0.083020833 | T12: =IFERROR(AVERAGEIF($A:$A,$P12,$N:$N)," ") -> 1.0926938
A13: 45812 | B13: DAM - Image Approval | C13: 20 | D13: =IFERROR(VLOOKUP($B13,Task!$B$1:$G$70,6,0)," ") -> 0.0027777778 | E13: =IFERROR(D13*C13," ") -> 0.055555556 | F13: =G12 -> 0.61717593 | G13: 0.68928241 | H13: =IF(G13="","", IF(L13=" ",IF(OR(F13=0,G13=0),"",G13-F13),((G13-F13)-L13))) -> 0.05025463 | I13: =IFERROR(IF(L13=" ",(F13+E13),(F13+E13+L13)),"") -> 0.69458333 | L13: 0.021851852 | N13: =IFERROR(E13/H13," ") -> 1.1054813 | P13: =IFERROR(__xludf.DUMMYFUNCTION("""COMPUTED_VALUE"""),45831) -> 45831 | Q13: =IF(SUMIF($A:$A,$P13,$E:$E)=0,"",SUMIF($A:$A,$P13,$E:$E)) -> 0.37152778 | R13: =IF(SUMIF($A:$A,$P13,$H:$H)=0,"",SUMIF($A:$A,$P13,$H:$H)) -> 0.33529976 | S13: =IF(OR(R13="",R13>=$U$1)," ",$U$1-R13) | T13: =IFERROR(AVERAGEIF($A:$A,$P13,$N:$N)," ") -> 1.1134048
A14: 45812 | B14: Wholesale Data Enrichment Report | C14: 1 | D14: =IFERROR(VLOOKUP($B14,Task!$B$1:$G$70,6,0)," ") -> 0.020833333 | E14: =IFERROR(D14*C14," ") -> 0.020833333 | F14: =G13 -> 0.68928241 | G14: 0.70825231 | H14: =IF(G14="","", IF(L14=" ",IF(OR(F14=0,G14=0),"",G14-F14),((G14-F14)-L14))) -> 0.018969907 | I14: =IFERROR(IF(L14=" ",(F14+E14),(F14+E14+L14)),"") -> 0.71011574 | N14: =IFERROR(E14/H14," ") -> 1.0982306 | P14: =IFERROR(__xludf.DUMMYFUNCTION("""COMPUTED_VALUE"""),45832) -> 45832 | Q14: =IF(SUMIF($A:$A,$P14,$E:$E)=0,"",SUMIF($A:$A,$P14,$E:$E)) -> 0.25694444 | R14: =IF(SUMIF($A:$A,$P14,$H:$H)=0,"",SUMIF($A:$A,$P14,$H:$H)) -> 0.093796296 | S14: =IF(OR(R14="",R14>=$U$1)," ",$U$1-R14) -> 0.23953704 | T14: =IFERROR(AVERAGEIF($A:$A,$P14,$N:$N)," ") -> 1.1909953
A15: 45813 | B15: Nordstrom SQL DATA Dump | C15: 1 | D15: =IFERROR(VLOOKUP($B15,Task!$B$1:$G$70,6,0)," ") -> 0.048611111 | E15: =IFERROR(D15*C15," ") -> 0.048611111 | F15: 0.38018519 | G15: 0.42590278 | H15: =IF(G15="","", IF(L15=" ",IF(OR(F15=0,G15=0),"",G15-F15),((G15-F15)-L15))) -> 0.045717593 | I15: =IFERROR(IF(L15=" ",(F15+E15),(F15+E15+L15)),"") -> 0.4287963 | N15: =IFERROR(E15/H15," ") -> 1.0632911 | Q15: =IF(SUMIF($A:$A,$P15,$E:$E)=0,"",SUMIF($A:$A,$P15,$E:$E)) | R15: =IF(SUMIF($A:$A,$P15,$H:$H)=0,"",SUMIF($A:$A,$P15,$H:$H)) | S15: =IF(OR(R15="",R15>=$U$1)," ",$U$1-R15) | T15: =IFERROR(AVERAGEIF($A:$A,$P15,$N:$N)," ")
A16: 45813 | B16: OGM - Sizing update | C16: 8 | D16: =IFERROR(VLOOKUP($B16,Task!$B$1:$G$70,6,0)," ") -> 0.0055555556 | E16: =IFERROR(D16*C16," ") -> 0.044444444 | F16: =G15 -> 0.42590278 | G16: 0.46783565 | H16: =IF(G16="","", IF(L16=" ",IF(OR(F16=0,G16=0),"",G16-F16),((G16-F16)-L16))) -> 0.04193287 | I16: =IFERROR(IF(L16=" ",(F16+E16),(F16+E16+L16)),"") -> 0.47034722 | N16: =IFERROR(E16/H16," ") -> 1.0598951 | Q16: =IF(SUMIF($A:$A,$P16,$E:$E)=0,"",SUMIF($A:$A,$P16,$E:$E)) | R16: =IF(SUMIF($A:$A,$P16,$H:$H)=0,"",SUMIF($A:$A,$P16,$H:$H)) | S16: =IF(OR(R16="",R16>=$U$1)," ",$U$1-R16) | T16: =IFERROR(AVERAGEIF($A:$A,$P16,$N:$N)," ")
A17: 45813 | B17: Nordstrom SQL DATA Dump | C17: 1 | D17: =IFERROR(VLOOKUP($B17,Task!$B$1:$G$70,6,0)," ") -> 0.048611111 | E17: =IFERROR(D17*C17," ") -> 0.048611111 | F17: =G16 -> 0.46783565 | G17: 0.53450231 | H17: =IF(G17="","", IF(L17=" ",IF(OR(F17=0,G17=0),"",G17-F17),((G17-F17)-L17))) -> 0.043738426 | I17: =IFERROR(IF(L17=" ",(F17+E17),(F17+E17+L17)),"") -> 0.539375 | L17: 0.022928241 | N17: =IFERROR(E17/H17," ") -> 1.1114051 | Q17: =IF(SUMIF($A:$A,$P17,$E:$E)=0,"",SUMIF($A:$A,$P17,$E:$E)) | R17: =IF(SUMIF($A:$A,$P17,$H:$H)=0,"",SUMIF($A:$A,$P17,$H:$H)) | S17: =IF(OR(R17="",R17>=$U$1)," ",$U$1-R17) | T17: =IFERROR(AVERAGEIF($A:$A,$P17,$N:$N)," ")
A18: 45813 | B18: OGM - Sizing update | C18: 22 | D18: =IFERROR(VLOOKUP($B18,Task!$B$1:$G$70,6,0)," ") -> 0.0055555556 | E18: =IFERROR(D18*C18," ") -> 0.12222222 | F18: =G17 -> 0.53450231 | G18: 0.66586806 | H18: =IF(G18="","", IF(L18=" ",IF(OR(F18=0,G18=0),"",G18-F18),((G18-F18)-L18))) -> 0.10954861 | I18: =IFERROR(IF(L18=" ",(F18+E18),(F18+E18+L18)),"") -> 0.67854167 | L18: 0.02181713 | N18: =IFERROR(E18/H18," ") -> 1.1156894 | Q18: =IF(SUMIF($A:$A,$P18,$E:$E)=0,"",SUMIF($A:$A,$P18,$E:$E)) | R18: =IF(SUMIF($A:$A,$P18,$H:$H)=0,"",SUMIF($A:$A,$P18,$H:$H)) | S18: =IF(OR(R18="",R18>=$U$1)," ",$U$1-R18) | T18: =IFERROR(AVERAGEIF($A:$A,$P18,$N:$N)," ")
A19: 45813 | B19: Wholesale Data Enrichment Report | C19: 1 | D19: =IFERROR(VLOOKUP($B19,Task!$B$1:$G$70,6,0)," ") -> 0.020833333 | E19: =IFERROR(D19*C19," ") -> 0.020833333 | F19: =G18 -> 0.66586806 | G19: 0.6956713 | H19: =IF(G19="","", IF(L19=" ",IF(OR(F19=0,G19=0),"",G19-F19),((G19-F19)-L19))) -> 0.018888889 | I19: =IFERROR(IF(L19=" ",(F19+E19),(F19+E19+L19)),"") -> 0.69761574 | L19: 0.010914352 | N19: =IFERROR(E19/H19," ") -> 1.1029412 | Q19: =IF(SUMIF($A:$A,$P19,$E:$E)=0,"",SUMIF($A:$A,$P19,$E:$E)) | R19: =IF(SUMIF($A:$A,$P19,$H:$H)=0,"",SUMIF($A:$A,$P19,$H:$H)) | S19: =IF(R19=""," ",$U$1-R19) | T19: =IFERROR(AVERAGEIF($A:$A,$P19,$N:$N)," ")
A20: 45813 | B20: WH - Fabric Composition | C20: 15 | D20: =IFERROR(VLOOKUP($B20,Task!$B$1:$G$70,6,0)," ") -> 0.0020833333 | E20: =IFERROR(D20*C20," ") -> 0.03125 | F20: =G19 -> 0.6956713 | G20: 0.72340278 | H20: =IF(G20="","", IF(L20=" ",IF(OR(F20=0,G20=0),"",G20-F20),((G20-F20)-L20))) -> 0.027731481 | I20: =IFERROR(IF(L20=" ",(F20+E20),(F20+E20+L20)),"") -> 0.7269213 | N20: =IFERROR(E20/H20," ") -> 1.1268781 | Q20: =IF(SUMIF($A:$A,$P20,$E:$E)=0,"",SUMIF($A:$A,$P20,$E:$E)) | R20: =IF(SUMIF($A:$A,$P20,$H:$H)=0,"",SUMIF($A:$A,$P20,$H:$H)) | S20: =IF(R20=""," ",$U$1-R20) | T20: =IFERROR(AVERAGEIF($A:$A,$P20,$N:$N)," ")
A21: 45813 | B21: WH - Fabric Composition | C21: 4 | D21: =IFERROR(VLOOKUP($B21,Task!$B$1:$G$70,6,0)," ") -> 0.0020833333 | E21: =IFERROR(D21*C21," ") -> 0.0083333333 | F21: =G20 -> 0.72340278 | G21: 0.74201389 | H21: =IF(G21="","", IF(L21=" ",IF(OR(F21=0,G21=0),"",G21-F21),((G21-F21)-L21))) -> 0.0075462963 | I21: =IFERROR(IF(L21=" ",(F21+E21),(F21+E21+L21)),"") -> 0.74280093 | L21: 0.011064815 | N21: =IFERROR(E21/H21," ") -> 1.1042945 | Q21: =IF(SUMIF($A:$A,$P21,$E:$E)=0,"",SUMIF($A:$A,$P21,$E:$E)) | R21: =IF(SUMIF($A:$A,$P21,$H:$H)=0,"",SUMIF($A:$A,$P21,$H:$H)) | S21: =IF(R21=""," ",$U$1-R21) | T21: =IFERROR(AVERAGEIF($A:$A,$P21,$N:$N)," ")
A22: 45819 | B22: Nordstrom SQL DATA Dump | C22: 1 | D22: =IFERROR(VLOOKUP($B22,Task!$B$1:$G$70,6,0)," ") -> 0.048611111 | E22: =IFERROR(D22*C22," ") -> 0.048611111 | F22: 0.3721875 | G22: 0.41615741 | H22: =IF(G22="","", IF(L22=" ",IF(OR(F22=0,G22=0),"",G22-F22),((G22-F22)-L22))) -> 0.043969907 | I22: =IFERROR(IF(L22=" ",(F22+E22),(F22+E22+L22)),"") -> 0.42079861 | N22: =IFERROR(E22/H22," ") -> 1.1055541 | Q22: =IF(SUMIF($A:$A,$P22,$E:$E)=0,"",SUMIF($A:$A,$P22,$E:$E)) | R22: =IF(SUMIF($A:$A,$P22,$H:$H)=0,"",SUMIF($A:$A,$P22,$H:$H)) | S22: =IF(R22=""," ",$U$1-R22) | T22: =IFERROR(AVERAGEIF($A:$A,$P22,$N:$N)," ")
A23: 45819 | B23: DAM - Image Approval | C23: 24 | D23: =IFERROR(VLOOKUP($B23,Task!$B$1:$G$70,6,0)," ") -> 0.0027777778 | E23: =IFERROR(D23*C23," ") -> 0.066666667 | F23: =G22 -> 0.41615741 | G23: 0.49802083 | H23: =IF(G23="","", IF(L23=" ",IF(OR(F23=0,G23=0),"",G23-F23),((G23-F23)-L23))) -> 0.059872685 | I23: =IFERROR(IF(L23=" ",(F23+E23),(F23+E23+L23)),"") -> 0.50481481 | L23: 0.021990741 | N23: =IFERROR(E23/H23," ") -> 1.1134738 | Q23: =IF(SUMIF($A:$A,$P23,$E:$E)=0,"",SUMIF($A:$A,$P23,$E:$E)) | R23: =IF(SUMIF($A:$A,$P23,$H:$H)=0,"",SUMIF($A:$A,$P23,$H:$H)) | S23: =IF(R23=""," ",$U$1-R23) | T23: =IFERROR(AVERAGEIF($A:$A,$P23,$N:$N)," ")
A24: 45819 | B24: Wholesale Data Enrichment Report | C24: 1 | D24: =IFERROR(VLOOKUP($B24,Task!$B$1:$G$70,6,0)," ") -> 0.020833333 | E24: =IFERROR(D24*C24," ") -> 0.020833333 | F24: =G23 -> 0.49802083 | G24: 0.52861111 | H24: =IF(G24="","", IF(L24=" ",IF(OR(F24=0,G24=0),"",G24-F24),((G24-F24)-L24))) -> 0.019189815 | I24: =IFERROR(IF(L24=" ",(F24+E24),(F24+E24+L24)),"") -> 0.53025463 | L24: 0.011400463 | N24: =IFERROR(E24/H24," ") -> 1.0856454
A25: 45819 | B25: DAM - Image Approval | C25: 22 | D25: =IFERROR(VLOOKUP($B25,Task!$B$1:$G$70,6,0)," ") -> 0.0027777778 | E25: =IFERROR(D25*C25," ") -> 0.061111111 | F25: =G24 -> 0.52861111 | G25: 0.5858912 | H25: =IF(G25="","", IF(L25=" ",IF(OR(F25=0,G25=0),"",G25-F25),((G25-F25)-L25))) -> 0.057280093 | I25: =IFERROR(IF(L25=" ",(F25+E25),(F25+E25+L25)),"") -> 0.58972222 | N25: =IFERROR(E25/H25," ") -> 1.0668822 | P25: C1042
A26: 45819 | B26: DAM - Image Approval | C26: 32 | D26: =IFERROR(VLOOKUP($B26,Task!$B$1:$G$70,6,0)," ") -> 0.0027777778 | E26: =IFERROR(D26*C26," ") -> 0.088888889 | F26: =G25 -> 0.5858912 | G26: 0.68699074 | H26: =IF(G26="","", IF(L26=" ",IF(OR(F26=0,G26=0),"",G26-F26),((G26-F26)-L26))) -> 0.079976852 | I26: =IFERROR(IF(L26=" ",(F26+E26),(F26+E26+L26)),"") -> 0.69590278 | L26: 0.021122685 | N26: =IFERROR(E26/H26," ") -> 1.1114327 | P26: Date | Q26: Core | R26: Break | S26: Other-Idle | T26: Daily Huddle
A27: 45819 | B27: DAM - Image Approval | C27: 6 | D27: =IFERROR(VLOOKUP($B27,Task!$B$1:$G$70,6,0)," ") -> 0.0027777778 | E27: =IFERROR(D27*C27," ") -> 0.016666667 | F27: =G26 -> 0.68699074 | G27: 0.7094213 | H27: =IF(G27="","", IF(L27=" ",IF(OR(F27=0,G27=0),"",G27-F27),((G27-F27)-L27))) -> 0.015439815 | I27: =IFERROR(IF(L27=" ",(F27+E27),(F27+E27+L27)),"") -> 0.71064815 | L27: 0.0069907407 | N27: =IFERROR(E27/H27," ") -> 1.0794603
A28: 45819 | B28: DAM - Image Approval | C28: 16 | D28: =IFERROR(VLOOKUP($B28,Task!$B$1:$G$70,6,0)," ") -> 0.0027777778 | E28: =IFERROR(D28*C28," ") -> 0.044444444 | F28: =G27 -> 0.7094213 | G28: 0.75080432 | H28: =IF(G28="","", IF(L28=" ",IF(OR(F28=0,G28=0),"",G28-F28),((G28-F28)-L28))) -> 0.041383021 | I28: =IFERROR(IF(L28=" ",(F28+E28),(F28+E28+L28)),"") -> 0.75386574 | N28: =IFERROR(E28/H28," ") -> 1.0739778
A29: 45820 | B29: DAM - Image Approval | C29: 18 | D29: =IFERROR(VLOOKUP($B29,Task!$B$1:$G$70,6,0)," ") -> 0.0027777778 | E29: =IFERROR(D29*C29," ") -> 0.05 | F29: 0.3550463 | G29: 0.45251157 | H29: =IF(G29="","", IF(L29=" ",IF(OR(F29=0,G29=0),"",G29-F29),((G29-F29)-L29))) -> 0.045960648 | I29: =IFERROR(IF(L29=" ",(F29+E29),(F29+E29+L29)),"") -> 0.45655093 | L29: 0.05150463 | N29: =IFERROR(E29/H29," ") -> 1.0878872
A30: 45820 | B30: Nordstrom SQL DATA Dump | C30: 1 | D30: =IFERROR(VLOOKUP($B30,Task!$B$1:$G$70,6,0)," ") -> 0.048611111 | E30: =IFERROR(D30*C30," ") -> 0.048611111 | F30: =G29 -> 0.45251157 | G30: 0.52017361 | H30: =IF(G30="","", IF(L30=" ",IF(OR(F30=0,G30=0),"",G30-F30),((G30-F30)-L30))) -> 0.044108796 | I30: =IFERROR(IF(L30=" ",(F30+E30),(F30+E30+L30)),"") -> 0.52467593 | L30: 0.023553241 | N30: =IFERROR(E30/H30," ") -> 1.1020729
A31: 45820 | B31: OGM - Sizing update | C31: 24 | D31: =IFERROR(VLOOKUP($B31,Task!$B$1:$G$70,6,0)," ") -> 0.0055555556 | E31: =IFERROR(D31*C31," ") -> 0.13333333 | F31: =G30 -> 0.52017361 | G31: 0.64217593 | H31: =IF(G31="","", IF(L31=" ",IF(OR(F31=0,G31=0),"",G31-F31),((G31-F31)-L31))) -> 0.12200231 | I31: =IFERROR(IF(L31=" ",(F31+E31),(F31+E31+L31)),"") -> 0.65350694 | N31: =IFERROR(E31/H31," ") -> 1.0928754
A32: 45820 | B32: Nordstrom SQL DATA Dump | C32: 1 | D32: =IFERROR(VLOOKUP($B32,Task!$B$1:$G$70,6,0)," ") -> 0.048611111 | E32: =IFERROR(D32*C32," ") -> 0.048611111 | F32: =G31 -> 0.64217593 | G32: 0.69354167 | H32: =IF(G32="","", IF(L32=" ",IF(OR(F32=0,G32=0),"",G32-F32),((G32-F32)-L32))) -> 0.051365741 | I32: =IFERROR(IF(L32=" ",(F32+E32),(F32+E32+L32)),"") -> 0.69078704 | N32: =IFERROR(E32/H32," ") -> 0.94637224
A33: 45820 | B33: OGM - Sizing update | C33: 5 | D33: =IFERROR(VLOOKUP($B33,Task!$B$1:$G$70,6,0)," ") -> 0.0055555556 | E33: =IFERROR(D33*C33," ") -> 0.027777778 | F33: =G32 -> 0.69354167 | G33: 0.73263889 | H33: =IF(G33="","", IF(L33=" ",IF(OR(F33=0,G33=0),"",G33-F33),((G33-F33)-L33))) -> 0.022037037 | I33: =IFERROR(IF(L33=" ",(F33+E33),(F33+E33+L33)),"") -> 0.73837963 | L33: 0.017060185 | N33: =IFERROR(E33/H33," ") -> 1.2605042
A34: 45821 | B34: Nordstrom SQL DATA Dump | C34: 1 | D34: =IFERROR(VLOOKUP($B34,Task!$B$1:$G$70,6,0)," ") -> 0.048611111 | E34: =IFERROR(D34*C34," ") -> 0.048611111 | F34: 0.3759375 | G34: 0.45972222 | H34: =IF(G34="","", IF(L34=" ",IF(OR(F34=0,G34=0),"",G34-F34),((G34-F34)-L34))) -> 0.043761574 | I34: =IFERROR(IF(L34=" ",(F34+E34),(F34+E34+L34)),"") -> 0.46457176 | L34: 0.040023148 | N34: =IFERROR(E34/H34," ") -> 1.1108172
A35: 45821 | B35: Nordstrom SQL DATA Dump | C35: 1 | D35: =IFERROR(VLOOKUP($B35,Task!$B$1:$G$70,6,0)," ") -> 0.048611111 | E35: =IFERROR(D35*C35," ") -> 0.048611111 | F35: =G34 -> 0.45972222 | G35: 0.5034375 | H35: =IF(G35="","", IF(L35=" ",IF(OR(F35=0,G35=0),"",G35-F35),((G35-F35)-L35))) -> 0.043715278 | I35: =IFERROR(IF(L35=" ",(F35+E35),(F35+E35+L35)),"") -> 0.50833333 | N35: =IFERROR(E35/H35," ") -> 1.1119936
A36: 45821 | B36: Wholesale Data Enrichment Report | C36: 2 | D36: =IFERROR(VLOOKUP($B36,Task!$B$1:$G$70,6,0)," ") -> 0.020833333 | E36: =IFERROR(D36*C36," ") -> 0.041666667 | F36: =G35 -> 0.5034375 | G36: 0.54351852 | H36: =IF(G36="","", IF(L36=" ",IF(OR(F36=0,G36=0),"",G36-F36),((G36-F36)-L36))) -> 0.040081019 | I36: =IFERROR(IF(L36=" ",(F36+E36),(F36+E36+L36)),"") -> 0.54510417 | N36: =IFERROR(E36/H36," ") -> 1.0395611
A37: 45821 | B37: OGM - Sizing update | C37: 17 | D37: =IFERROR(VLOOKUP($B37,Task!$B$1:$G$70,6,0)," ") -> 0.0055555556 | E37: =IFERROR(D37*C37," ") -> 0.094444444 | F37: =G36 -> 0.54351852 | G37: 0.65164352 | H37: =IF(G37="","", IF(L37=" ",IF(OR(F37=0,G37=0),"",G37-F37),((G37-F37)-L37))) -> 0.085185185 | I37: =IFERROR(IF(L37=" ",(F37+E37),(F37+E37+L37)),"") -> 0.66090278 | L37: 0.022939815 | N37: =IFERROR(E37/H37," ") -> 1.1086957
A38: 45821 | B38: DAM - Image Approval | C38: 20 | D38: =IFERROR(VLOOKUP($B38,Task!$B$1:$G$70,6,0)," ") -> 0.0027777778 | E38: =IFERROR(D38*C38," ") -> 0.055555556 | F38: =G37 -> 0.65164352 | G38: 0.70184028 | H38: =IF(G38="","", IF(L38=" ",IF(OR(F38=0,G38=0),"",G38-F38),((G38-F38)-L38))) -> 0.050196759 | I38: =IFERROR(IF(L38=" ",(F38+E38),(F38+E38+L38)),"") -> 0.70719907 | N38: =IFERROR(E38/H38," ") -> 1.1067558
A39: 45821 | B39: OGM - Sizing update | C39: 10 | D39: =IFERROR(VLOOKUP($B39,Task!$B$1:$G$70,6,0)," ") -> 0.0055555556 | E39: =IFERROR(D39*C39," ") -> 0.055555556 | F39: =G38 -> 0.70184028 | G39: 0.75347222 | H39: =IF(G39="","", IF(L39=" ",IF(OR(F39=0,G39=0),"",G39-F39),((G39-F39)-L39))) -> 0.051631944 | I39: =IFERROR(IF(L39=" ",(F39+E39),(F39+E39+L39)),"") -> 0.75739583 | N39: =IFERROR(E39/H39," ") -> 1.0759919
A40: 45824 | B40: OGM - Sizing update | C40: =12-C39 -> 2 | D40: =IFERROR(VLOOKUP($B40,Task!$B$1:$G$70,6,0)," ") -> 0.0055555556 | E40: =IFERROR(D40*C40," ") -> 0.011111111 | F40: 0.39108796 | G40: 0.40119213 | H40: =IF(G40="","", IF(L40=" ",IF(OR(F40=0,G40=0),"",G40-F40),((G40-F40)-L40))) -> 0.010104167 | I40: =IFERROR(IF(L40=" ",(F40+E40),(F40+E40+L40)),"") -> 0.40219907 | N40: =IFERROR(E40/H40," ") -> 1.0996564 | P40: IF(RIGHT(N3,2)="DB","-"&N3,N3)
A41: 45824 | B41: Wholesale Data Enrichment Report | C41: 1 | D41: =IFERROR(VLOOKUP($B41,Task!$B$1:$G$70,6,0)," ") -> 0.020833333 | E41: =IFERROR(D41*C41," ") -> 0.020833333 | F41: =G40 -> 0.40119213 | G41: 0.43659722 | H41: =IF(G41="","", IF(L41=" ",IF(OR(F41=0,G41=0),"",G41-F41),((G41-F41)-L41))) -> 0.018946759 | I41: =IFERROR(IF(L41=" ",(F41+E41),(F41+E41+L41)),"") -> 0.4384838 | L41: 0.016458333 | N41: =IFERROR(E41/H41," ") -> 1.0995724
A42: 45824 | B42: Nordstrom SQL DATA Dump | C42: 1 | D42: =IFERROR(VLOOKUP($B42,Task!$B$1:$G$70,6,0)," ") -> 0.048611111 | E42: =IFERROR(D42*C42," ") -> 0.048611111 | F42: =G41 -> 0.43659722 | G42: 0.50019676 | H42: =IF(G42="","", IF(L42=" ",IF(OR(F42=0,G42=0),"",G42-F42),((G42-F42)-L42))) -> 0.043761574 | I42: =IFERROR(IF(L42=" ",(F42+E42),(F42+E42+L42)),"") -> 0.5050463 | L42: 0.019837963 | N42: =IFERROR(E42/H42," ") -> 1.1108172
A43: 45824 | B43: DAM - Image Approval | C43: 38 | D43: =IFERROR(VLOOKUP($B43,Task!$B$1:$G$70,6,0)," ") -> 0.0027777778 | E43: =IFERROR(D43*C43," ") -> 0.10555556 | F43: =G42 -> 0.50019676 | G43: 0.59619213 | H43: =IF(G43="","", IF(L43=" ",IF(OR(F43=0,G43=0),"",G43-F43),((G43-F43)-L43))) -> 0.09599537 | I43: =IFERROR(IF(L43=" ",(F43+E43),(F43+E43+L43)),"") -> 0.60575231 | N43: =IFERROR(E43/H43," ") -> 1.0995901
A44: 45824 | B44: DAM - Image Approval | C44: =64-C43 -> 26 | D44: =IFERROR(VLOOKUP($B44,Task!$B$1:$G$70,6,0)," ") -> 0.0027777778 | E44: =IFERROR(D44*C44," ") -> 0.072222222 | F44: =G43 -> 0.59619213 | G44: 0.67327546 | H44: =IF(G44="","", IF(L44=" ",IF(OR(F44=0,G44=0),"",G44-F44),((G44-F44)-L44))) -> 0.065636574 | I44: =IFERROR(IF(L44=" ",(F44+E44),(F44+E44+L44)),"") -> 0.67986111 | L44: 0.011446759 | N44: =IFERROR(E44/H44," ") -> 1.100335
A45: 45824 | B45: Very Invoice Report | C45: 1 | D45: =IFERROR(VLOOKUP($B45,Task!$B$1:$G$70,6,0)," ") -> 0.020833333 | E45: =IFERROR(D45*C45," ") -> 0.020833333 | F45: =G44 -> 0.67327546 | G45: 0.71643519 | H45: =IF(G45="","", IF(L45=" ",IF(OR(F45=0,G45=0),"",G45-F45),((G45-F45)-L45))) -> 0.019097222 | I45: =IFERROR(IF(L45=" ",(F45+E45),(F45+E45+L45)),"") -> 0.7181713 | L45: 0.0240625 | N45: =IFERROR(E45/H45," ") -> 1.0909091
A46: 45824 | B46: Wholesale Adding Images | C46: 26 | D46: =IFERROR(VLOOKUP($B46,Task!$B$1:$G$70,6,0)," ") -> 0.0013888889 | E46: =IFERROR(D46*C46," ") -> 0.036111111 | F46: =G45 -> 0.71643519 | G46: 0.75002315 | H46: =IF(G46="","", IF(L46=" ",IF(OR(F46=0,G46=0),"",G46-F46),((G46-F46)-L46))) -> 0.033587963 | I46: =IFERROR(IF(L46=" ",(F46+E46),(F46+E46+L46)),"") -> 0.7525463 | N46: =IFERROR(E46/H46," ") -> 1.0751206
A47: 45824 | B47: Wholesale Adding Images | C47: 15 | D47: =IFERROR(VLOOKUP($B47,Task!$B$1:$G$70,6,0)," ") -> 0.0013888889 | E47: =IFERROR(D47*C47," ") -> 0.020833333 | F47: =G46 -> 0.75002315 | G47: 0.76875 | H47: =IF(G47="","", IF(L47=" ",IF(OR(F47=0,G47=0),"",G47-F47),((G47-F47)-L47))) -> 0.018726852 | I47: =IFERROR(IF(L47=" ",(F47+E47),(F47+E47+L47)),"") -> 0.77085648 | N47: =IFERROR(E47/H47," ") -> 1.1124845
A48: 45825 | B48: Wholesale Adding Images | C48: 51 | D48: =IFERROR(VLOOKUP($B48,Task!$B$1:$G$70,6,0)," ") -> 0.0013888889 | E48: =IFERROR(D48*C48," ") -> 0.070833333 | F48: 0.3787037 | G48: 0.44299769 | H48: =IF(G48="","", IF(L48=" ",IF(OR(F48=0,G48=0),"",G48-F48),((G48-F48)-L48))) -> 0.064293981 | I48: =IFERROR(IF(L48=" ",(F48+E48),(F48+E48+L48)),"") -> 0.44953704 | N48: =IFERROR(E48/H48," ") -> 1.1017102
A49: 45825 | B49: Nordstrom SQL DATA Dump | C49: 1 | D49: =IFERROR(VLOOKUP($B49,Task!$B$1:$G$70,6,0)," ") -> 0.048611111 | E49: =IFERROR(D49*C49," ") -> 0.048611111 | F49: =G48 -> 0.44299769 | G49: 0.51443287 | H49: =IF(G49="","", IF(L49=" ",IF(OR(F49=0,G49=0),"",G49-F49),((G49-F49)-L49))) -> 0.043449074 | I49: =IFERROR(IF(L49=" ",(F49+E49),(F49+E49+L49)),"") -> 0.51959491 | L49: 0.027986111 | N49: =IFERROR(E49/H49," ") -> 1.1188066
A50: 45825 | B50: OGM - Sizing update | C50: 20 | D50: =IFERROR(VLOOKUP($B50,Task!$B$1:$G$70,6,0)," ") -> 0.0055555556 | E50: =IFERROR(D50*C50," ") -> 0.11111111 | F50: =G49 -> 0.51443287 | G50: 0.65295139 | H50: =IF(G50="","", IF(L50=" ",IF(OR(F50=0,G50=0),"",G50-F50),((G50-F50)-L50))) -> 0.10099537 | I50: =IFERROR(IF(L50=" ",(F50+E50),(F50+E50+L50)),"") -> 0.66306713 | L50: 0.037523148 | N50: =IFERROR(E50/H50," ") -> 1.1001604
A51: 45825 | B51: Nordstrom SQL DATA Dump | C51: 1 | D51: =IFERROR(VLOOKUP($B51,Task!$B$1:$G$70,6,0)," ") -> 0.048611111 | E51: =IFERROR(D51*C51," ") -> 0.048611111 | F51: =G50 -> 0.65295139 | G51: 0.71128472 | H51: =IF(G51="","", IF(L51=" ",IF(OR(F51=0,G51=0),"",G51-F51),((G51-F51)-L51))) -> 0.044166667 | I51: =IFERROR(IF(L51=" ",(F51+E51),(F51+E51+L51)),"") -> 0.71572917 | L51: 0.014166667 | N51: =IFERROR(E51/H51," ") -> 1.1006289
A52: 45825 | B52: Wholesale Adding Images | C52: 36 | D52: =IFERROR(VLOOKUP($B52,Task!$B$1:$G$70,6,0)," ") -> 0.0013888889 | E52: =IFERROR(D52*C52," ") -> 0.05 | F52: =G51 -> 0.71128472 | G52: 0.75694444 | H52: =IF(G52="","", IF(L52=" ",IF(OR(F52=0,G52=0),"",G52-F52),((G52-F52)-L52))) -> 0.045659722 | I52: =IFERROR(IF(L52=" ",(F52+E52),(F52+E52+L52)),"") -> 0.76128472 | N52: =IFERROR(E52/H52," ") -> 1.095057
A53: 45827 | B53: Nordstrom SQL DATA Dump | C53: 1 | D53: =IFERROR(VLOOKUP($B53,Task!$B$1:$G$70,6,0)," ") -> 0.048611111 | E53: =IFERROR(D53*C53," ") -> 0.048611111 | F53: 0.36989583 | G53: 0.41365741 | H53: =IF(G53="","", IF(L53=" ",IF(OR(F53=0,G53=0),"",G53-F53),((G53-F53)-L53))) -> 0.043761574 | I53: =IFERROR(IF(L53=" ",(F53+E53),(F53+E53+L53)),"") -> 0.41850694 | N53: =IFERROR(E53/H53," ") -> 1.1108172
A54: 45827 | B54: Wholesale Adding Images | C54: 115 | D54: =IFERROR(VLOOKUP($B54,Task!$B$1:$G$70,6,0)," ") -> 0.0013888889 | E54: =IFERROR(D54*C54," ") -> 0.15972222 | F54: =G53 -> 0.41365741 | G54: 0.61484954 | H54: =IF(G54="","", IF(L54=" ",IF(OR(F54=0,G54=0),"",G54-F54),((G54-F54)-L54))) -> 0.14520833 | I54: =IFERROR(IF(L54=" ",(F54+E54),(F54+E54+L54)),"") -> 0.62936343 | L54: 0.055983796 | N54: =IFERROR(E54/H54," ") -> 1.0999522
A55: 45827 | B55: Wholesale Data Enrichment Report | C55: 1 | D55: =IFERROR(VLOOKUP($B55,Task!$B$1:$G$70,6,0)," ") -> 0.020833333 | E55: =IFERROR(D55*C55," ") -> 0.020833333 | F55: =G54 -> 0.61484954 | G55: 0.63378257 | H55: =IF(G55="","", IF(L55=" ",IF(OR(F55=0,G55=0),"",G55-F55),((G55-F55)-L55))) -> 0.018933032 | I55: =IFERROR(IF(L55=" ",(F55+E55),(F55+E55+L55)),"") -> 0.63568287 | N55: =IFERROR(E55/H55," ") -> 1.1003696
A56: 45827 | B56: Adhoc Task | C56: 15 | D56: =IFERROR(VLOOKUP($B56,Task!$B$1:$G$70,6,0)," ") -> 0.0013888889 | E56: =IFERROR(D56*C56," ") -> 0.020833333 | F56: =G55 -> 0.63378257 | G56: 0.6530787 | H56: =IF(G56="","", IF(L56=" ",IF(OR(F56=0,G56=0),"",G56-F56),((G56-F56)-L56))) -> 0.019296134 | I56: =IFERROR(IF(L56=" ",(F56+E56),(F56+E56+L56)),"") -> 0.6546159 | N56: =IFERROR(E56/H56," ") -> 1.0796636
A57: 45827 | B57: WH - Wash Care update | C57: 23 | D57: =IFERROR(VLOOKUP($B57,Task!$B$1:$G$70,6,0)," ") -> 0.0020833333 | E57: =IFERROR(D57*C57," ") -> 0.047916667 | F57: =G56 -> 0.6530787 | G57: 0.70155093 | H57: =IF(G57="","", IF(L57=" ",IF(OR(F57=0,G57=0),"",G57-F57),((G57-F57)-L57))) -> 0.044502315 | I57: =IFERROR(IF(L57=" ",(F57+E57),(F57+E57+L57)),"") -> 0.70496528 | L57: 0.0039699074 | N57: =IFERROR(E57/H57," ") -> 1.076723
A58: 45827 | B58: WH - Wash Care update | C58: 14 | D58: =IFERROR(VLOOKUP($B58,Task!$B$1:$G$70,6,0)," ") -> 0.0020833333 | E58: =IFERROR(D58*C58," ") -> 0.029166667 | F58: =G57 -> 0.70155093 | G58: 0.72763889 | H58: =IF(G58="","", IF(L58=" ",IF(OR(F58=0,G58=0),"",G58-F58),((G58-F58)-L58))) -> 0.026087963 | I58: =IFERROR(IF(L58=" ",(F58+E58),(F58+E58+L58)),"") -> 0.73071759 | N58: =IFERROR(E58/H58," ") -> 1.1180124
A59: 45827 | B59: WH - Wash Care update | C59: 11 | D59: =IFERROR(VLOOKUP($B59,Task!$B$1:$G$70,6,0)," ") -> 0.0020833333 | E59: =IFERROR(D59*C59," ") -> 0.022916667 | F59: =G58 -> 0.72763889 | G59: 0.75 | H59: =IF(G59="","", IF(L59=" ",IF(OR(F59=0,G59=0),"",G59-F59),((G59-F59)-L59))) -> 0.022361111 | I59: =IFERROR(IF(L59=" ",(F59+E59),(F59+E59+L59)),"") -> 0.75055556 | N59: =IFERROR(E59/H59," ") -> 1.0248447
A60: 45828 | B60: Nordstrom SQL DATA Dump | C60: 1 | D60: =IFERROR(VLOOKUP($B60,Task!$B$1:$G$70,6,0)," ") -> 0.048611111 | E60: =IFERROR(D60*C60," ") -> 0.048611111 | F60: 0.38001157 | G60: 0.47233796 | H60: =IF(G60="","", IF(L60=" ",IF(OR(F60=0,G60=0),"",G60-F60),((G60-F60)-L60))) -> 0.044178241 | I60: =IFERROR(IF(L60=" ",(F60+E60),(F60+E60+L60)),"") -> 0.47677083 | L60: 0.048148148 | N60: =IFERROR(E60/H60," ") -> 1.1003406 | P60: 0.56751157
A61: 45828 | B61: Nordstrom SQL DATA Dump | C61: 1 | D61: =IFERROR(VLOOKUP($B61,Task!$B$1:$G$70,6,0)," ") -> 0.048611111 | E61: =IFERROR(D61*C61," ") -> 0.048611111 | F61: =G60 -> 0.47233796 | G61: 0.51652778 | H61: =IF(G61="","", IF(L61=" ",IF(OR(F61=0,G61=0),"",G61-F61),((G61-F61)-L61))) -> 0.044189815 | I61: =IFERROR(IF(L61=" ",(F61+E61),(F61+E61+L61)),"") -> 0.52094907 | N61: =IFERROR(E61/H61," ") -> 1.1000524 | P61: 0.86597222
A62: 45828 | B62: Wholesale Data Enrichment Report | C62: 1 | D62: =IFERROR(VLOOKUP($B62,Task!$B$1:$G$70,6,0)," ") -> 0.020833333 | E62: =IFERROR(D62*C62," ") -> 0.020833333 | F62: =G61 -> 0.51652778 | G62: 0.53546296 | H62: =IF(G62="","", IF(L62=" ",IF(OR(F62=0,G62=0),"",G62-F62),((G62-F62)-L62))) -> 0.018935185 | I62: =IFERROR(IF(L62=" ",(F62+E62),(F62+E62+L62)),"") -> 0.53736111 | N62: =IFERROR(E62/H62," ") -> 1.1002445 | P62: =P61-P60 -> 0.29846065
A63: 45828 | B63: WH - Wash Care update | C63: 31 | D63: =IFERROR(VLOOKUP($B63,Task!$B$1:$G$70,6,0)," ") -> 0.0020833333 | E63: =IFERROR(D63*C63," ") -> 0.064583333 | F63: =G62 -> 0.53546296 | G63: 0.59415509 | H63: =IF(G63="","", IF(L63=" ",IF(OR(F63=0,G63=0),"",G63-F63),((G63-F63)-L63))) -> 0.05869213 | I63: =IFERROR(IF(L63=" ",(F63+E63),(F63+E63+L63)),"") -> 0.6000463 | N63: =IFERROR(E63/H63," ") -> 1.1003747 | P63: 0.048148148
A64: 45828 | B64: WH - Wash Care update | C64: 43 | D64: =IFERROR(VLOOKUP($B64,Task!$B$1:$G$70,6,0)," ") -> 0.0020833333 | E64: =IFERROR(D64*C64," ") -> 0.089583333 | F64: =G63 -> 0.59415509 | G64: 0.67847222 | H64: =IF(G64="","", IF(L64=" ",IF(OR(F64=0,G64=0),"",G64-F64),((G64-F64)-L64))) -> 0.08431713 | I64: =IFERROR(IF(L64=" ",(F64+E64),(F64+E64+L64)),"") -> 0.68373843 | N64: =IFERROR(E64/H64," ") -> 1.0624571 | P64: =P62-P63 -> 0.2503125
A65: 45831 | B65: SQL Data Dump | C65: 2 | D65: =IFERROR(VLOOKUP($B65,Task!$B$1:$G$70,6,0)," ") -> 0.048611111 | E65: =IFERROR(D65*C65," ") -> 0.097222222 | F65: 0.37700231 | G65: 0.49173611 | H65: =IF(G65="","", IF(L65=" ",IF(OR(F65=0,G65=0),"",G65-F65),((G65-F65)-L65))) -> 0.088518519 | I65: =IFERROR(IF(L65=" ",(F65+E65),(F65+E65+L65)),"") -> 0.50043981 | L65: 0.026215278 | N65: =IFERROR(E65/H65," ") -> 1.0983264
A66: 45831 | B66: WH - Wash Care update | C66: 53 | D66: =IFERROR(VLOOKUP($B66,Task!$B$1:$G$70,6,0)," ") -> 0.0020833333 | E66: =IFERROR(D66*C66," ") -> 0.11041667 | F66: =G65 -> 0.49173611 | G66: 0.59179398 | H66: =IF(G66="","", IF(L66=" ",IF(OR(F66=0,G66=0),"",G66-F66),((G66-F66)-L66))) -> 0.10005787 | I66: =IFERROR(IF(L66=" ",(F66+E66),(F66+E66+L66)),"") -> 0.60215278 | N66: =IFERROR(E66/H66," ") -> 1.1035281
A67: 45831 | B67: DAM - Image Approval | C67: 20 | D67: =IFERROR(VLOOKUP($B67,Task!$B$1:$G$70,6,0)," ") -> 0.0027777778 | E67: =IFERROR(D67*C67," ") -> 0.055555556 | F67: =G66 -> 0.59179398 | G67: 0.64725694 | H67: =IF(G67="","", IF(L67=" ",IF(OR(F67=0,G67=0),"",G67-F67),((G67-F67)-L67))) -> 0.050497685 | I67: =IFERROR(IF(L67=" ",(F67+E67),(F67+E67+L67)),"") -> 0.65231481 | L67: 0.0049652778 | N67: =IFERROR(E67/H67," ") -> 1.1001604
A68: 45831 | B68: DAM - Image Approval | C68: 30 | D68: =IFERROR(VLOOKUP($B68,Task!$B$1:$G$70,6,0)," ") -> 0.0027777778 | E68: =IFERROR(D68*C68," ") -> 0.083333333 | F68: =G67 -> 0.64725694 | G68: 0.73658565 | H68: =IF(G68="","", IF(L68=" ",IF(OR(F68=0,G68=0),"",G68-F68),((G68-F68)-L68))) -> 0.074386574 | I68: =IFERROR(IF(L68=" ",(F68+E68),(F68+E68+L68)),"") -> 0.74553241 | L68: 0.01494213 | N68: =IFERROR(E68/H68," ") -> 1.1202738
A69: 45831 | B69: DAM - Image Approval | C69: 9 | D69: =IFERROR(VLOOKUP($B69,Task!$B$1:$G$70,6,0)," ") -> 0.0027777778 | E69: =IFERROR(D69*C69," ") -> 0.025 | F69: =G68 -> 0.73658565 | G69: 0.75842476 | H69: =IF(G69="","", IF(L69=" ",IF(OR(F69=0,G69=0),"",G69-F69),((G69-F69)-L69))) -> 0.021839109 | I69: =IFERROR(IF(L69=" ",(F69+E69),(F69+E69+L69)),"") -> 0.76158565 | N69: =IFERROR(E69/H69," ") -> 1.1447354
A70: 45832 | B70: Nordstrom SQL DATA Dump | C70: 1 | D70: =IFERROR(VLOOKUP($B70,Task!$B$1:$G$70,6,0)," ") -> 0.048611111 | E70: =IFERROR(D70*C70," ") -> 0.048611111 | F70: 0.38777778 | G70: 0.43108796 | H70: =IF(G70="","", IF(L70=" ",IF(OR(F70=0,G70=0),"",G70-F70),((G70-F70)-L70))) -> 0.043310185 | I70: =IFERROR(IF(L70=" ",(F70+E70),(F70+E70+L70)),"") -> 0.43638889 | N70: =IFERROR(E70/H70," ") -> 1.1223944
A71: 45832 | B71: Very Invoice Report | C71: 2 | D71: =IFERROR(VLOOKUP($B71,Task!$B$1:$G$70,6,0)," ") -> 0.020833333 | E71: =IFERROR(D71*C71," ") -> 0.041666667 | F71: 0.44157407 | G71: 0.5315625 | H71: =IF(G71="","", IF(L71=" ",IF(OR(F71=0,G71=0),"",G71-F71),((G71-F71)-L71))) -> 0.032881944 | I71: =IFERROR(IF(L71=" ",(F71+E71),(F71+E71+L71)),"") -> 0.54034722 | L71: 0.057106481 | N71: =IFERROR(E71/H71," ") -> 1.2671595
A72: 45832 | B72: Weekly Catchup - 30 | C72: 1 | D72: =IFERROR(VLOOKUP($B72,Task!$B$1:$G$70,6,0)," ") -> 0.020833333 | E72: =IFERROR(D72*C72," ") -> 0.020833333 | F72: 0.50221065 | G72: 0.51981481 | H72: =IF(G72="","", IF(L72=" ",IF(OR(F72=0,G72=0),"",G72-F72),((G72-F72)-L72))) -> 0.017604167 | I72: =IFERROR(IF(L72=" ",(F72+E72),(F72+E72+L72)),"") -> 0.52304398 | N72: =IFERROR(E72/H72," ") -> 1.183432
A73: 45832 | B73: Nordstrom SQL DATA Dump | C73: 3 | D73: =IFERROR(VLOOKUP($B73,Task!$B$1:$G$70,6,0)," ") -> 0.048611111 | E73: =IFERROR(D73*C73," ") -> 0.14583333 | F73: 0.54422454 | H73: =IF(G73="","", IF(L73=" ",IF(OR(F73=0,G73=0),"",G73-F73),((G73-F73)-L73))) | I73: =IFERROR(IF(L73=" ",(F73+E73),(F73+E73+L73)),"") -> 0.69005787 | N73: =IFERROR(E73/H73," ")
D74: =IFERROR(VLOOKUP($B74,Task!$B$1:$G$70,6,0)," ") | E74: =IFERROR(D74*C74," ") | H74: =IF(G74="","", IF(L74=" ",IF(OR(F74=0,G74=0),"",G74-F74),((G74-F74)-L74))) | I74: =IFERROR(IF(L74=" ",(F74+E74),(F74+E74+L74)),"") | N74: =IFERROR(E74/H74," ")
D75: =IFERROR(VLOOKUP($B75,Task!$B$1:$G$70,6,0)," ") | E75: =IFERROR(D75*C75," ") | H75: =IF(G75="","", IF(L75=" ",IF(OR(F75=0,G75=0),"",G75-F75),((G75-F75)-L75))) | I75: =IFERROR(IF(L75=" ",(F75+E75),(F75+E75+L75)),"") | N75: =IFERROR(E75/H75," ")
D76: =IFERROR(VLOOKUP($B76,Task!$B$1:$G$70,6,0)," ") | E76: =IFERROR(D76*C76," ") | H76: =IF(G76="","", IF(L76=" ",IF(OR(F76=0,G76=0),"",G76-F76),((G76-F76)-L76))) | I76: =IFERROR(IF(L76=" ",(F76+E76),(F76+E76+L76)),"") | N76: =IFERROR(E76/H76," ")
D77: =IFERROR(VLOOKUP($B77,Task!$B$1:$G$70,6,0)," ") | E77: =IFERROR(D77*C77," ") | H77: =IF(G77="","", IF(L77=" ",IF(OR(F77=0,G77=0),"",G77-F77),((G77-F77)-L77))) | I77: =IFERROR(IF(L77=" ",(F77+E77),(F77+E77+L77)),"") | N77: =IFERROR(E77/H77," ")
D78: =IFERROR(VLOOKUP($B78,Task!$B$1:$G$70,6,0)," ") | E78: =IFERROR(D78*C78," ") | H78: =IF(G78="","", IF(L78=" ",IF(OR(F78=0,G78=0),"",G78-F78),((G78-F78)-L78))) | I78: =IFERROR(IF(L78=" ",(F78+E78),(F78+E78+L78)),"") | N78: =IFERROR(E78/H78," ")
D79: =IFERROR(VLOOKUP($B79,Task!$B$1:$G$70,6,0)," ") | E79: =IFERROR(D79*C79," ") | H79: =IF(G79="","", IF(L79=" ",IF(OR(F79=0,G79=0),"",G79-F79),((G79-F79)-L79))) | I79: =IFERROR(IF(L79=" ",(F79+E79),(F79+E79+L79)),"") | N79: =IFERROR(E79/H79," ") | O79: =AVERAGEIF(A:A,TODAY(),N:N) -> 1.1909953
D80: =IFERROR(VLOOKUP($B80,Task!$B$1:$G$70,6,0)," ") | E80: =IFERROR(D80*C80," ") | H80: =IF(G80="","", IF(L80=" ",IF(OR(F80=0,G80=0),"",G80-F80),((G80-F80)-L80))) | I80: =IFERROR(IF(L80=" ",(F80+E80),(F80+E80+L80)),"") | N80: =IFERROR(E80/H80," ")
D81: =IFERROR(VLOOKUP($B81,Task!$B$1:$G$70,6,0)," ") | E81: =IFERROR(D81*C81," ") | H81: =IF(G81="","", IF(L81=" ",IF(OR(F81=0,G81=0),"",G81-F81),((G81-F81)-L81))) | I81: =IFERROR(IF(L81=" ",(F81+E81),(F81+E81+L81)),"") | N81: =IFERROR(E81/H81," ")
D82: =IFERROR(VLOOKUP($B82,Task!$B$1:$G$70,6,0)," ") | E82: =IFERROR(D82*C82," ") | H82: =IF(G82="","", IF(L82=" ",IF(OR(F82=0,G82=0),"",G82-F82),((G82-F82)-L82))) | I82: =IFERROR(IF(L82=" ",(F82+E82),(F82+E82+L82)),"") | N82: =IFERROR(E82/H82," ")
D83: =IFERROR(VLOOKUP($B83,Task!$B$1:$G$70,6,0)," ") | E83: =IFERROR(D83*C83," ") | H83: =IF(G83="","", IF(L83=" ",IF(OR(F83=0,G83=0),"",G83-F83),((G83-F83)-L83))) | I83: =IFERROR(IF(L83=" ",(F83+E83),(F83+E83+L83)),"") | N83: =IFERROR(E83/H83," ")
D84: =IFERROR(VLOOKUP($B84,Task!$B$1:$G$70,6,0)," ") | E84: =IFERROR(D84*C84," ") | H84: =IF(G84="","", IF(L84=" ",IF(OR(F84=0,G84=0),"",G84-F84),((G84-F84)-L84))) | I84: =IFERROR(IF(L84=" ",(F84+E84),(F84+E84+L84)),"") | N84: =IFERROR(E84/H84," ")
D85: =IFERROR(VLOOKUP($B85,Task!$B$1:$G$70,6,0)," ") | E85: =IFERROR(D85*C85," ") | H85: =IF(G85="","", IF(L85=" ",IF(OR(F85=0,G85=0),"",G85-F85),((G85-F85)-L85))) | I85: =IFERROR(IF(L85=" ",(F85+E85),(F85+E85+L85)),"") | N85: =IFERROR(E85/H85," ")
D86: =IFERROR(VLOOKUP($B86,Task!$B$1:$G$70,6,0)," ") | E86: =IFERROR(D86*C86," ") | H86: =IF(G86="","", IF(L86=" ",IF(OR(F86=0,G86=0),"",G86-F86),((G86-F86)-L86))) | I86: =IFERROR(IF(L86=" ",(F86+E86),(F86+E86+L86)),"") | N86: =IFERROR(E86/H86," ")
D87: =IFERROR(VLOOKUP($B87,Task!$B$1:$G$70,6,0)," ") | E87: =IFERROR(D87*C87," ") | H87: =IF(G87="","", IF(L87=" ",IF(OR(F87=0,G87=0),"",G87-F87),((G87-F87)-L87))) | I87: =IFERROR(IF(L87=" ",(F87+E87),(F87+E87+L87)),"") | N87: =IFERROR(E87/H87," ")
D88: =IFERROR(VLOOKUP($B88,Task!$B$1:$G$70,6,0)," ") | E88: =IFERROR(D88*C88," ") | H88: =IF(G88="","", IF(L88=" ",IF(OR(F88=0,G88=0),"",G88-F88),((G88-F88)-L88))) | I88: =IFERROR(IF(L88=" ",(F88+E88),(F88+E88+L88)),"") | N88: =IFERROR(E88/H88," ")
D89: =IFERROR(VLOOKUP($B89,Task!$B$1:$G$70,6,0)," ") | E89: =IFERROR(D89*C89," ") | H89: =IF(G89="","", IF(L89=" ",IF(OR(F89=0,G89=0),"",G89-F89),((G89-F89)-L89))) | I89: =IFERROR(IF(L89=" ",(F89+E89),(F89+E89+L89)),"") | N89: =IFERROR(E89/H89," ")
D90: =IFERROR(VLOOKUP($B90,Task!$B$1:$G$70,6,0)," ") | E90: =IFERROR(D90*C90," ") | H90: =IF(G90="","", IF(L90=" ",IF(OR(F90=0,G90=0),"",G90-F90),((G90-F90)-L90))) | I90: =IFERROR(IF(L90=" ",(F90+E90),(F90+E90+L90)),"") | N90: =IFERROR(E90/H90," ")
D91: =IFERROR(VLOOKUP($B91,Task!$B$1:$G$70,6,0)," ") | E91: =IFERROR(D91*C91," ") | H91: =IF(G91="","", IF(L91=" ",IF(OR(F91=0,G91=0),"",G91-F91),((G91-F91)-L91))) | I91: =IFERROR(IF(L91=" ",(F91+E91),(F91+E91+L91)),"") | N91: =IFERROR(E91/H91," ")
... D206: =IFERROR(VLOOKUP($B206,Task!$B$1:$G$70,6,0)," ") | E206: =IFERROR(D206*C206," ") | H206: =IF(G206="","", IF(L206=" ",IF(OR(F206=0,G206=0),"",G206-F206),((G206-F206)-L206))) | I206: =IFERROR(IF(L206=" ",(F206+E206),(F206+E206+L206)),"") | N206: =IFERROR(E206/H206," ")
W992: LIMA - #Lipsy123
W993: r7pIdldl

Sheet May 25
A1: Date | B1: Task Name | C1: Quantity | D1: RE | E1: Total RE | F1: Start Time | G1: End Time | H1: Actual Time taken | I1: Actual End Time | J1: Break Start Time | K1: Break End Time | L1: Total Break time | M1: Comment | N1: Productivity | O1: 0.1875 | P1: Date | Q1: Total RE | R1: Core | S1: Non-Core | T1: Productivity | U1: 0.33333333
A2: 45783 | B2: Missing information | C2: 12 | D2: =IFERROR(VLOOKUP($B2,Task!$B$1:$G$70,6,0)," ") -> 0.0083333333 | E2: =IFERROR(D2*C2," ") -> 0.1 | F2: 0.32368056 | G2: 0.41458333 | H2: =IF(G2="","", IF(L2=" ",IF(OR(F2=0,G2=0),"",G2-F2),((G2-F2)-L2))) -> 0.090902778 | I2: =IFERROR(IF(L2=" ",(F2+E2),(F2+E2+L2)),"") -> 0.42368056 | N2: =IFERROR(E2/H2," ") -> 1.1000764 | O2: 0.86133102 | P2: =IFERROR(__xludf.DUMMYFUNCTION("UNIQUE($A$2:$A$993)"),45783) -> 45783 | Q2: =SUMIF($A:$A,$P2,$E:$E) -> 0.31875 | R2: =SUMIF($A:$A,$P2,$H:$H) -> 0.2887963 | S2: =IF(OR(R2="",R2>=$U$1)," ",$U$1-R2) -> 0.044537037 | T2: =IFERROR(AVERAGEIF($A:$A,$P2,$N:$N)," ") -> 1.1023614 | U2: =S2-V2 -> 0.036585648 | V2: 0.0079513889
A3: 45783 | B3: OGM - Sizing update | C3: 10 | D3: =IFERROR(VLOOKUP($B3,Task!$B$1:$G$70,6,0)," ") -> 0.0055555556 | E3: =IFERROR(D3*C3," ") -> 0.055555556 | F3: =G2 -> 0.41458333 | G3: 0.48783565 | H3: =IF(G3="","", IF(L3=" ",IF(OR(F3=0,G3=0),"",G3-F3),((G3-F3)-L3))) -> 0.050462963 | I3: =IFERROR(IF(L3=" ",(F3+E3),(F3+E3+L3)),"") -> 0.49292824 | L3: 0.022789352 | N3: =IFERROR(E3/H3," ") -> 1.1009174 | O3: =O2-O1 -> 0.67383102 | P3: =IFERROR(__xludf.DUMMYFUNCTION("""COMPUTED_VALUE"""),45784) -> 45784 | Q3: =IF(SUMIF($A:$A,$P3,$E:$E)=0,"",SUMIF($A:$A,$P3,$E:$E)) -> 0.31597222 | R3: =IF(SUMIF($A:$A,$P3,$H:$H)=0,"",SUMIF($A:$A,$P3,$H:$H)) -> 0.28361111 | S3: =IF(OR(R3="",R3>=$U$1)," ",$U$1-R3) -> 0.049722222 | T3: =IFERROR(AVERAGEIF($A:$A,$P3,$N:$N)," ") -> 1.1001055
A4: 45783 | B4: Nordstrom SQL DATA Dump | C4: 1 | D4: =IFERROR(VLOOKUP($B4,Task!$B$1:$G$70,6,0)," ") -> 0.048611111 | E4: =IFERROR(D4*C4," ") -> 0.048611111 | F4: =G3 -> 0.48783565 | G4: 0.53212963 | H4: =IF(G4="","", IF(L4=" ",IF(OR(F4=0,G4=0),"",G4-F4),((G4-F4)-L4))) -> 0.044293981 | I4: =IFERROR(IF(L4=" ",(F4+E4),(F4+E4+L4)),"") -> 0.53644676 | N4: =IFERROR(E4/H4," ") -> 1.0974654 | P4: =IFERROR(__xludf.DUMMYFUNCTION("""COMPUTED_VALUE"""),45785) -> 45785 | Q4: =IF(SUMIF($A:$A,$P4,$E:$E)=0,"",SUMIF($A:$A,$P4,$E:$E)) -> 0.34236111 | R4: =IF(SUMIF($A:$A,$P4,$H:$H)=0,"",SUMIF($A:$A,$P4,$H:$H)) -> 0.31034722 | S4: =IF(OR(R4="",R4>=$U$1)," ",$U$1-R4) -> 0.022986111 | T4: =IFERROR(AVERAGEIF($A:$A,$P4,$N:$N)," ") -> 1.1003047
A5: 45783 | B5: WH - Fabric Composition | C5: 55 | D5: =IFERROR(VLOOKUP($B5,Task!$B$1:$G$70,6,0)," ") -> 0.0020833333 | E5: =IFERROR(D5*C5," ") -> 0.11458333 | F5: =G4 -> 0.53212963 | G5: 0.70833333 | H5: =IF(G5="","", IF(L5=" ",IF(OR(F5=0,G5=0),"",G5-F5),((G5-F5)-L5))) -> 0.10313657 | I5: =IFERROR(IF(L5=" ",(F5+E5),(F5+E5+L5)),"") -> 0.71978009 | L5: 0.07306713 | N5: =IFERROR(E5/H5," ") -> 1.1109864 | P5: =IFERROR(__xludf.DUMMYFUNCTION("""COMPUTED_VALUE"""),45786) -> 45786 | Q5: =IF(SUMIF($A:$A,$P5,$E:$E)=0,"",SUMIF($A:$A,$P5,$E:$E)) -> 0.31041667 | R5: =IF(SUMIF($A:$A,$P5,$H:$H)=0,"",SUMIF($A:$A,$P5,$H:$H)) -> 0.28330662 | S5: =IF(OR(R5="",R5>=$U$1)," ",$U$1-R5) -> 0.050026713 | T5: =IFERROR(AVERAGEIF($A:$A,$P5,$N:$N)," ") -> 1.0881073
A6: 45784 | B6: WH - Fabric Composition | C6: 20 | D6: =IFERROR(VLOOKUP($B6,Task!$B$1:$G$70,6,0)," ") -> 0.0020833333 | E6: =IFERROR(D6*C6," ") -> 0.041666667 | F6: 0.33076389 | G6: 0.36851852 | H6: =IF(G6="","", IF(L6=" ",IF(OR(F6=0,G6=0),"",G6-F6),((G6-F6)-L6))) -> 0.03775463 | I6: =IFERROR(IF(L6=" ",(F6+E6),(F6+E6+L6)),"") -> 0.37243056 | N6: =IFERROR(E6/H6," ") -> 1.1036174 | P6: =IFERROR(__xludf.DUMMYFUNCTION("""COMPUTED_VALUE"""),45789) -> 45789 | Q6: =IF(SUMIF($A:$A,$P6,$E:$E)=0,"",SUMIF($A:$A,$P6,$E:$E)) -> 0.35138889 | R6: =IF(SUMIF($A:$A,$P6,$H:$H)=0,"",SUMIF($A:$A,$P6,$H:$H)) -> 0.32054819 | S6: =IF(OR(R6="",R6>=$U$1)," ",$U$1-R6) -> 0.012785139 | T6: =IFERROR(AVERAGEIF($A:$A,$P6,$N:$N)," ") -> 1.095786
A7: 45784 | B7: Nordstrom SQL DATA Dump | C7: 2 | D7: =IFERROR(VLOOKUP($B7,Task!$B$1:$G$70,6,0)," ") -> 0.048611111 | E7: =IFERROR(D7*C7," ") -> 0.097222222 | F7: =G6 -> 0.36851852 | G7: 0.49975694 | H7: =IF(G7="","", IF(L7=" ",IF(OR(F7=0,G7=0),"",G7-F7),((G7-F7)-L7))) -> 0.087210648 | I7: =IFERROR(IF(L7=" ",(F7+E7),(F7+E7+L7)),"") -> 0.50976852 | L7: 0.044027778 | N7: =IFERROR(E7/H7," ") -> 1.1147976 | P7: =IFERROR(__xludf.DUMMYFUNCTION("""COMPUTED_VALUE"""),45790) -> 45790 | Q7: =IF(SUMIF($A:$A,$P7,$E:$E)=0,"",SUMIF($A:$A,$P7,$E:$E)) -> 0.28611111 | R7: =IF(SUMIF($A:$A,$P7,$H:$H)=0,"",SUMIF($A:$A,$P7,$H:$H)) -> 0.26149306 | S7: =IF(OR(R7="",R7>=$U$1)," ",$U$1-R7) -> 0.071840278 | T7: =IFERROR(AVERAGEIF($A:$A,$P7,$N:$N)," ") -> 1.0825554
A8: 45784 | B8: Wholesale Data Enrichment Report | C8: 1 | D8: =IFERROR(VLOOKUP($B8,Task!$B$1:$G$70,6,0)," ") -> 0.020833333 | E8: =IFERROR(D8*C8," ") -> 0.020833333 | F8: =G7 -> 0.49975694 | G8: 0.57866898 | H8: =IF(G8="","", IF(L8=" ",IF(OR(F8=0,G8=0),"",G8-F8),((G8-F8)-L8))) -> 0.020150463 | I8: =IFERROR(IF(L8=" ",(F8+E8),(F8+E8+L8)),"") -> 0.57935185 | L8: 0.058761574 | N8: =IFERROR(E8/H8," ") -> 1.0338886 | P8: =IFERROR(__xludf.DUMMYFUNCTION("""COMPUTED_VALUE"""),45791) -> 45791 | Q8: =IF(SUMIF($A:$A,$P8,$E:$E)=0,"",SUMIF($A:$A,$P8,$E:$E)) -> 0.24166667 | R8: =IF(SUMIF($A:$A,$P8,$H:$H)=0,"",SUMIF($A:$A,$P8,$H:$H)) -> 0.22043981 | S8: =IF(OR(R8="",R8>=$U$1)," ",$U$1-R8) -> 0.11289352 | T8: =IFERROR(AVERAGEIF($A:$A,$P8,$N:$N)," ") -> 1.0964528
A9: 45784 | B9: Training | C9: 1 | D9: =IFERROR(VLOOKUP($B9,Task!$B$1:$G$70,6,0)," ") -> 0.041666667 | E9: =IFERROR(D9*C9," ") -> 0.041666667 | F9: 0.49997685 | G9: 0.53733796 | H9: =IF(G9="","", IF(L9=" ",IF(OR(F9=0,G9=0),"",G9-F9),((G9-F9)-L9))) -> 0.037361111 | I9: =IFERROR(IF(L9=" ",(F9+E9),(F9+E9+L9)),"") -> 0.54164352 | N9: =IFERROR(E9/H9," ") -> 1.1152416 | P9: =IFERROR(__xludf.DUMMYFUNCTION("""COMPUTED_VALUE"""),45792) -> 45792 | Q9: =IF(SUMIF($A:$A,$P9,$E:$E)=0,"",SUMIF($A:$A,$P9,$E:$E)) -> 0.18194444 | R9: =IF(SUMIF($A:$A,$P9,$H:$H)=0,"",SUMIF($A:$A,$P9,$H:$H)) -> 0.16087963 | S9: =IF(OR(R9="",R9>=$U$1)," ",$U$1-R9) -> 0.1724537 | T9: =IFERROR(AVERAGEIF($A:$A,$P9,$N:$N)," ") -> 2.9126799
A10: 45784 | B10: WH - Wash Care update | C10: 55 | D10: =IFERROR(VLOOKUP($B10,Task!$B$1:$G$70,6,0)," ") -> 0.0020833333 | E10: =IFERROR(D10*C10," ") -> 0.11458333 | F10: =G8 -> 0.57866898 | G10: 0.71180556 | H10: =IF(G10="","", IF(L10=" ",IF(OR(F10=0,G10=0),"",G10-F10),((G10-F10)-L10))) -> 0.10113426 | I10: =IFERROR(IF(L10=" ",(F10+E10),(F10+E10+L10)),"") -> 0.72525463 | L10: 0.032002315 | N10: =IFERROR(E10/H10," ") -> 1.1329824 | P10: =IFERROR(__xludf.DUMMYFUNCTION("""COMPUTED_VALUE"""),45793) -> 45793 | Q10: =IF(SUMIF($A:$A,$P10,$E:$E)=0,"",SUMIF($A:$A,$P10,$E:$E)) -> 0.28472222 | R10: =IF(SUMIF($A:$A,$P10,$H:$H)=0,"",SUMIF($A:$A,$P10,$H:$H)) -> 0.26271991 | S10: =IF(OR(R10="",R10>=$U$1)," ",$U$1-R10) -> 0.070613426 | T10: =IFERROR(AVERAGEIF($A:$A,$P10,$N:$N)," ") -> 1.0871626
A11: 45785 | B11: WH - Wash Care update | C11: 71 | D11: =IFERROR(VLOOKUP($B11,Task!$B$1:$G$70,6,0)," ") -> 0.0020833333 | E11: =IFERROR(D11*C11," ") -> 0.14791667 | F11: 0.33653935 | G11: 0.5162037 | H11: =IF(G11="","", IF(L11=" ",IF(OR(F11=0,G11=0),"",G11-F11),((G11-F11)-L11))) -> 0.13459491 | I11: =IFERROR(IF(L11=" ",(F11+E11),(F11+E11+L11)),"") -> 0.52952546 | L11: 0.045069444 | N11: =IFERROR(E11/H11," ") -> 1.0989767 | P11: =IFERROR(__xludf.DUMMYFUNCTION("""COMPUTED_VALUE"""),45796) -> 45796 | Q11: =IF(SUMIF($A:$A,$P11,$E:$E)=0,"",SUMIF($A:$A,$P11,$E:$E)) -> 0.20694444 | R11: =IF(SUMIF($A:$A,$P11,$H:$H)=0,"",SUMIF($A:$A,$P11,$H:$H)) -> 0.18923781 | S11: =IF(OR(R11="",R11>=$U$1)," ",$U$1-R11) -> 0.14409552 | T11: =IFERROR(AVERAGEIF($A:$A,$P11,$N:$N)," ") -> 1.0888777
A12: 45785 | B12: Nordstrom SQL DATA Dump | C12: 1 | D12: =IFERROR(VLOOKUP($B12,Task!$B$1:$G$70,6,0)," ") -> 0.048611111 | E12: =IFERROR(D12*C12," ") -> 0.048611111 | F12: =G11 -> 0.5162037 | G12: 0.56040509 | H12: =IF(G12="","", IF(L12=" ",IF(OR(F12=0,G12=0),"",G12-F12),((G12-F12)-L12))) -> 0.044201389 | I12: =IFERROR(IF(L12=" ",(F12+E12),(F12+E12+L12)),"") -> 0.56481481 | N12: =IFERROR(E12/H12," ") -> 1.0997643 | P12: =IFERROR(__xludf.DUMMYFUNCTION("""COMPUTED_VALUE"""),45797) -> 45797 | Q12: =IF(SUMIF($A:$A,$P12,$E:$E)=0,"",SUMIF($A:$A,$P12,$E:$E)) -> 0.31111111 | R12: =IF(SUMIF($A:$A,$P12,$H:$H)=0,"",SUMIF($A:$A,$P12,$H:$H)) -> 0.27717593 | S12: =IF(OR(R12="",R12>=$U$1)," ",$U$1-R12) -> 0.056157407 | T12: =IFERROR(AVERAGEIF($A:$A,$P12,$N:$N)," ") -> 1.1003696
A13: 45785 | B13: Very Invoice Report | C13: 1 | D13: =IFERROR(VLOOKUP($B13,Task!$B$1:$G$70,6,0)," ") -> 0.020833333 | E13: =IFERROR(D13*C13," ") -> 0.020833333 | F13: =G12 -> 0.56040509 | G13: 0.57950231 | H13: =IF(G13="","", IF(L13=" ",IF(OR(F13=0,G13=0),"",G13-F13),((G13-F13)-L13))) -> 0.019097222 | I13: =IFERROR(IF(L13=" ",(F13+E13),(F13+E13+L13)),"") -> 0.58123843 | N13: =IFERROR(E13/H13," ") -> 1.0909091 | P13: =IFERROR(__xludf.DUMMYFUNCTION("""COMPUTED_VALUE"""),45798) -> 45798 | Q13: =IF(SUMIF($A:$A,$P13,$E:$E)=0,"",SUMIF($A:$A,$P13,$E:$E)) -> 0.24861111 | R13: =IF(SUMIF($A:$A,$P13,$H:$H)=0,"",SUMIF($A:$A,$P13,$H:$H)) -> 0.22947248 | S13: =IF(OR(R13="",R13>=$U$1)," ",$U$1-R13) -> 0.10386086 | T13: =IFERROR(AVERAGEIF($A:$A,$P13,$N:$N)," ") -> 1.0829432
A14: 45785 | B14: WH - Wash Care update | C14: 60 | D14: =IFERROR(VLOOKUP($B14,Task!$B$1:$G$70,6,0)," ") -> 0.0020833333 | E14: =IFERROR(D14*C14," ") -> 0.125 | F14: =G13 -> 0.57950231 | G14: 0.71527778 | H14: =IF(G14="","", IF(L14=" ",IF(OR(F14=0,G14=0),"",G14-F14),((G14-F14)-L14))) -> 0.1124537 | I14: =IFERROR(IF(L14=" ",(F14+E14),(F14+E14+L14)),"") -> 0.72782407 | L14: 0.023321759 | N14: =IFERROR(E14/H14," ") -> 1.1115685 | P14: =IFERROR(__xludf.DUMMYFUNCTION("""COMPUTED_VALUE"""),45799) -> 45799 | Q14: =IF(SUMIF($A:$A,$P14,$E:$E)=0,"",SUMIF($A:$A,$P14,$E:$E)) -> 0.3125 | R14: =IF(SUMIF($A:$A,$P14,$H:$H)=0,"",SUMIF($A:$A,$P14,$H:$H)) -> 0.29038774 | S14: =IF(OR(R14="",R14>=$U$1)," ",$U$1-R14) -> 0.04294559 | T14: =IFERROR(AVERAGEIF($A:$A,$P14,$N:$N)," ") -> 1.0843169
A15: 45786 | B15: WH - Wash Care update | C15: 39 | D15: =IFERROR(VLOOKUP($B15,Task!$B$1:$G$70,6,0)," ") -> 0.0020833333 | E15: =IFERROR(D15*C15," ") -> 0.08125 | F15: 0.34417824 | G15: 0.45226852 | H15: =IF(G15="","", IF(L15=" ",IF(OR(F15=0,G15=0),"",G15-F15),((G15-F15)-L15))) -> 0.074224537 | I15: =IFERROR(IF(L15=" ",(F15+E15),(F15+E15+L15)),"") -> 0.45929398 | L15: 0.033865741 | N15: =IFERROR(E15/H15," ") -> 1.0946515 | P15: =IFERROR(__xludf.DUMMYFUNCTION("""COMPUTED_VALUE"""),45800) -> 45800 | Q15: =IF(SUMIF($A:$A,$P15,$E:$E)=0,"",SUMIF($A:$A,$P15,$E:$E)) -> 0.29027778 | R15: =IF(SUMIF($A:$A,$P15,$H:$H)=0,"",SUMIF($A:$A,$P15,$H:$H)) -> 0.2683912 | S15: =IF(OR(R15="",R15>=$U$1)," ",$U$1-R15) -> 0.06494213 | T15: =IFERROR(AVERAGEIF($A:$A,$P15,$N:$N)," ") -> 1.0690949
A16: 45786 | B16: Nordstrom SQL DATA Dump | C16: 1 | D16: =IFERROR(VLOOKUP($B16,Task!$B$1:$G$70,6,0)," ") -> 0.048611111 | E16: =IFERROR(D16*C16," ") -> 0.048611111 | F16: =G15 -> 0.45226852 | G16: 0.5478125 | H16: =IF(G16="","", IF(L16=" ",IF(OR(F16=0,G16=0),"",G16-F16),((G16-F16)-L16))) -> 0.045648148 | I16: =IFERROR(IF(L16=" ",(F16+E16),(F16+E16+L16)),"") -> 0.55077546 | L16: 0.049895833 | N16: =IFERROR(E16/H16," ") -> 1.0649087 | P16: =IFERROR(__xludf.DUMMYFUNCTION("""COMPUTED_VALUE"""),45804) -> 45804 | Q16: =IF(SUMIF($A:$A,$P16,$E:$E)=0,"",SUMIF($A:$A,$P16,$E:$E)) -> 0.34166667 | R16: =IF(SUMIF($A:$A,$P16,$H:$H)=0,"",SUMIF($A:$A,$P16,$H:$H)) -> 0.31488426 | S16: =IF(OR(R16="",R16>=$U$1)," ",$U$1-R16) -> 0.018449074 | T16: =IFERROR(AVERAGEIF($A:$A,$P16,$N:$N)," ") -> 1.0799339
A17: 45786 | B17: Wholesale Adding Images | C17: 130 | D17: =IFERROR(VLOOKUP($B17,Task!$B$1:$G$70,6,0)," ") -> 0.0013888889 | E17: =IFERROR(D17*C17," ") -> 0.18055556 | F17: =G16 -> 0.5478125 | G17: 0.72227653 | H17: =IF(G17="","", IF(L17=" ",IF(OR(F17=0,G17=0),"",G17-F17),((G17-F17)-L17))) -> 0.16343394 | I17: =IFERROR(IF(L17=" ",(F17+E17),(F17+E17+L17)),"") -> 0.73939815 | L17: 0.011030093 | N17: =IFERROR(E17/H17," ") -> 1.1047617 | P17: =IFERROR(__xludf.DUMMYFUNCTION("""COMPUTED_VALUE"""),45805) -> 45805 | Q17: =IF(SUMIF($A:$A,$P17,$E:$E)=0,"",SUMIF($A:$A,$P17,$E:$E)) -> 0.27777778 | R17: =IF(SUMIF($A:$A,$P17,$H:$H)=0,"",SUMIF($A:$A,$P17,$H:$H)) -> 0.25342801 | S17: =IF(OR(R17="",R17>=$U$1)," ",$U$1-R17) -> 0.079905324 | T17: =IFERROR(AVERAGEIF($A:$A,$P17,$N:$N)," ") -> 1.0972892
A18: 45789 | B18: Nordstrom SQL DATA Dump | C18: 2 | D18: =IFERROR(VLOOKUP($B18,Task!$B$1:$G$70,6,0)," ") -> 0.048611111 | E18: =IFERROR(D18*C18," ") -> 0.097222222 | F18: 0.42283565 | G18: 0.53645833 | H18: =IF(G18="","", IF(L18=" ",IF(OR(F18=0,G18=0),"",G18-F18),((G18-F18)-L18))) -> 0.088356481 | I18: =IFERROR(IF(L18=" ",(F18+E18),(F18+E18+L18)),"") -> 0.54532407 | L18: 0.025266204 | N18: =IFERROR(E18/H18," ") -> 1.1003406 | P18: =IFERROR(__xludf.DUMMYFUNCTION("""COMPUTED_VALUE"""),45806) -> 45806 | Q18: =IF(SUMIF($A:$A,$P18,$E:$E)=0,"",SUMIF($A:$A,$P18,$E:$E)) -> 0.30138889 | R18: =IF(SUMIF($A:$A,$P18,$H:$H)=0,"",SUMIF($A:$A,$P18,$H:$H)) -> 0.27494084 | S18: =IF(OR(R18="",R18>=$U$1)," ",$U$1-R18) -> 0.058392488 | T18: =IFERROR(AVERAGEIF($A:$A,$P18,$N:$N)," ") -> 1.0931463
A19: 45789 | B19: Wholesale Adding Images | C19: 121 | D19: =IFERROR(VLOOKUP($B19,Task!$B$1:$G$70,6,0)," ") -> 0.0013888889 | E19: =IFERROR(D19*C19," ") -> 0.16805556 | F19: =G18 -> 0.53645833 | G19: 0.74722222 | H19: =IF(G19="","", IF(L19=" ",IF(OR(F19=0,G19=0),"",G19-F19),((G19-F19)-L19))) -> 0.15327546 | I19: =IFERROR(IF(L19=" ",(F19+E19),(F19+E19+L19)),"") -> 0.76200231 | L19: 0.057488426 | N19: =IFERROR(E19/H19," ") -> 1.0964283 | P19: =IFERROR(__xludf.DUMMYFUNCTION("""COMPUTED_VALUE"""),45807) -> 45807 | Q19: =IF(SUMIF($A:$A,$P19,$E:$E)=0,"",SUMIF($A:$A,$P19,$E:$E)) -> 0.30277778 | R19: =IF(SUMIF($A:$A,$P19,$H:$H)=0,"",SUMIF($A:$A,$P19,$H:$H)) -> 0.26842593 | S19: =IF(R19=""," ",$U$1-R19) -> 0.064907407 | T19: =IFERROR(AVERAGEIF($A:$A,$P19,$N:$N)," ") -> 1.1002984
A20: 45789 | B20: DAM - Image Approval | C20: 11 | D20: =IFERROR(VLOOKUP($B20,Task!$B$1:$G$70,6,0)," ") -> 0.0027777778 | E20: =IFERROR(D20*C20," ") -> 0.030555556 | F20: 0.64001157 | G20: 0.66778935 | H20: =IF(G20="","", IF(L20=" ",IF(OR(F20=0,G20=0),"",G20-F20),((G20-F20)-L20))) -> 0.027777778 | I20: =IFERROR(IF(L20=" ",(F20+E20),(F20+E20+L20)),"") -> 0.67056713 | N20: =IFERROR(E20/H20," ") -> 1.1 | Q20: =IF(SUMIF($A:$A,$P20,$E:$E)=0,"",SUMIF($A:$A,$P20,$E:$E)) | R20: =IF(SUMIF($A:$A,$P20,$H:$H)=0,"",SUMIF($A:$A,$P20,$H:$H)) | S20: =IF(R20=""," ",$U$1-R20) | T20: =IFERROR(AVERAGEIF($A:$A,$P20,$N:$N)," ")
A21: 45789 | B21: OGM - Sizing update | C21: 10 | D21: =IFERROR(VLOOKUP($B21,Task!$B$1:$G$70,6,0)," ") -> 0.0055555556 | E21: =IFERROR(D21*C21," ") -> 0.055555556 | F21: =G19 -> 0.74722222 | G21: 0.79836069 | H21: =IF(G21="","", IF(L21=" ",IF(OR(F21=0,G21=0),"",G21-F21),((G21-F21)-L21))) -> 0.051138472 | I21: =IFERROR(IF(L21=" ",(F21+E21),(F21+E21+L21)),"") -> 0.80277778 | N21: =IFERROR(E21/H21," ") -> 1.086375 | Q21: =IF(SUMIF($A:$A,$P21,$E:$E)=0,"",SUMIF($A:$A,$P21,$E:$E)) | R21: =IF(SUMIF($A:$A,$P21,$H:$H)=0,"",SUMIF($A:$A,$P21,$H:$H)) | S21: =IF(R21=""," ",$U$1-R21) | T21: =IFERROR(AVERAGEIF($A:$A,$P21,$N:$N)," ")
A22: 45790 | B22: Nordstrom SQL DATA Dump | C22: 3 | D22: =IFERROR(VLOOKUP($B22,Task!$B$1:$G$70,6,0)," ") -> 0.048611111 | E22: =IFERROR(D22*C22," ") -> 0.14583333 | F22: 0.38869213 | G22: 0.57377315 | H22: =IF(G22="","", IF(L22=" ",IF(OR(F22=0,G22=0),"",G22-F22),((G22-F22)-L22))) -> 0.13266204 | I22: =IFERROR(IF(L22=" ",(F22+E22),(F22+E22+L22)),"") -> 0.58694444 | L22: 0.052418981 | N22: =IFERROR(E22/H22," ") -> 1.0992846 | Q22: =IF(SUMIF($A:$A,$P22,$E:$E)=0,"",SUMIF($A:$A,$P22,$E:$E)) | R22: =IF(SUMIF($A:$A,$P22,$H:$H)=0,"",SUMIF($A:$A,$P22,$H:$H)) | S22: =IF(R22=""," ",$U$1-R22) | T22: =IFERROR(AVERAGEIF($A:$A,$P22,$N:$N)," ")
A23: 45790 | B23: DAM - Image Search | C23: 52 | D23: =IFERROR(VLOOKUP($B23,Task!$B$1:$G$70,6,0)," ") -> 0.00069444444 | E23: =IFERROR(D23*C23," ") -> 0.036111111 | F23: =G22 -> 0.57377315 | G23: 0.62552083 | H23: =IF(G23="","", IF(L23=" ",IF(OR(F23=0,G23=0),"",G23-F23),((G23-F23)-L23))) -> 0.032824074 | I23: =IFERROR(IF(L23=" ",(F23+E23),(F23+E23+L23)),"") -> 0.62880787 | L23: 0.018923611 | N23: =IFERROR(E23/H23," ") -> 1.100141 | Q23: =IF(SUMIF($A:$A,$P23,$E:$E)=0,"",SUMIF($A:$A,$P23,$E:$E)) | R23: =IF(SUMIF($A:$A,$P23,$H:$H)=0,"",SUMIF($A:$A,$P23,$H:$H)) | S23: =IF(R23=""," ",$U$1-R23) | T23: =IFERROR(AVERAGEIF($A:$A,$P23,$N:$N)," ")
A24: 45790 | B24: Very Invoice Report | C24: 1 | D24: =IFERROR(VLOOKUP($B24,Task!$B$1:$G$70,6,0)," ") -> 0.020833333 | E24: =IFERROR(D24*C24," ") -> 0.020833333 | F24: =G23 -> 0.62552083 | G24: 0.645625 | H24: =IF(G24="","", IF(L24=" ",IF(OR(F24=0,G24=0),"",G24-F24),((G24-F24)-L24))) -> 0.020104167 | I24: =IFERROR(IF(L24=" ",(F24+E24),(F24+E24+L24)),"") -> 0.64635417 | N24: =IFERROR(E24/H24," ") -> 1.0362694
A25: 45790 | B25: OGM - Sizing update | C25: 10 | D25: =IFERROR(VLOOKUP($B25,Task!$B$1:$G$70,6,0)," ") -> 0.0055555556 | E25: =IFERROR(D25*C25," ") -> 0.055555556 | F25: =G24 -> 0.645625 | G25: 0.71680556 | H25: =IF(G25="","", IF(L25=" ",IF(OR(F25=0,G25=0),"",G25-F25),((G25-F25)-L25))) -> 0.049652778 | I25: =IFERROR(IF(L25=" ",(F25+E25),(F25+E25+L25)),"") -> 0.72270833 | L25: 0.021527778 | N25: =IFERROR(E25/H25," ") -> 1.1188811
A26: 45790 | B26: OGM - Sizing update | C26: 5 | D26: =IFERROR(VLOOKUP($B26,Task!$B$1:$G$70,6,0)," ") -> 0.0055555556 | E26: =IFERROR(D26*C26," ") -> 0.027777778 | F26: =G25 -> 0.71680556 | G26: 0.74305556 | H26: =IF(G26="","", IF(L26=" ",IF(OR(F26=0,G26=0),"",G26-F26),((G26-F26)-L26))) -> 0.02625 | I26: =IFERROR(IF(L26=" ",(F26+E26),(F26+E26+L26)),"") -> 0.74458333 | N26: =IFERROR(E26/H26," ") -> 1.0582011 | P26: Date | Q26: Core | R26: Break | S26: Other-Idle | T26: Daily Huddle
A27: 45791 | B27: OGM - Sizing update | C27: =14-C26 -> 9 | D27: =IFERROR(VLOOKUP($B27,Task!$B$1:$G$70,6,0)," ") -> 0.0055555556 | E27: =IFERROR(D27*C27," ") -> 0.05 | F27: 0.33649306 | G27: 0.38251157 | H27: =IF(G27="","", IF(L27=" ",IF(OR(F27=0,G27=0),"",G27-F27),((G27-F27)-L27))) -> 0.046018519 | I27: =IFERROR(IF(L27=" ",(F27+E27),(F27+E27+L27)),"") -> 0.38649306 | N27: =IFERROR(E27/H27," ") -> 1.0865191
A28: 45791 | B28: Nordstrom SQL DATA Dump | C28: 2 | D28: =IFERROR(VLOOKUP($B28,Task!$B$1:$G$70,6,0)," ") -> 0.048611111 | E28: =IFERROR(D28*C28," ") -> 0.097222222 | F28: =G27 -> 0.38251157 | G28: 0.51979167 | H28: =IF(G28="","", IF(L28=" ",IF(OR(F28=0,G28=0),"",G28-F28),((G28-F28)-L28))) -> 0.088425926 | I28: =IFERROR(IF(L28=" ",(F28+E28),(F28+E28+L28)),"") -> 0.52858796 | L28: 0.048854167 | N28: =IFERROR(E28/H28," ") -> 1.0994764
A29: 45791 | B29: DAM - Image Approval | C29: 5 | D29: =IFERROR(VLOOKUP($B29,Task!$B$1:$G$70,6,0)," ") -> 0.0027777778 | E29: =IFERROR(D29*C29," ") -> 0.013888889 | F29: =G28 -> 0.51979167 | G29: 0.54746157 | H29: =IF(G29="","", IF(L29=" ",IF(OR(F29=0,G29=0),"",G29-F29),((G29-F29)-L29))) -> 0.012600463 | I29: =IFERROR(IF(L29=" ",(F29+E29),(F29+E29+L29)),"") -> 0.54875 | L29: 0.015069444 | N29: =IFERROR(E29/H29," ") -> 1.1022523
A30: 45791 | B30: DAM - Image Approval | C30: 29 | D30: =IFERROR(VLOOKUP($B30,Task!$B$1:$G$70,6,0)," ") -> 0.0027777778 | E30: =IFERROR(D30*C30," ") -> 0.080555556 | F30: =G29 -> 0.54746157 | G30: 0.62928241 | H30: =IF(G30="","", IF(L30=" ",IF(OR(F30=0,G30=0),"",G30-F30),((G30-F30)-L30))) -> 0.073394907 | I30: =IFERROR(IF(L30=" ",(F30+E30),(F30+E30+L30)),"") -> 0.63644306 | L30: 0.0084259259 | N30: =IFERROR(E30/H30," ") -> 1.0975633
A31: 45792 | B31: Nordstrom SQL DATA Dump | C31: 1 | D31: =IFERROR(VLOOKUP($B31,Task!$B$1:$G$70,6,0)," ") -> 0.048611111 | E31: =IFERROR(D31*C31," ") -> 0.048611111 | F31: 0.33915509 | G31: 0.38774306 | H31: =IF(G31="","", IF(L31=" ",IF(OR(F31=0,G31=0),"",G31-F31),((G31-F31)-L31))) -> 0.048587963 | I31: =IFERROR(IF(L31=" ",(F31+E31),(F31+E31+L31)),"") -> 0.3877662 | N31: =IFERROR(E31/H31," ") -> 1.0004764
A32: 45792 | B32: DAM - Image Approval | C32: 38 | D32: =IFERROR(VLOOKUP($B32,Task!$B$1:$G$70,6,0)," ") -> 0.0027777778 | E32: =IFERROR(D32*C32," ") -> 0.10555556 | F32: 0.40388889 | G32: 0.53962963 | H32: =IF(G32="","", IF(L32=" ",IF(OR(F32=0,G32=0),"",G32-F32),((G32-F32)-L32))) -> 0.090798611 | I32: =IFERROR(IF(L32=" ",(F32+E32),(F32+E32+L32)),"") -> 0.55438657 | L32: 0.04494213 | N32: =IFERROR(E32/H32," ") -> 1.1625239
A33: 45792 | B33: OGM - Sizing update | C33: 1 | D33: =IFERROR(VLOOKUP($B33,Task!$B$1:$G$70,6,0)," ") -> 0.0055555556 | E33: =IFERROR(D33*C33," ") -> 0.0055555556 | F33: 0.65172454 | G33: 0.67986111 | H33: =IF(G33="","", IF(L33=" ",IF(OR(F33=0,G33=0),"",G33-F33),((G33-F33)-L33))) -> 0.00065972222 | I33: =IFERROR(IF(L33=" ",(F33+E33),(F33+E33+L33)),"") -> 0.68475694 | L33: 0.027476852 | N33: =IFERROR(E33/H33," ") -> 8.4210526
A34: 45792 | B34: OGM - Sizing update | C34: 4 | D34: =IFERROR(VLOOKUP($B34,Task!$B$1:$G$70,6,0)," ") -> 0.0055555556 | E34: =IFERROR(D34*C34," ") -> 0.022222222 | F34: =G33 -> 0.67986111 | G34: 0.70069444 | H34: =IF(G34="","", IF(L34=" ",IF(OR(F34=0,G34=0),"",G34-F34),((G34-F34)-L34))) -> 0.020833333 | I34: =IFERROR(IF(L34=" ",(F34+E34),(F34+E34+L34)),"") -> 0.70208333 | N34: =IFERROR(E34/H34," ") -> 1.0666667
A35: 45793 | B35: Nordstrom SQL DATA Dump | C35: 1 | D35: =IFERROR(VLOOKUP($B35,Task!$B$1:$G$70,6,0)," ") -> 0.048611111 | E35: =IFERROR(D35*C35," ") -> 0.048611111 | F35: 0.33628472 | G35: 0.42315972 | H35: =IF(G35="","", IF(L35=" ",IF(OR(F35=0,G35=0),"",G35-F35),((G35-F35)-L35))) -> 0.044270833 | I35: =IFERROR(IF(L35=" ",(F35+E35),(F35+E35+L35)),"") -> 0.4275 | L35: 0.042604167 | N35: =IFERROR(E35/H35," ") -> 1.0980392
A36: 45793 | B36: OGM - Sizing update | C36: 20 | D36: =IFERROR(VLOOKUP($B36,Task!$B$1:$G$70,6,0)," ") -> 0.0055555556 | E36: =IFERROR(D36*C36," ") -> 0.11111111 | F36: =G35 -> 0.42315972 | G36: 0.55277778 | H36: =IF(G36="","", IF(L36=" ",IF(OR(F36=0,G36=0),"",G36-F36),((G36-F36)-L36))) -> 0.10155093 | I36: =IFERROR(IF(L36=" ",(F36+E36),(F36+E36+L36)),"") -> 0.56233796 | L36: 0.02806713 | N36: =IFERROR(E36/H36," ") -> 1.0941418
A37: 45793 | B37: WH - Fabric Composition | C37: 60 | D37: =IFERROR(VLOOKUP($B37,Task!$B$1:$G$70,6,0)," ") -> 0.0020833333 | E37: =IFERROR(D37*C37," ") -> 0.125 | F37: =G36 -> 0.55277778 | G37: 0.71527778 | H37: =IF(G37="","", IF(L37=" ",IF(OR(F37=0,G37=0),"",G37-F37),((G37-F37)-L37))) -> 0.11689815 | I37: =IFERROR(IF(L37=" ",(F37+E37),(F37+E37+L37)),"") -> 0.72337963 | L37: 0.045601852 | N37: =IFERROR(E37/H37," ") -> 1.0693069
A38: 45796 | B38: OGM - Sizing update | C38: 21 | D38: =IFERROR(VLOOKUP($B38,Task!$B$1:$G$70,6,0)," ") -> 0.0055555556 | E38: =IFERROR(D38*C38," ") -> 0.11666667 | F38: 0.35261574 | G38: 0.49444444 | H38: =IF(G38="","", IF(L38=" ",IF(OR(F38=0,G38=0),"",G38-F38),((G38-F38)-L38))) -> 0.10606481 | I38: =IFERROR(IF(L38=" ",(F38+E38),(F38+E38+L38)),"") -> 0.5050463 | L38: 0.035763889 | N38: =IFERROR(E38/H38," ") -> 1.0999564
A39: 45796 | B39: Nordstrom SQL DATA Dump | C39: 1 | D39: =IFERROR(VLOOKUP($B39,Task!$B$1:$G$70,6,0)," ") -> 0.048611111 | E39: =IFERROR(D39*C39," ") -> 0.048611111 | F39: =G38 -> 0.49444444 | G39: 0.53919686 | H39: =IF(G39="","", IF(L39=" ",IF(OR(F39=0,G39=0),"",G39-F39),((G39-F39)-L39))) -> 0.044752419 | I39: =IFERROR(IF(L39=" ",(F39+E39),(F39+E39+L39)),"") -> 0.54305556 | N39: =IFERROR(E39/H39," ") -> 1.0862231
A40: 45796 | B40: WH - EAN Update | C40: 15 | D40: =IFERROR(VLOOKUP($B40,Task!$B$1:$G$70,6,0)," ") -> 0.0013888889 | E40: =IFERROR(D40*C40," ") -> 0.020833333 | F40: 0.6005787 | G40: 0.61954326 | H40: =IF(G40="","", IF(L40=" ",IF(OR(F40=0,G40=0),"",G40-F40),((G40-F40)-L40))) -> 0.01896456 | I40: =IFERROR(IF(L40=" ",(F40+E40),(F40+E40+L40)),"") -> 0.62141204 | N40: =IFERROR(E40/H40," ") -> 1.0985403
A41: 45796 | B41: Wholesale Data Enrichment Report | C41: 1 | D41: =IFERROR(VLOOKUP($B41,Task!$B$1:$G$70,6,0)," ") -> 0.020833333 | E41: =IFERROR(D41*C41," ") -> 0.020833333 | F41: 0.68336806 | G41: 0.70282407 | H41: =IF(G41="","", IF(L41=" ",IF(OR(F41=0,G41=0),"",G41-F41),((G41-F41)-L41))) -> 0.019456019 | I41: =IFERROR(IF(L41=" ",(F41+E41),(F41+E41+L41)),"") -> 0.70420139 | N41: =IFERROR(E41/H41," ") -> 1.0707912
A42: 45797 | B42: Very Invoice Report | C42: 1 | D42: =IFERROR(VLOOKUP($B42,Task!$B$1:$G$70,6,0)," ") -> 0.020833333 | E42: =IFERROR(D42*C42," ") -> 0.020833333 | F42: 0.33627315 | G42: 0.35563657 | H42: =IF(G42="","", IF(L42=" ",IF(OR(F42=0,G42=0),"",G42-F42),((G42-F42)-L42))) -> 0.019363426 | I42: =IFERROR(IF(L42=" ",(F42+E42),(F42+E42+L42)),"") -> 0.35710648 | N42: =IFERROR(E42/H42," ") -> 1.0759115
A43: 45797 | B43: Image upload to Very/John Lewis | C43: 3 | D43: =IFERROR(VLOOKUP($B43,Task!$B$1:$G$70,6,0)," ") -> 0.0027777778 | E43: =IFERROR(D43*C43," ") -> 0.0083333333 | F43: =G42 -> 0.35563657 | G43: 0.36353009 | H43: =IF(G43="","", IF(L43=" ",IF(OR(F43=0,G43=0),"",G43-F43),((G43-F43)-L43))) -> 0.0078935185 | I43: =IFERROR(IF(L43=" ",(F43+E43),(F43+E43+L43)),"") -> 0.36396991 | N43: =IFERROR(E43/H43," ") -> 1.0557185
A44: 45797 | B44: Nordstrom SQL DATA Dump | C44: 1 | D44: =IFERROR(VLOOKUP($B44,Task!$B$1:$G$70,6,0)," ") -> 0.048611111 | E44: =IFERROR(D44*C44," ") -> 0.048611111 | F44: 0.41946759 | G44: 0.48874473 | H44: =IF(G44="","", IF(L44=" ",IF(OR(F44=0,G44=0),"",G44-F44),((G44-F44)-L44))) -> 0.044277141 | I44: =IFERROR(IF(L44=" ",(F44+E44),(F44+E44+L44)),"") -> 0.4930787 | L44: 0.025 | N44: =IFERROR(E44/H44," ") -> 1.0978828
A45: 45797 | B45: OGM - Sizing update | C45: 21 | D45: =IFERROR(VLOOKUP($B45,Task!$B$1:$G$70,6,0)," ") -> 0.0055555556 | E45: =IFERROR(D45*C45," ") -> 0.11666667 | F45: =G44 -> 0.48874473 | G45: 0.5953125 | H45: =IF(G45="","", IF(L45=" ",IF(OR(F45=0,G45=0),"",G45-F45),((G45-F45)-L45))) -> 0.10656777 | I45: =IFERROR(IF(L45=" ",(F45+E45),(F45+E45+L45)),"") -> 0.6054114 | N45: =IFERROR(E45/H45," ") -> 1.0947651
A46: 45797 | B46: DAM - Image Approval | C46: 42 | D46: =IFERROR(VLOOKUP($B46,Task!$B$1:$G$70,6,0)," ") -> 0.0027777778 | E46: =IFERROR(D46*C46," ") -> 0.11666667 | F46: =G45 -> 0.5953125 | G46: 0.71180556 | H46: =IF(G46="","", IF(L46=" ",IF(OR(F46=0,G46=0),"",G46-F46),((G46-F46)-L46))) -> 0.099074074 | I46: =IFERROR(IF(L46=" ",(F46+E46),(F46+E46+L46)),"") -> 0.72939815 | L46: 0.017418981 | N46: =IFERROR(E46/H46," ") -> 1.1775701
A47: 45798 | B47: Wholesale Adding Images | C47: 16 | D47: =IFERROR(VLOOKUP($B47,Task!$B$1:$G$70,6,0)," ") -> 0.0013888889 | E47: =IFERROR(D47*C47," ") -> 0.022222222 | F47: 0.34506944 | G47: 0.36541667 | H47: =IF(G47="","", IF(L47=" ",IF(OR(F47=0,G47=0),"",G47-F47),((G47-F47)-L47))) -> 0.020347222 | I47: =IFERROR(IF(L47=" ",(F47+E47),(F47+E47+L47)),"") -> 0.36729167 | N47: =IFERROR(E47/H47," ") -> 1.0921502
A48: 45798 | B48: Wholesale Adding Images | C48: 40 | D48: =IFERROR(VLOOKUP($B48,Task!$B$1:$G$70,6,0)," ") -> 0.0013888889 | E48: =IFERROR(D48*C48," ") -> 0.055555556 | F48: 0.36642361 | G48: 0.41697917 | H48: =IF(G48="","", IF(L48=" ",IF(OR(F48=0,G48=0),"",G48-F48),((G48-F48)-L48))) -> 0.050555556 | I48: =IFERROR(IF(L48=" ",(F48+E48),(F48+E48+L48)),"") -> 0.42197917 | N48: =IFERROR(E48/H48," ") -> 1.0989011
A49: 45798 | B49: Nordstrom SQL DATA Dump | C49: 1 | D49: =IFERROR(VLOOKUP($B49,Task!$B$1:$G$70,6,0)," ") -> 0.048611111 | E49: =IFERROR(D49*C49," ") -> 0.048611111 | F49: =G48 -> 0.41697917 | G49: 0.49627315 | H49: =IF(G49="","", IF(L49=" ",IF(OR(F49=0,G49=0),"",G49-F49),((G49-F49)-L49))) -> 0.047337963 | I49: =IFERROR(IF(L49=" ",(F49+E49),(F49+E49+L49)),"") -> 0.4975463 | L49: 0.031956019 | N49: =IFERROR(E49/H49," ") -> 1.0268949
A50: 45798 | B50: OGM - Sizing update | C50: 8 | D50: =IFERROR(VLOOKUP($B50,Task!$B$1:$G$70,6,0)," ") -> 0.0055555556 | E50: =IFERROR(D50*C50," ") -> 0.044444444 | F50: =G49 -> 0.49627315 | G50: 0.53679398 | H50: =IF(G50="","", IF(L50=" ",IF(OR(F50=0,G50=0),"",G50-F50),((G50-F50)-L50))) -> 0.040520833 | I50: =IFERROR(IF(L50=" ",(F50+E50),(F50+E50+L50)),"") -> 0.54071759 | N50: =IFERROR(E50/H50," ") -> 1.0968295
A51: 45798 | B51: Wholesale Adding Images | C51: 56 | D51: =IFERROR(VLOOKUP($B51,Task!$B$1:$G$70,6,0)," ") -> 0.0013888889 | E51: =IFERROR(D51*C51," ") -> 0.077777778 | F51: =G50 -> 0.53679398 | G51: 0.62709979 | H51: =IF(G51="","", IF(L51=" ",IF(OR(F51=0,G51=0),"",G51-F51),((G51-F51)-L51))) -> 0.070710903 | I51: =IFERROR(IF(L51=" ",(F51+E51),(F51+E51+L51)),"") -> 0.63416667 | L51: 0.019594907 | N51: =IFERROR(E51/H51," ") -> 1.0999404
A52: 45799 | B52: DAM - Image Approval | C52: 35 | D52: =IFERROR(VLOOKUP($B52,Task!$B$1:$G$70,6,0)," ") -> 0.0027777778 | E52: =IFERROR(D52*C52," ") -> 0.097222222 | F52: 0.37134259 | G52: 0.50403935 | H52: =IF(G52="","", IF(L52=" ",IF(OR(F52=0,G52=0),"",G52-F52),((G52-F52)-L52))) -> 0.088761574 | I52: =IFERROR(IF(L52=" ",(F52+E52),(F52+E52+L52)),"") -> 0.5125 | L52: 0.043935185 | N52: =IFERROR(E52/H52," ") -> 1.0953188
A53: 45799 | B53: Nordstrom SQL DATA Dump | C53: 1 | D53: =IFERROR(VLOOKUP($B53,Task!$B$1:$G$70,6,0)," ") -> 0.048611111 | E53: =IFERROR(D53*C53," ") -> 0.048611111 | F53: =G52 -> 0.50403935 | G53: 0.54828704 | H53: =IF(G53="","", IF(L53=" ",IF(OR(F53=0,G53=0),"",G53-F53),((G53-F53)-L53))) -> 0.044247685 | I53: =IFERROR(IF(L53=" ",(F53+E53),(F53+E53+L53)),"") -> 0.55265046 | N53: =IFERROR(E53/H53," ") -> 1.0986137
A54: 45799 | B54: OGM - Sizing update | C54: 30 | D54: =IFERROR(VLOOKUP($B54,Task!$B$1:$G$70,6,0)," ") -> 0.0055555556 | E54: =IFERROR(D54*C54," ") -> 0.16666667 | F54: =G53 -> 0.54828704 | G54: 0.73934608 | H54: =IF(G54="","", IF(L54=" ",IF(OR(F54=0,G54=0),"",G54-F54),((G54-F54)-L54))) -> 0.15737848 | I54: =IFERROR(IF(L54=" ",(F54+E54),(F54+E54+L54)),"") -> 0.74863426 | L54: 0.033680556 | N54: =IFERROR(E54/H54," ") -> 1.0590181
A55: 45800 | B55: Nordstrom SQL DATA Dump | C55: 1 | D55: =IFERROR(VLOOKUP($B55,Task!$B$1:$G$70,6,0)," ") -> 0.048611111 | E55: =IFERROR(D55*C55," ") -> 0.048611111 | F55: 0.34028935 | G55: 0.4378125 | H55: =IF(G55="","", IF(L55=" ",IF(OR(F55=0,G55=0),"",G55-F55),((G55-F55)-L55))) -> 0.044398148 | I55: =IFERROR(IF(L55=" ",(F55+E55),(F55+E55+L55)),"") -> 0.44202546 | L55: 0.053125 | N55: =IFERROR(E55/H55," ") -> 1.0948905
A56: 45800 | B56: OGM - Sizing update | C56: 7 | D56: =IFERROR(VLOOKUP($B56,Task!$B$1:$G$70,6,0)," ") -> 0.0055555556 | E56: =IFERROR(D56*C56," ") -> 0.038888889 | F56: =G55 -> 0.4378125 | G56: 0.49988426 | H56: =IF(G56="","", IF(L56=" ",IF(OR(F56=0,G56=0),"",G56-F56),((G56-F56)-L56))) -> 0.038865741 | I56: =IFERROR(IF(L56=" ",(F56+E56),(F56+E56+L56)),"") -> 0.49990741 | L56: 0.023206019 | N56: =IFERROR(E56/H56," ") -> 1.0005956
A57: 45800 | B57: Wholesale Adding Images | C57: 98 | D57: =IFERROR(VLOOKUP($B57,Task!$B$1:$G$70,6,0)," ") -> 0.0013888889 | E57: =IFERROR(D57*C57," ") -> 0.13611111 | F57: =G56 -> 0.49988426 | G57: 0.65677083 | H57: =IF(G57="","", IF(L57=" ",IF(OR(F57=0,G57=0),"",G57-F57),((G57-F57)-L57))) -> 0.12314815 | I57: =IFERROR(IF(L57=" ",(F57+E57),(F57+E57+L57)),"") -> 0.6697338 | L57: 0.033738426 | N57: =IFERROR(E57/H57," ") -> 1.1052632
A58: 45800 | B58: OGM - Sizing update | C58: 12 | D58: =IFERROR(VLOOKUP($B58,Task!$B$1:$G$70,6,0)," ") -> 0.0055555556 | E58: =IFERROR(D58*C58," ") -> 0.066666667 | F58: =G57 -> 0.65677083 | G58: 0.71875 | H58: =IF(G58="","", IF(L58=" ",IF(OR(F58=0,G58=0),"",G58-F58),((G58-F58)-L58))) -> 0.061979167 | I58: =IFERROR(IF(L58=" ",(F58+E58),(F58+E58+L58)),"") -> 0.7234375 | N58: =IFERROR(E58/H58," ") -> 1.0756303
A59: 45804 | B59: OGM - Sizing update | C59: 15 | D59: =IFERROR(VLOOKUP($B59,Task!$B$1:$G$70,6,0)," ") -> 0.0055555556 | E59: =IFERROR(D59*C59," ") -> 0.083333333 | F59: 0.39368056 | G59: 0.49364583 | H59: =IF(G59="","", IF(L59=" ",IF(OR(F59=0,G59=0),"",G59-F59),((G59-F59)-L59))) -> 0.075555556 | I59: =IFERROR(IF(L59=" ",(F59+E59),(F59+E59+L59)),"") -> 0.50142361 | L59: 0.024409722 | N59: =IFERROR(E59/H59," ") -> 1.1029412
A60: 45804 | B60: Wholesale Adding Images | C60: 17 | D60: =IFERROR(VLOOKUP($B60,Task!$B$1:$G$70,6,0)," ") -> 0.0013888889 | E60: =IFERROR(D60*C60," ") -> 0.023611111 | F60: 0.49949074 | G60: 0.52108796 | H60: =IF(G60="","", IF(L60=" ",IF(OR(F60=0,G60=0),"",G60-F60),((G60-F60)-L60))) -> 0.021597222 | I60: =IFERROR(IF(L60=" ",(F60+E60),(F60+E60+L60)),"") -> 0.52310185 | N60: =IFERROR(E60/H60," ") -> 1.0932476
A61: 45804 | B61: Wholesale Data Enrichment Report | C61: 1 | D61: =IFERROR(VLOOKUP($B61,Task!$B$1:$G$70,6,0)," ") -> 0.020833333 | E61: =IFERROR(D61*C61," ") -> 0.020833333 | F61: =G60 -> 0.52108796 | G61: 0.54063657 | H61: =IF(G61="","", IF(L61=" ",IF(OR(F61=0,G61=0),"",G61-F61),((G61-F61)-L61))) -> 0.019548611 | I61: =IFERROR(IF(L61=" ",(F61+E61),(F61+E61+L61)),"") -> 0.5419213 | N61: =IFERROR(E61/H61," ") -> 1.0657194
A62: 45804 | B62: Nordstrom SQL DATA Dump | C62: 2 | D62: =IFERROR(VLOOKUP($B62,Task!$B$1:$G$70,6,0)," ") -> 0.048611111 | E62: =IFERROR(D62*C62," ") -> 0.097222222 | F62: =G61 -> 0.54063657 | G62: 0.63438657 | H62: =IF(G62="","", IF(L62=" ",IF(OR(F62=0,G62=0),"",G62-F62),((G62-F62)-L62))) -> 0.088784722 | I62: =IFERROR(IF(L62=" ",(F62+E62),(F62+E62+L62)),"") -> 0.64282407 | L62: 0.0049652778 | N62: =IFERROR(E62/H62," ") -> 1.0950332
A63: 45804 | B63: OGM - Sizing update | C63: 9 | D63: =IFERROR(VLOOKUP($B63,Task!$B$1:$G$70,6,0)," ") -> 0.0055555556 | E63: =IFERROR(D63*C63," ") -> 0.05 | F63: =G62 -> 0.63438657 | G63: 0.68049769 | H63: =IF(G63="","", IF(L63=" ",IF(OR(F63=0,G63=0),"",G63-F63),((G63-F63)-L63))) -> 0.046111111 | I63: =IFERROR(IF(L63=" ",(F63+E63),(F63+E63+L63)),"") -> 0.68438657 | N63: =IFERROR(E63/H63," ") -> 1.0843373
A64: 45804 | B64: OGM - Sizing update | C64: 8 | D64: =IFERROR(VLOOKUP($B64,Task!$B$1:$G$70,6,0)," ") -> 0.0055555556 | E64: =IFERROR(D64*C64," ") -> 0.044444444 | F64: =G63 -> 0.68049769 | G64: 0.74877315 | H64: =IF(G64="","", IF(L64=" ",IF(OR(F64=0,G64=0),"",G64-F64),((G64-F64)-L64))) -> 0.042627315 | I64: =IFERROR(IF(L64=" ",(F64+E64),(F64+E64+L64)),"") -> 0.75059028 | L64: 0.025648148 | N64: =IFERROR(E64/H64," ") -> 1.0426283
A65: 45804 | B65: OGM - Sizing update | C65: 4 | D65: =IFERROR(VLOOKUP($B65,Task!$B$1:$G$70,6,0)," ") -> 0.0055555556 | E65: =IFERROR(D65*C65," ") -> 0.022222222 | F65: =G64 -> 0.74877315 | G65: 0.76943287 | H65: =IF(G65="","", IF(L65=" ",IF(OR(F65=0,G65=0),"",G65-F65),((G65-F65)-L65))) -> 0.020659722 | I65: =IFERROR(IF(L65=" ",(F65+E65),(F65+E65+L65)),"") -> 0.77099537 | N65: =IFERROR(E65/H65," ") -> 1.0756303
A66: 45805 | B66: OGM - Sizing update | C66: =18-C65 -> 14 | D66: =IFERROR(VLOOKUP($B66,Task!$B$1:$G$70,6,0)," ") -> 0.0055555556 | E66: =IFERROR(D66*C66," ") -> 0.077777778 | F66: 0.38327546 | G66: 0.49630787 | H66: =IF(G66="","", IF(L66=" ",IF(OR(F66=0,G66=0),"",G66-F66),((G66-F66)-L66))) -> 0.071365741 | I66: =IFERROR(IF(L66=" ",(F66+E66),(F66+E66+L66)),"") -> 0.50271991 | L66: 0.041666667 | N66: =IFERROR(E66/H66," ") -> 1.0898476 | O66: =AVERAGEIF(A:A,TODAY(),N:N) -> #DIV/0!
A67: 45805 | B67: Very Invoice Report | C67: 1 | D67: =IFERROR(VLOOKUP($B67,Task!$B$1:$G$70,6,0)," ") -> 0.020833333 | E67: =IFERROR(D67*C67," ") -> 0.020833333 | F67: =G66 -> 0.49630787 | G67: 0.51533565 | H67: =IF(G67="","", IF(L67=" ",IF(OR(F67=0,G67=0),"",G67-F67),((G67-F67)-L67))) -> 0.019027778 | I67: =IFERROR(IF(L67=" ",(F67+E67),(F67+E67+L67)),"") -> 0.5171412 | N67: =IFERROR(E67/H67," ") -> 1.0948905
A68: 45805 | B68: Wholesale Data Enrichment Report | C68: 1 | D68: =IFERROR(VLOOKUP($B68,Task!$B$1:$G$70,6,0)," ") -> 0.020833333 | E68: =IFERROR(D68*C68," ") -> 0.020833333 | F68: =G67 -> 0.51533565 | G68: 0.53428241 | H68: =IF(G68="","", IF(L68=" ",IF(OR(F68=0,G68=0),"",G68-F68),((G68-F68)-L68))) -> 0.018946759 | I68: =IFERROR(IF(L68=" ",(F68+E68),(F68+E68+L68)),"") -> 0.53616898 | N68: =IFERROR(E68/H68," ") -> 1.0995724
A69: 45805 | B69: Nordstrom SQL DATA Dump | C69: 1 | D69: =IFERROR(VLOOKUP($B69,Task!$B$1:$G$70,6,0)," ") -> 0.048611111 | E69: =IFERROR(D69*C69," ") -> 0.048611111 | F69: =G68 -> 0.53428241 | G69: 0.57826389 | H69: =IF(G69="","", IF(L69=" ",IF(OR(F69=0,G69=0),"",G69-F69),((G69-F69)-L69))) -> 0.043981481 | I69: =IFERROR(IF(L69=" ",(F69+E69),(F69+E69+L69)),"") -> 0.58289352 | N69: =IFERROR(E69/H69," ") -> 1.1052632
A70: 45805 | B70: DAM - Image Approval | C70: 22 | D70: =IFERROR(VLOOKUP($B70,Task!$B$1:$G$70,6,0)," ") -> 0.0027777778 | E70: =IFERROR(D70*C70," ") -> 0.061111111 | F70: =G69 -> 0.57826389 | G70: 0.66385417 | H70: =IF(G70="","", IF(L70=" ",IF(OR(F70=0,G70=0),"",G70-F70),((G70-F70)-L70))) -> 0.056134259 | I70: =IFERROR(IF(L70=" ",(F70+E70),(F70+E70+L70)),"") -> 0.66883102 | L70: 0.029456019 | N70: =IFERROR(E70/H70," ") -> 1.0886598
A71: 45805 | B71: Nordstrom SQL DATA Dump | C71: 1 | D71: =IFERROR(VLOOKUP($B71,Task!$B$1:$G$70,6,0)," ") -> 0.048611111 | E71: =IFERROR(D71*C71," ") -> 0.048611111 | F71: 0.68591435 | G71: 0.72988634 | H71: =IF(G71="","", IF(L71=" ",IF(OR(F71=0,G71=0),"",G71-F71),((G71-F71)-L71))) -> 0.043971991 | I71: =IFERROR(IF(L71=" ",(F71+E71),(F71+E71+L71)),"") -> 0.73452546 | N71: =IFERROR(E71/H71," ") -> 1.1055017
A72: 45806 | B72: Nordstrom SQL DATA Dump | C72: 1 | D72: =IFERROR(VLOOKUP($B72,Task!$B$1:$G$70,6,0)," ") -> 0.048611111 | E72: =IFERROR(D72*C72," ") -> 0.048611111 | F72: 0.4043287 | G72: 0.44958333 | H72: =IF(G72="","", IF(L72=" ",IF(OR(F72=0,G72=0),"",G72-F72),((G72-F72)-L72))) -> 0.04525463 | I72: =IFERROR(IF(L72=" ",(F72+E72),(F72+E72+L72)),"") -> 0.45293981 | N72: =IFERROR(E72/H72," ") -> 1.0741688
A73: 45806 | B73: Nordstrom SQL DATA Dump | C73: 1 | D73: =IFERROR(VLOOKUP($B73,Task!$B$1:$G$70,6,0)," ") -> 0.048611111 | E73: =IFERROR(D73*C73," ") -> 0.048611111 | F73: =G72 -> 0.44958333 | G73: 0.54221065 | H73: =IF(G73="","", IF(L73=" ",IF(OR(F73=0,G73=0),"",G73-F73),((G73-F73)-L73))) -> 0.043842593 | I73: =IFERROR(IF(L73=" ",(F73+E73),(F73+E73+L73)),"") -> 0.54697917 | L73: 0.048784722 | N73: =IFERROR(E73/H73," ") -> 1.1087645
A74: 45806 | B74: Wholesale Data Enrichment Report | C74: 1 | D74: =IFERROR(VLOOKUP($B74,Task!$B$1:$G$70,6,0)," ") -> 0.020833333 | E74: =IFERROR(D74*C74," ") -> 0.020833333 | F74: =G73 -> 0.54221065 | G74: 0.56173611 | H74: =IF(G74="","", IF(L74=" ",IF(OR(F74=0,G74=0),"",G74-F74),((G74-F74)-L74))) -> 0.019525463 | I74: =IFERROR(IF(L74=" ",(F74+E74),(F74+E74+L74)),"") -> 0.56304398 | N74: =IFERROR(E74/H74," ") -> 1.0669828
A75: 45806 | B75: OGM - Sizing update | C75: 13 | D75: =IFERROR(VLOOKUP($B75,Task!$B$1:$G$70,6,0)," ") -> 0.0055555556 | E75: =IFERROR(D75*C75," ") -> 0.072222222 | F75: =G74 -> 0.56173611 | G75: 0.62751157 | H75: =IF(G75="","", IF(L75=" ",IF(OR(F75=0,G75=0),"",G75-F75),((G75-F75)-L75))) -> 0.065775463 | I75: =IFERROR(IF(L75=" ",(F75+E75),(F75+E75+L75)),"") -> 0.63395833 | N75: =IFERROR(E75/H75," ") -> 1.0980116
A76: 45806 | B76: DAM - Image Approval | C76: 30 | D76: =IFERROR(VLOOKUP($B76,Task!$B$1:$G$70,6,0)," ") -> 0.0027777778 | E76: =IFERROR(D76*C76," ") -> 0.083333333 | F76: =G75 -> 0.62751157 | G76: 0.70905432 | H76: =IF(G76="","", IF(L76=" ",IF(OR(F76=0,G76=0),"",G76-F76),((G76-F76)-L76))) -> 0.075431632 | I76: =IFERROR(IF(L76=" ",(F76+E76),(F76+E76+L76)),"") -> 0.71695602 | L76: 0.0061111111 | N76: =IFERROR(E76/H76," ") -> 1.1047532
A77: 45806 | B77: OGM - Sizing update | C77: 5 | D77: =IFERROR(VLOOKUP($B77,Task!$B$1:$G$70,6,0)," ") -> 0.0055555556 | E77: =IFERROR(D77*C77," ") -> 0.027777778 | F77: 0.72571759 | G77: 0.75082866 | H77: =IF(G77="","", IF(L77=" ",IF(OR(F77=0,G77=0),"",G77-F77),((G77-F77)-L77))) -> 0.025111065 | I77: =IFERROR(IF(L77=" ",(F77+E77),(F77+E77+L77)),"") -> 0.75349537 | N77: =IFERROR(E77/H77," ") -> 1.1061967
A78: 45807 | B78: Wholesale Adding Images | C78: 57 | D78: =IFERROR(VLOOKUP($B78,Task!$B$1:$G$70,6,0)," ") -> 0.0013888889 | E78: =IFERROR(D78*C78," ") -> 0.079166667 | F78: 0.32762731 | G78: 0.46541667 | H78: =IF(G78="","", IF(L78=" ",IF(OR(F78=0,G78=0),"",G78-F78),((G78-F78)-L78))) -> 0.071666667 | I78: =IFERROR(IF(L78=" ",(F78+E78),(F78+E78+L78)),"") -> 0.47291667 | L78: 0.066122685 | N78: =IFERROR(E78/H78," ") -> 1.1046512
A79: 45807 | B79: Nordstrom SQL DATA Dump | C79: 1 | D79: =IFERROR(VLOOKUP($B79,Task!$B$1:$G$70,6,0)," ") -> 0.048611111 | E79: =IFERROR(D79*C79," ") -> 0.048611111 | F79: =G78 -> 0.46541667 | G79: 0.50957176 | H79: =IF(G79="","", IF(L79=" ",IF(OR(F79=0,G79=0),"",G79-F79),((G79-F79)-L79))) -> 0.044155093 | I79: =IFERROR(IF(L79=" ",(F79+E79),(F79+E79+L79)),"") -> 0.51402778 | N79: =IFERROR(E79/H79," ") -> 1.1009174
A80: 45807 | B80: Wholesale Data Enrichment Report | C80: 1 | D80: =IFERROR(VLOOKUP($B80,Task!$B$1:$G$70,6,0)," ") -> 0.020833333 | E80: =IFERROR(D80*C80," ") -> 0.020833333 | F80: =G79 -> 0.50957176 | G80: 0.5293287 | H80: =IF(G80="","", IF(L80=" ",IF(OR(F80=0,G80=0),"",G80-F80),((G80-F80)-L80))) -> 0.019756944 | I80: =IFERROR(IF(L80=" ",(F80+E80),(F80+E80+L80)),"") -> 0.53040509 | N80: =IFERROR(E80/H80," ") -> 1.0544815
A81: 45807 | B81: Nordstrom SQL DATA Dump | C81: 1 | D81: =IFERROR(VLOOKUP($B81,Task!$B$1:$G$70,6,0)," ") -> 0.048611111 | E81: =IFERROR(D81*C81," ") -> 0.048611111 | F81: =G80 -> 0.5293287 | G81: 0.57372685 | H81: =IF(G81="","", IF(L81=" ",IF(OR(F81=0,G81=0),"",G81-F81),((G81-F81)-L81))) -> 0.044398148 | I81: =IFERROR(IF(L81=" ",(F81+E81),(F81+E81+L81)),"") -> 0.57793981 | N81: =IFERROR(E81/H81," ") -> 1.0948905 | O81: =AVERAGEIF(A:A,TODAY(),N:N) -> #DIV/0!
A82: 45807 | B82: OGM - Sizing update | C82: 14 | D82: =IFERROR(VLOOKUP($B82,Task!$B$1:$G$70,6,0)," ") -> 0.0055555556 | E82: =IFERROR(D82*C82," ") -> 0.077777778 | F82: =G81 -> 0.57372685 | G82: 0.67369213 | H82: =IF(G82="","", IF(L82=" ",IF(OR(F82=0,G82=0),"",G82-F82),((G82-F82)-L82))) -> 0.053946759 | I82: =IFERROR(IF(L82=" ",(F82+E82),(F82+E82+L82)),"") -> 0.69752315 | L82: 0.046018519 | N82: =IFERROR(E82/H82," ") -> 1.4417507
A83: 45807 | B83: OGM - Sizing update | C83: 5 | D83: =IFERROR(VLOOKUP($B83,Task!$B$1:$G$70,6,0)," ") -> 0.0055555556 | E83: =IFERROR(D83*C83," ") -> 0.027777778 | F83: 0.67383102 | G83: 0.70833333 | H83: =IF(G83="","", IF(L83=" ",IF(OR(F83=0,G83=0),"",G83-F83),((G83-F83)-L83))) -> 0.034502315 | I83: =IFERROR(IF(L83=" ",(F83+E83),(F83+E83+L83)),"") -> 0.7016088 | N83: =IFERROR(E83/H83," ") -> 0.80509896
B84: OGM - Sizing update | C84: 8 | D84: =IFERROR(VLOOKUP($B84,Task!$B$1:$G$70,6,0)," ") -> 0.0055555556 | E84: =IFERROR(D84*C84," ") -> 0.044444444 | H84: =IF(G84="","", IF(L84=" ",IF(OR(F84=0,G84=0),"",G84-F84),((G84-F84)-L84))) | I84: =IFERROR(IF(L84=" ",(F84+E84),(F84+E84+L84)),"") -> 0.044444444 | N84: =IFERROR(E84/H84," ")
D85: =IFERROR(VLOOKUP($B85,Task!$B$1:$G$70,6,0)," ") | E85: =IFERROR(D85*C85," ") | H85: =IF(G85="","", IF(L85=" ",IF(OR(F85=0,G85=0),"",G85-F85),((G85-F85)-L85))) | I85: =IFERROR(IF(L85=" ",(F85+E85),(F85+E85+L85)),"") | N85: =IFERROR(E85/H85," ")
D86: =IFERROR(VLOOKUP($B86,Task!$B$1:$G$70,6,0)," ") | E86: =IFERROR(D86*C86," ") | H86: =IF(G86="","", IF(L86=" ",IF(OR(F86=0,G86=0),"",G86-F86),((G86-F86)-L86))) | I86: =IFERROR(IF(L86=" ",(F86+E86),(F86+E86+L86)),"") | N86: =IFERROR(E86/H86," ")
D87: =IFERROR(VLOOKUP($B87,Task!$B$1:$G$70,6,0)," ") | E87: =IFERROR(D87*C87," ") | H87: =IF(G87="","", IF(L87=" ",IF(OR(F87=0,G87=0),"",G87-F87),((G87-F87)-L87))) | I87: =IFERROR(IF(L87=" ",(F87+E87),(F87+E87+L87)),"") | N87: =IFERROR(E87/H87," ")
D88: =IFERROR(VLOOKUP($B88,Task!$B$1:$G$70,6,0)," ") | E88: =IFERROR(D88*C88," ") | H88: =IF(G88="","", IF(L88=" ",IF(OR(F88=0,G88=0),"",G88-F88),((G88-F88)-L88))) | I88: =IFERROR(IF(L88=" ",(F88+E88),(F88+E88+L88)),"") | N88: =IFERROR(E88/H88," ")
D89: =IFERROR(VLOOKUP($B89,Task!$B$1:$G$70,6,0)," ") | E89: =IFERROR(D89*C89," ") | H89: =IF(G89="","", IF(L89=" ",IF(OR(F89=0,G89=0),"",G89-F89),((G89-F89)-L89))) | I89: =IFERROR(IF(L89=" ",(F89+E89),(F89+E89+L89)),"") | N89: =IFERROR(E89/H89," ")
D90: =IFERROR(VLOOKUP($B90,Task!$B$1:$G$70,6,0)," ") | E90: =IFERROR(D90*C90," ") | H90: =IF(G90="","", IF(L90=" ",IF(OR(F90=0,G90=0),"",G90-F90),((G90-F90)-L90))) | I90: =IFERROR(IF(L90=" ",(F90+E90),(F90+E90+L90)),"") | N90: =IFERROR(E90/H90," ")
D91: =IFERROR(VLOOKUP($B91,Task!$B$1:$G$70,6,0)," ") | E91: =IFERROR(D91*C91," ") | H91: =IF(G91="","", IF(L91=" ",IF(OR(F91=0,G91=0),"",G91-F91),((G91-F91)-L91))) | I91: =IFERROR(IF(L91=" ",(F91+E91),(F91+E91+L91)),"") | N91: =IFERROR(E91/H91," ")
D92: =IFERROR(VLOOKUP($B92,Task!$B$1:$G$70,6,0)," ") | E92: =IFERROR(D92*C92," ") | H92: =IF(G92="","", IF(L92=" ",IF(OR(F92=0,G92=0),"",G92-F92),((G92-F92)-L92))) | I92: =IFERROR(IF(L92=" ",(F92+E92),(F92+E92+L92)),"") | N92: =IFERROR(E92/H92," ")
D93: =IFERROR(VLOOKUP($B93,Task!$B$1:$G$70,6,0)," ") | E93: =IFERROR(D93*C93," ") | H93: =IF(G93="","", IF(L93=" ",IF(OR(F93=0,G93=0),"",G93-F93),((G93-F93)-L93))) | I93: =IFERROR(IF(L93=" ",(F93+E93),(F93+E93+L93)),"") | N93: =IFERROR(E93/H93," ")
D94: =IFERROR(VLOOKUP($B94,Task!$B$1:$G$70,6,0)," ") | E94: =IFERROR(D94*C94," ") | H94: =IF(G94="","", IF(L94=" ",IF(OR(F94=0,G94=0),"",G94-F94),((G94-F94)-L94))) | I94: =IFERROR(IF(L94=" ",(F94+E94),(F94+E94+L94)),"") | N94: =IFERROR(E94/H94," ")
D95: =IFERROR(VLOOKUP($B95,Task!$B$1:$G$70,6,0)," ") | E95: =IFERROR(D95*C95," ") | H95: =IF(G95="","", IF(L95=" ",IF(OR(F95=0,G95=0),"",G95-F95),((G95-F95)-L95))) | I95: =IFERROR(IF(L95=" ",(F95+E95),(F95+E95+L95)),"") | N95: =IFERROR(E95/H95," ")
D96: =IFERROR(VLOOKUP($B96,Task!$B$1:$G$70,6,0)," ") | E96: =IFERROR(D96*C96," ") | H96: =IF(G96="","", IF(L96=" ",IF(OR(F96=0,G96=0),"",G96-F96),((G96-F96)-L96))) | I96: =IFERROR(IF(L96=" ",(F96+E96),(F96+E96+L96)),"") | N96: =IFERROR(E96/H96," ")
... D115: =IFERROR(VLOOKUP($B115,Task!$B$1:$G$70,6,0)," ") | E115: =IFERROR(D115*C115," ") | H115: =IF(G115="","", IF(L115=" ",IF(OR(F115=0,G115=0),"",G115-F115),((G115-F115)-L115))) | I115: =IFERROR(IF(L115=" ",(F115+E115),(F115+E115+L115)),"") | N115: =IFERROR(E115/H115," ")
D116: =IFERROR(VLOOKUP($B116,Task!$B$1:$G$70,6,0)," ") | E116: =IFERROR(D116*C116," ") | H116: =IF(G116="","", IF(L116=" ",IF(OR(F116=0,G116=0),"",G116-F116),((G116-F116)-L116))) | I116: =IFERROR(IF(L116=" ",(F116+E116),(F116+E116+L116)),"") | N116: =IFERROR(E116/H116," ") | O116: =AVERAGEIF(A:A,TODAY(),N:N) -> #DIV/0!
D117: =IFERROR(VLOOKUP($B117,Task!$B$1:$G$70,6,0)," ") | E117: =IFERROR(D117*C117," ") | H117: =IF(G117="","", IF(L117=" ",IF(OR(F117=0,G117=0),"",G117-F117),((G117-F117)-L117))) | I117: =IFERROR(IF(L117=" ",(F117+E117),(F117+E117+L117)),"") | N117: =IFERROR(E117/H117," ")
D118: =IFERROR(VLOOKUP($B118,Task!$B$1:$G$70,6,0)," ") | E118: =IFERROR(D118*C118," ") | H118: =IF(G118="","", IF(L118=" ",IF(OR(F118=0,G118=0),"",G118-F118),((G118-F118)-L118))) | I118: =IFERROR(IF(L118=" ",(F118+E118),(F118+E118+L118)),"") | N118: =IFERROR(E118/H118," ")
...

Sheet April 25
A1: Date | B1: Task Name | C1: Quantity | D1: RE | E1: Total RE | F1: Start Time | G1: End Time | H1: Actual Time taken | I1: Actual End Time | J1: Break Start Time | K1: Break End Time | L1: Total Break time | M1: Comment | N1: Productivity | O1: 0.1875 | P1: Date | Q1: Total RE | R1: Core | S1: Non-Core | T1: Productivity | U1: 0.33333333
A2: 45748 | B2: Nordstrom SQL DATA Dump | C2: 1 | D2: =IFERROR(VLOOKUP($B2,Task!$B$1:$G$67,6,0)," ") -> 0.048611111 | E2: =IFERROR(D2*C2," ") -> 0.048611111 | F2: 0.38043981 | G2: 0.42475694 | H2: =IF(G2="","", IF(L2=" ",IF(OR(F2=0,G2=0),"",G2-F2),((G2-F2)-L2))) -> 0.04431713 | I2: =IFERROR(IF(L2=" ",(F2+E2),(F2+E2+L2)),"") -> 0.42905093 | N2: =IFERROR(E2/H2," ") -> 1.0968921 | O2: 0.66658565 | P2: =IFERROR(__xludf.DUMMYFUNCTION("UNIQUE($A$2:$A$993)"),45748) -> 45748 | Q2: =SUMIF($A:$A,$P2,$E:$E) -> 0.35833333 | R2: =SUMIF($A:$A,$P2,$H:$H) -> 0.3275463 | S2: =IF(OR(R2="",R2>=$U$1)," ",$U$1-R2) -> 0.005787037 | T2: =IFERROR(AVERAGEIF($A:$A,$P2,$N:$N)," ") -> 1.0946437 | U2: =S2-V2 -> -0.0021643519 | V2: 0.0079513889
A3: 45748 | B3: Very Invoice Report | C3: 1 | D3: =IFERROR(VLOOKUP($B3,Task!$B$1:$G$67,6,0)," ") -> 0.020833333 | E3: =IFERROR(D3*C3," ") -> 0.020833333 | F3: =G2 -> 0.42475694 | G3: 0.44357639 | H3: =IF(G3="","", IF(L3=" ",IF(OR(F3=0,G3=0),"",G3-F3),((G3-F3)-L3))) -> 0.018819444 | I3: =IFERROR(IF(L3=" ",(F3+E3),(F3+E3+L3)),"") -> 0.44559028 | N3: =IFERROR(E3/H3," ") -> 1.1070111 | O3: =O2-O1 -> 0.47908565 | P3: =IFERROR(__xludf.DUMMYFUNCTION("""COMPUTED_VALUE"""),45749) -> 45749 | Q3: =IF(SUMIF($A:$A,$P3,$E:$E)=0,"",SUMIF($A:$A,$P3,$E:$E)) -> 0.34305556 | R3: =IF(SUMIF($A:$A,$P3,$H:$H)=0,"",SUMIF($A:$A,$P3,$H:$H)) -> 0.31303241 | S3: =IF(OR(R3="",R3>=$U$1)," ",$U$1-R3) -> 0.020300926 | T3: =IFERROR(AVERAGEIF($A:$A,$P3,$N:$N)," ") -> 1.0969028
A4: 45748 | B4: OGM - Sizing update | C4: 8 | D4: =IFERROR(VLOOKUP($B4,Task!$B$1:$G$67,6,0)," ") -> 0.0055555556 | E4: =IFERROR(D4*C4," ") -> 0.044444444 | F4: =G3 -> 0.44357639 | G4: 0.48450231 | H4: =IF(G4="","", IF(L4=" ",IF(OR(F4=0,G4=0),"",G4-F4),((G4-F4)-L4))) -> 0.040925926 | I4: =IFERROR(IF(L4=" ",(F4+E4),(F4+E4+L4)),"") -> 0.48802083 | N4: =IFERROR(E4/H4," ") -> 1.0859729 | P4: =IFERROR(__xludf.DUMMYFUNCTION("""COMPUTED_VALUE"""),45750) -> 45750 | Q4: =IF(SUMIF($A:$A,$P4,$E:$E)=0,"",SUMIF($A:$A,$P4,$E:$E)) -> 0.30555556 | R4: =IF(SUMIF($A:$A,$P4,$H:$H)=0,"",SUMIF($A:$A,$P4,$H:$H)) -> 0.28545139 | S4: =IF(OR(R4="",R4>=$U$1)," ",$U$1-R4) -> 0.047881944 | T4: =IFERROR(AVERAGEIF($A:$A,$P4,$N:$N)," ") -> 1.08548
A5: 45748 | B5: OGM - Sizing update | C5: 12 | D5: =IFERROR(VLOOKUP($B5,Task!$B$1:$G$67,6,0)," ") -> 0.0055555556 | E5: =IFERROR(D5*C5," ") -> 0.066666667 | F5: =G4 -> 0.48450231 | G5: 0.56409722 | H5: =IF(G5="","", IF(L5=" ",IF(OR(F5=0,G5=0),"",G5-F5),((G5-F5)-L5))) -> 0.061585648 | I5: =IFERROR(IF(L5=" ",(F5+E5),(F5+E5+L5)),"") -> 0.56917824 | L5: 0.018009259 | N5: =IFERROR(E5/H5," ") -> 1.0825033 | P5: =IFERROR(__xludf.DUMMYFUNCTION("""COMPUTED_VALUE"""),45751) -> 45751 | Q5: =IF(SUMIF($A:$A,$P5,$E:$E)=0,"",SUMIF($A:$A,$P5,$E:$E)) -> 0.29861111 | R5: =IF(SUMIF($A:$A,$P5,$H:$H)=0,"",SUMIF($A:$A,$P5,$H:$H)) -> 0.27211806 | S5: =IF(OR(R5="",R5>=$U$1)," ",$U$1-R5) -> 0.061215278 | T5: =IFERROR(AVERAGEIF($A:$A,$P5,$N:$N)," ") -> 1.0976166
A6: 45748 | B6: OGM - Sizing update | C6: 15 | D6: =IFERROR(VLOOKUP($B6,Task!$B$1:$G$67,6,0)," ") -> 0.0055555556 | E6: =IFERROR(D6*C6," ") -> 0.083333333 | F6: =G5 -> 0.56409722 | G6: 0.64699074 | H6: =IF(G6="","", IF(L6=" ",IF(OR(F6=0,G6=0),"",G6-F6),((G6-F6)-L6))) -> 0.076331019 | I6: =IFERROR(IF(L6=" ",(F6+E6),(F6+E6+L6)),"") -> 0.65399306 | L6: 0.0065625 | N6: =IFERROR(E6/H6," ") -> 1.0917362 | P6: =IFERROR(__xludf.DUMMYFUNCTION("""COMPUTED_VALUE"""),45754) -> 45754 | Q6: =IF(SUMIF($A:$A,$P6,$E:$E)=0,"",SUMIF($A:$A,$P6,$E:$E)) -> 0.34583333 | R6: =IF(SUMIF($A:$A,$P6,$H:$H)=0,"",SUMIF($A:$A,$P6,$H:$H)) -> 0.32188657 | S6: =IF(OR(R6="",R6>=$U$1)," ",$U$1-R6) -> 0.011446759 | T6: =IFERROR(AVERAGEIF($A:$A,$P6,$N:$N)," ") -> 1.0874699
A7: 45748 | B7: OGM - Sizing update | C7: 17 | D7: =IFERROR(VLOOKUP($B7,Task!$B$1:$G$67,6,0)," ") -> 0.0055555556 | E7: =IFERROR(D7*C7," ") -> 0.094444444 | F7: =G6 -> 0.64699074 | G7: 0.75694444 | H7: =IF(G7="","", IF(L7=" ",IF(OR(F7=0,G7=0),"",G7-F7),((G7-F7)-L7))) -> 0.08556713 | I7: =IFERROR(IF(L7=" ",(F7+E7),(F7+E7+L7)),"") -> 0.76582176 | L7: 0.024386574 | N7: =IFERROR(E7/H7," ") -> 1.1037468 | P7: =IFERROR(__xludf.DUMMYFUNCTION("""COMPUTED_VALUE"""),45755) -> 45755 | Q7: =IF(SUMIF($A:$A,$P7,$E:$E)=0,"",SUMIF($A:$A,$P7,$E:$E)) -> 0.34027778 | R7: =IF(SUMIF($A:$A,$P7,$H:$H)=0,"",SUMIF($A:$A,$P7,$H:$H)) -> 0.31559045 | S7: =IF(OR(R7="",R7>=$U$1)," ",$U$1-R7) -> 0.017742882 | T7: =IFERROR(AVERAGEIF($A:$A,$P7,$N:$N)," ") -> 1.0767588
A8: 45749 | B8: Nordstrom SQL DATA Dump | C8: 1 | D8: =IFERROR(VLOOKUP($B8,Task!$B$1:$G$67,6,0)," ") -> 0.048611111 | E8: =IFERROR(D8*C8," ") -> 0.048611111 | F8: 0.38469907 | G8: 0.42827546 | H8: =IF(G8="","", IF(L8=" ",IF(OR(F8=0,G8=0),"",G8-F8),((G8-F8)-L8))) -> 0.043576389 | I8: =IFERROR(IF(L8=" ",(F8+E8),(F8+E8+L8)),"") -> 0.43331019 | N8: =IFERROR(E8/H8," ") -> 1.1155378 | P8: =IFERROR(__xludf.DUMMYFUNCTION("""COMPUTED_VALUE"""),45756) -> 45756 | Q8: =IF(SUMIF($A:$A,$P8,$E:$E)=0,"",SUMIF($A:$A,$P8,$E:$E)) -> 0.34166667 | R8: =IF(SUMIF($A:$A,$P8,$H:$H)=0,"",SUMIF($A:$A,$P8,$H:$H)) -> 0.32104167 | S8: =IF(OR(R8="",R8>=$U$1)," ",$U$1-R8) -> 0.012291667 | T8: =IFERROR(AVERAGEIF($A:$A,$P8,$N:$N)," ") -> 1.0693352
A9: 45749 | B9: Wholesale Adding Images | C9: 80 | D9: =IFERROR(VLOOKUP($B9,Task!$B$1:$G$67,6,0)," ") -> 0.0013888889 | E9: =IFERROR(D9*C9," ") -> 0.11111111 | F9: =G8 -> 0.42827546 | G9: 0.56319444 | H9: =IF(G9="","", IF(L9=" ",IF(OR(F9=0,G9=0),"",G9-F9),((G9-F9)-L9))) -> 0.10075231 | I9: =IFERROR(IF(L9=" ",(F9+E9),(F9+E9+L9)),"") -> 0.57355324 | L9: 0.034166667 | N9: =IFERROR(E9/H9," ") -> 1.1028145 | P9: =IFERROR(__xludf.DUMMYFUNCTION("""COMPUTED_VALUE"""),45757) -> 45757 | Q9: =IF(SUMIF($A:$A,$P9,$E:$E)=0,"",SUMIF($A:$A,$P9,$E:$E)) -> 0.35 | R9: =IF(SUMIF($A:$A,$P9,$H:$H)=0,"",SUMIF($A:$A,$P9,$H:$H)) -> 0.32435656 | S9: =IF(OR(R9="",R9>=$U$1)," ",$U$1-R9) -> 0.0089767708 | T9: =IFERROR(AVERAGEIF($A:$A,$P9,$N:$N)," ") -> 1.0897232
A10: 45749 | B10: OGM - Sizing update | C10: 9 | D10: =IFERROR(VLOOKUP($B10,Task!$B$1:$G$67,6,0)," ") -> 0.0055555556 | E10: =IFERROR(D10*C10," ") -> 0.05 | F10: =G9 -> 0.56319444 | G10: 0.61888889 | H10: =IF(G10="","", IF(L10=" ",IF(OR(F10=0,G10=0),"",G10-F10),((G10-F10)-L10))) -> 0.046296296 | I10: =IFERROR(IF(L10=" ",(F10+E10),(F10+E10+L10)),"") -> 0.62259259 | L10: 0.0093981481 | N10: =IFERROR(E10/H10," ") -> 1.08 | P10: =IFERROR(__xludf.DUMMYFUNCTION("""COMPUTED_VALUE"""),45758) -> 45758 | Q10: =IF(SUMIF($A:$A,$P10,$E:$E)=0,"",SUMIF($A:$A,$P10,$E:$E)) -> 0.32083333 | R10: =IF(SUMIF($A:$A,$P10,$H:$H)=0,"",SUMIF($A:$A,$P10,$H:$H)) -> 0.29108796 | S10: =IF(OR(R10="",R10>=$U$1)," ",$U$1-R10) -> 0.04224537 | T10: =IFERROR(AVERAGEIF($A:$A,$P10,$N:$N)," ") -> 1.1044141
A11: 45749 | B11: OGM - Sizing update | C11: 24 | D11: =IFERROR(VLOOKUP($B11,Task!$B$1:$G$67,6,0)," ") -> 0.0055555556 | E11: =IFERROR(D11*C11," ") -> 0.13333333 | F11: =G10 -> 0.61888889 | G11: 0.76388889 | H11: =IF(G11="","", IF(L11=" ",IF(OR(F11=0,G11=0),"",G11-F11),((G11-F11)-L11))) -> 0.12240741 | I11: =IFERROR(IF(L11=" ",(F11+E11),(F11+E11+L11)),"") -> 0.77481481 | L11: 0.022592593 | N11: =IFERROR(E11/H11," ") -> 1.0892587 | P11: =IFERROR(__xludf.DUMMYFUNCTION("""COMPUTED_VALUE"""),45761) -> 45761 | Q11: =IF(SUMIF($A:$A,$P11,$E:$E)=0,"",SUMIF($A:$A,$P11,$E:$E)) -> 0.34722222 | R11: =IF(SUMIF($A:$A,$P11,$H:$H)=0,"",SUMIF($A:$A,$P11,$H:$H)) -> 0.32356481 | S11: =IF(OR(R11="",R11>=$U$1)," ",$U$1-R11) -> 0.0097685185 | T11: =IFERROR(AVERAGEIF($A:$A,$P11,$N:$N)," ") -> 1.0805392
A12: 45750 | B12: Nordstrom SQL DATA Dump | C12: 1 | D12: =IFERROR(VLOOKUP($B12,Task!$B$1:$G$67,6,0)," ") -> 0.048611111 | E12: =IFERROR(D12*C12," ") -> 0.048611111 | F12: 0.39038194 | G12: 0.43465278 | H12: =IF(G12="","", IF(L12=" ",IF(OR(F12=0,G12=0),"",G12-F12),((G12-F12)-L12))) -> 0.044270833 | I12: =IFERROR(IF(L12=" ",(F12+E12),(F12+E12+L12)),"") -> 0.43899306 | N12: =IFERROR(E12/H12," ") -> 1.0980392 | P12: =IFERROR(__xludf.DUMMYFUNCTION("""COMPUTED_VALUE"""),45762) -> 45762 | Q12: =IF(SUMIF($A:$A,$P12,$E:$E)=0,"",SUMIF($A:$A,$P12,$E:$E)) -> 0.25694444 | R12: =IF(SUMIF($A:$A,$P12,$H:$H)=0,"",SUMIF($A:$A,$P12,$H:$H)) -> 0.23569457 | S12: =IF(OR(R12="",R12>=$U$1)," ",$U$1-R12) -> 0.097638762 | T12: =IFERROR(AVERAGEIF($A:$A,$P12,$N:$N)," ") -> 1.0888843
A13: 45750 | B13: OGM - Sizing update | C13: =37-C11 -> 13 | D13: =IFERROR(VLOOKUP($B13,Task!$B$1:$G$67,6,0)," ") -> 0.0055555556 | E13: =IFERROR(D13*C13," ") -> 0.072222222 | F13: =G12 -> 0.43465278 | G13: 0.55398148 | H13: =IF(G13="","", IF(L13=" ",IF(OR(F13=0,G13=0),"",G13-F13),((G13-F13)-L13))) -> 0.067824074 | I13: =IFERROR(IF(L13=" ",(F13+E13),(F13+E13+L13)),"") -> 0.55837963 | L13: 0.05150463 | N13: =IFERROR(E13/H13," ") -> 1.0648464 | P13: =IFERROR(__xludf.DUMMYFUNCTION("""COMPUTED_VALUE"""),45763) -> 45763 | Q13: =IF(SUMIF($A:$A,$P13,$E:$E)=0,"",SUMIF($A:$A,$P13,$E:$E)) -> 0.22361111 | R13: =IF(SUMIF($A:$A,$P13,$H:$H)=0,"",SUMIF($A:$A,$P13,$H:$H)) -> 0.20196759 | S13: =IF(OR(R13="",R13>=$U$1)," ",$U$1-R13) -> 0.13136574 | T13: =IFERROR(AVERAGEIF($A:$A,$P13,$N:$N)," ") -> 1.0998741
A14: 45750 | B14: DAM - Image Search | C14: 6 | D14: =IFERROR(VLOOKUP($B14,Task!$B$1:$G$67,6,0)," ") -> 0.00069444444 | E14: =IFERROR(D14*C14," ") -> 0.0041666667 | F14: =G13 -> 0.55398148 | G14: 0.55771991 | H14: =IF(G14="","", IF(L14=" ",IF(OR(F14=0,G14=0),"",G14-F14),((G14-F14)-L14))) -> 0.0037384259 | I14: =IFERROR(IF(L14=" ",(F14+E14),(F14+E14+L14)),"") -> 0.55814815 | N14: =IFERROR(E14/H14," ") -> 1.1145511 | P14: =IFERROR(__xludf.DUMMYFUNCTION("""COMPUTED_VALUE"""),45764) -> 45764 | Q14: =IF(SUMIF($A:$A,$P14,$E:$E)=0,"",SUMIF($A:$A,$P14,$E:$E)) -> 0.34861111 | R14: =IF(SUMIF($A:$A,$P14,$H:$H)=0,"",SUMIF($A:$A,$P14,$H:$H)) -> 0.31748843 | S14: =IF(OR(R14="",R14>=$U$1)," ",$U$1-R14) -> 0.015844907 | T14: =IFERROR(AVERAGEIF($A:$A,$P14,$N:$N)," ") -> 1.0952073
A15: 45750 | B15: DAM - Image Approval | C15: 65 | D15: =IFERROR(VLOOKUP($B15,Task!$B$1:$G$67,6,0)," ") -> 0.0027777778 | E15: =IFERROR(D15*C15," ") -> 0.18055556 | F15: =G14 -> 0.55771991 | G15: 0.77097222 | H15: =IF(G15="","", IF(L15=" ",IF(OR(F15=0,G15=0),"",G15-F15),((G15-F15)-L15))) -> 0.16961806 | I15: =IFERROR(IF(L15=" ",(F15+E15),(F15+E15+L15)),"") -> 0.78190972 | L15: 0.043634259 | N15: =IFERROR(E15/H15," ") -> 1.0644831 | P15: =IFERROR(__xludf.DUMMYFUNCTION("""COMPUTED_VALUE"""),45769) -> 45769 | Q15: =IF(SUMIF($A:$A,$P15,$E:$E)=0,"",SUMIF($A:$A,$P15,$E:$E)) -> 0.35763889 | R15: =IF(SUMIF($A:$A,$P15,$H:$H)=0,"",SUMIF($A:$A,$P15,$H:$H)) -> 0.32353009 | S15: =IF(OR(R15="",R15>=$U$1)," ",$U$1-R15) -> 0.0098032407 | T15: =IFERROR(AVERAGEIF($A:$A,$P15,$N:$N)," ") -> 1.0985691
A16: 45751 | B16: Nordstrom SQL DATA Dump | C16: 1 | D16: =IFERROR(VLOOKUP($B16,Task!$B$1:$G$67,6,0)," ") -> 0.048611111 | E16: =IFERROR(D16*C16," ") -> 0.048611111 | F16: 0.38006944 | G16: 0.47354167 | H16: =IF(G16="","", IF(L16=" ",IF(OR(F16=0,G16=0),"",G16-F16),((G16-F16)-L16))) -> 0.043969907 | I16: =IFERROR(IF(L16=" ",(F16+E16),(F16+E16+L16)),"") -> 0.47818287 | L16: 0.049502315 | N16: =IFERROR(E16/H16," ") -> 1.1055541 | P16: =IFERROR(__xludf.DUMMYFUNCTION("""COMPUTED_VALUE"""),45770) -> 45770 | Q16: =IF(SUMIF($A:$A,$P16,$E:$E)=0,"",SUMIF($A:$A,$P16,$E:$E)) -> 0.35694444 | R16: =IF(SUMIF($A:$A,$P16,$H:$H)=0,"",SUMIF($A:$A,$P16,$H:$H)) -> 0.32287206 | S16: =IF(OR(R16="",R16>=$U$1)," ",$U$1-R16) -> 0.010461273 | T16: =IFERROR(AVERAGEIF($A:$A,$P16,$N:$N)," ") -> 1.150221
A17: 45751 | B17: DAM - Image Approval | C17: 18 | D17: =IFERROR(VLOOKUP($B17,Task!$B$1:$G$67,6,0)," ") -> 0.0027777778 | E17: =IFERROR(D17*C17," ") -> 0.05 | F17: =G16 -> 0.47354167 | G17: 0.56356481 | H17: =IF(G17="","", IF(L17=" ",IF(OR(F17=0,G17=0),"",G17-F17),((G17-F17)-L17))) -> 0.045868056 | I17: =IFERROR(IF(L17=" ",(F17+E17),(F17+E17+L17)),"") -> 0.56769676 | L17: 0.044155093 | N17: =IFERROR(E17/H17," ") -> 1.0900833 | P17: =IFERROR(__xludf.DUMMYFUNCTION("""COMPUTED_VALUE"""),45771) -> 45771 | Q17: =IF(SUMIF($A:$A,$P17,$E:$E)=0,"",SUMIF($A:$A,$P17,$E:$E)) -> 0.32777778 | R17: =IF(SUMIF($A:$A,$P17,$H:$H)=0,"",SUMIF($A:$A,$P17,$H:$H)) -> 0.297139 | S17: =IF(OR(R17="",R17>=$U$1)," ",$U$1-R17) -> 0.036194329 | T17: =IFERROR(AVERAGEIF($A:$A,$P17,$N:$N)," ") -> 1.1016204
A18: 45751 | B18: Missing information | C18: 24 | D18: =IFERROR(VLOOKUP($B18,Task!$B$1:$G$67,6,0)," ") -> 0.0083333333 | E18: =IFERROR(D18*C18," ") -> 0.2 | F18: =G17 -> 0.56356481 | G18: 0.76041667 | H18: =IF(G18="","", IF(L18=" ",IF(OR(F18=0,G18=0),"",G18-F18),((G18-F18)-L18))) -> 0.18228009 | I18: =IFERROR(IF(L18=" ",(F18+E18),(F18+E18+L18)),"") -> 0.77813657 | L18: 0.014571759 | N18: =IFERROR(E18/H18," ") -> 1.0972125 | P18: =IFERROR(__xludf.DUMMYFUNCTION("""COMPUTED_VALUE"""),45772) -> 45772 | Q18: =IF(SUMIF($A:$A,$P18,$E:$E)=0,"",SUMIF($A:$A,$P18,$E:$E)) -> 0.27847222 | R18: =IF(SUMIF($A:$A,$P18,$H:$H)=0,"",SUMIF($A:$A,$P18,$H:$H)) -> 0.25643822 | S18: =IF(OR(R18="",R18>=$U$1)," ",$U$1-R18) -> 0.076895116 | T18: =IFERROR(AVERAGEIF($A:$A,$P18,$N:$N)," ") -> 1.0832948
A19: 45754 | B19: Nordstrom SQL DATA Dump | C19: 1 | D19: =IFERROR(VLOOKUP($B19,Task!$B$1:$G$67,6,0)," ") -> 0.048611111 | E19: =IFERROR(D19*C19," ") -> 0.048611111 | F19: 0.37636574 | G19: 0.42094907 | H19: =IF(G19="","", IF(L19=" ",IF(OR(F19=0,G19=0),"",G19-F19),((G19-F19)-L19))) -> 0.044583333 | I19: =IFERROR(IF(L19=" ",(F19+E19),(F19+E19+L19)),"") -> 0.42497685 | N19: =IFERROR(E19/H19," ") -> 1.0903427 | P19: =IFERROR(__xludf.DUMMYFUNCTION("""COMPUTED_VALUE"""),45775) -> 45775 | Q19: =IF(SUMIF($A:$A,$P19,$E:$E)=0,"",SUMIF($A:$A,$P19,$E:$E)) -> 0.35 | R19: =IF(SUMIF($A:$A,$P19,$H:$H)=0,"",SUMIF($A:$A,$P19,$H:$H)) -> 0.32163694 | S19: =IF(R19=""," ",$U$1-R19) -> 0.011696389 | T19: =IFERROR(AVERAGEIF($A:$A,$P19,$N:$N)," ") -> 1.0842815
A20: 45754 | B20: Missing information | C20: 16 | D20: =IFERROR(VLOOKUP($B20,Task!$B$1:$G$67,6,0)," ") -> 0.0083333333 | E20: =IFERROR(D20*C20," ") -> 0.13333333 | F20: =G19 -> 0.42094907 | G20: 0.58149306 | H20: =IF(G20="","", IF(L20=" ",IF(OR(F20=0,G20=0),"",G20-F20),((G20-F20)-L20))) -> 0.1296412 | I20: =IFERROR(IF(L20=" ",(F20+E20),(F20+E20+L20)),"") -> 0.58518519 | L20: 0.030902778 | N20: =IFERROR(E20/H20," ") -> 1.0284796 | P20: =IFERROR(__xludf.DUMMYFUNCTION("""COMPUTED_VALUE"""),45776) -> 45776 | Q20: =IF(SUMIF($A:$A,$P20,$E:$E)=0,"",SUMIF($A:$A,$P20,$E:$E)) -> 0.32152778 | R20: =IF(SUMIF($A:$A,$P20,$H:$H)=0,"",SUMIF($A:$A,$P20,$H:$H)) -> 0.29053241 | S20: =IF(R20=""," ",$U$1-R20) -> 0.042800926 | T20: =IFERROR(AVERAGEIF($A:$A,$P20,$N:$N)," ") -> 1.103862
A21: 45754 | B21: DAM - Image Approval | C21: 24 | D21: =IFERROR(VLOOKUP($B21,Task!$B$1:$G$67,6,0)," ") -> 0.0027777778 | E21: =IFERROR(D21*C21," ") -> 0.066666667 | F21: =G20 -> 0.58149306 | G21: 0.66596065 | H21: =IF(G21="","", IF(L21=" ",IF(OR(F21=0,G21=0),"",G21-F21),((G21-F21)-L21))) -> 0.059583333 | I21: =IFERROR(IF(L21=" ",(F21+E21),(F21+E21+L21)),"") -> 0.67304398 | L21: 0.024884259 | N21: =IFERROR(E21/H21," ") -> 1.1188811 | P21: =IFERROR(__xludf.DUMMYFUNCTION("""COMPUTED_VALUE"""),45777) -> 45777 | Q21: =IF(SUMIF($A:$A,$P21,$E:$E)=0,"",SUMIF($A:$A,$P21,$E:$E)) -> 0.32222222 | R21: =IF(SUMIF($A:$A,$P21,$H:$H)=0,"",SUMIF($A:$A,$P21,$H:$H)) -> 0.29389094 | S21: =IF(R21=""," ",$U$1-R21) -> 0.039442396 | T21: =IFERROR(AVERAGEIF($A:$A,$P21,$N:$N)," ") -> 1.0990809
A22: 45754 | B22: OGM - Sizing update | C22: 2 | D22: =IFERROR(VLOOKUP($B22,Task!$B$1:$G$67,6,0)," ") -> 0.0055555556 | E22: =IFERROR(D22*C22," ") -> 0.011111111 | F22: 0.65478009 | G22: 0.66493056 | H22: =IF(G22="","", IF(L22=" ",IF(OR(F22=0,G22=0),"",G22-F22),((G22-F22)-L22))) -> 0.010150463 | I22: =IFERROR(IF(L22=" ",(F22+E22),(F22+E22+L22)),"") -> 0.6658912 | N22: =IFERROR(E22/H22," ") -> 1.0946408 | Q22: =IF(SUMIF($A:$A,$P22,$E:$E)=0,"",SUMIF($A:$A,$P22,$E:$E)) | R22: =IF(SUMIF($A:$A,$P22,$H:$H)=0,"",SUMIF($A:$A,$P22,$H:$H)) | S22: =IF(R22=""," ",$U$1-R22) | T22: =IFERROR(AVERAGEIF($A:$A,$P22,$N:$N)," ")
A23: 45754 | B23: Wholesale Adding Images | C23: 62 | D23: =IFERROR(VLOOKUP($B23,Task!$B$1:$G$67,6,0)," ") -> 0.0013888889 | E23: =IFERROR(D23*C23," ") -> 0.086111111 | F23: =G21 -> 0.66596065 | G23: 0.75694444 | H23: =IF(G23="","", IF(L23=" ",IF(OR(F23=0,G23=0),"",G23-F23),((G23-F23)-L23))) -> 0.077928241 | I23: =IFERROR(IF(L23=" ",(F23+E23),(F23+E23+L23)),"") -> 0.76512731 | L23: 0.013055556 | N23: =IFERROR(E23/H23," ") -> 1.1050052 | Q23: =IF(SUMIF($A:$A,$P23,$E:$E)=0,"",SUMIF($A:$A,$P23,$E:$E)) | R23: =IF(SUMIF($A:$A,$P23,$H:$H)=0,"",SUMIF($A:$A,$P23,$H:$H)) | S23: =IF(R23=""," ",$U$1-R23) | T23: =IFERROR(AVERAGEIF($A:$A,$P23,$N:$N)," ")
A24: 45755 | B24: Nordstrom SQL DATA Dump | C24: 1 | D24: =IFERROR(VLOOKUP($B24,Task!$B$1:$G$67,6,0)," ") -> 0.048611111 | E24: =IFERROR(D24*C24," ") -> 0.048611111 | F24: 0.3816088 | G24: 0.42696759 | H24: =IF(G24="","", IF(L24=" ",IF(OR(F24=0,G24=0),"",G24-F24),((G24-F24)-L24))) -> 0.045358796 | I24: =IFERROR(IF(L24=" ",(F24+E24),(F24+E24+L24)),"") -> 0.43021991 | N24: =IFERROR(E24/H24," ") -> 1.071702
A25: 45755 | B25: Wholesale Adding Images | C25: 24 | D25: =IFERROR(VLOOKUP($B25,Task!$B$1:$G$67,6,0)," ") -> 0.0013888889 | E25: =IFERROR(D25*C25," ") -> 0.033333333 | F25: =G24 -> 0.42696759 | G25: 0.4899537 | H25: =IF(G25="","", IF(L25=" ",IF(OR(F25=0,G25=0),"",G25-F25),((G25-F25)-L25))) -> 0.033321759 | I25: =IFERROR(IF(L25=" ",(F25+E25),(F25+E25+L25)),"") -> 0.48996528 | L25: 0.029664352 | N25: =IFERROR(E25/H25," ") -> 1.0003473
A26: 45755 | B26: DAM - Image Approval | C26: 75 | D26: =IFERROR(VLOOKUP($B26,Task!$B$1:$G$67,6,0)," ") -> 0.0027777778 | E26: =IFERROR(D26*C26," ") -> 0.20833333 | F26: =G25 -> 0.4899537 | G26: 0.71796296 | H26: =IF(G26="","", IF(L26=" ",IF(OR(F26=0,G26=0),"",G26-F26),((G26-F26)-L26))) -> 0.19380787 | I26: =IFERROR(IF(L26=" ",(F26+E26),(F26+E26+L26)),"") -> 0.73248843 | L26: 0.034201389 | N26: =IFERROR(E26/H26," ") -> 1.0749477
A27: 45755 | B27: OGM - Sizing update | C27: 9 | D27: =IFERROR(VLOOKUP($B27,Task!$B$1:$G$67,6,0)," ") -> 0.0055555556 | E27: =IFERROR(D27*C27," ") -> 0.05 | F27: =G26 -> 0.71796296 | G27: 0.76106499 | H27: =IF(G27="","", IF(L27=" ",IF(OR(F27=0,G27=0),"",G27-F27),((G27-F27)-L27))) -> 0.043102025 | I27: =IFERROR(IF(L27=" ",(F27+E27),(F27+E27+L27)),"") -> 0.76796296 | N27: =IFERROR(E27/H27," ") -> 1.1600383
A28: 45756 | B28: Nordstrom SQL DATA Dump | C28: 1 | D28: =IFERROR(VLOOKUP($B28,Task!$B$1:$G$67,6,0)," ") -> 0.048611111 | E28: =IFERROR(D28*C28," ") -> 0.048611111 | F28: 0.38349537 | G28: 0.42813657 | H28: =IF(G28="","", IF(L28=" ",IF(OR(F28=0,G28=0),"",G28-F28),((G28-F28)-L28))) -> 0.044641204 | I28: =IFERROR(IF(L28=" ",(F28+E28),(F28+E28+L28)),"") -> 0.43210648 | N28: =IFERROR(E28/H28," ") -> 1.0889292
A29: 45756 | B29: OGM - Sizing update | C29: 19 | D29: =IFERROR(VLOOKUP($B29,Task!$B$1:$G$67,6,0)," ") -> 0.0055555556 | E29: =IFERROR(D29*C29," ") -> 0.10555556 | F29: =G28 -> 0.42813657 | G29: 0.57020833 | H29: =IF(G29="","", IF(L29=" ",IF(OR(F29=0,G29=0),"",G29-F29),((G29-F29)-L29))) -> 0.099513889 | I29: =IFERROR(IF(L29=" ",(F29+E29),(F29+E29+L29)),"") -> 0.57625 | L29: 0.04255787 | N29: =IFERROR(E29/H29," ") -> 1.0607118
A30: 45756 | B30: Very Invoice Report | C30: 1 | D30: =IFERROR(VLOOKUP($B30,Task!$B$1:$G$67,6,0)," ") -> 0.020833333 | E30: =IFERROR(D30*C30," ") -> 0.020833333 | F30: 0.48592593 | G30: 0.50517361 | H30: =IF(G30="","", IF(L30=" ",IF(OR(F30=0,G30=0),"",G30-F30),((G30-F30)-L30))) -> 0.019247685 | I30: =IFERROR(IF(L30=" ",(F30+E30),(F30+E30+L30)),"") -> 0.50675926 | N30: =IFERROR(E30/H30," ") -> 1.0823812
A31: 45756 | B31: OGM - Sizing update | C31: 20 | D31: =IFERROR(VLOOKUP($B31,Task!$B$1:$G$67,6,0)," ") -> 0.0055555556 | E31: =IFERROR(D31*C31," ") -> 0.11111111 | F31: 0.57020833 | G31: 0.6890625 | H31: =IF(G31="","", IF(L31=" ",IF(OR(F31=0,G31=0),"",G31-F31),((G31-F31)-L31))) -> 0.10510417 | I31: =IFERROR(IF(L31=" ",(F31+E31),(F31+E31+L31)),"") -> 0.69506944 | L31: 0.01375 | N31: =IFERROR(E31/H31," ") -> 1.0571523
A32: 45756 | B32: DAM - Image Approval | C32: 20 | D32: =IFERROR(VLOOKUP($B32,Task!$B$1:$G$67,6,0)," ") -> 0.0027777778 | E32: =IFERROR(D32*C32," ") -> 0.055555556 | F32: =G31 -> 0.6890625 | G32: 0.76388889 | H32: =IF(G32="","", IF(L32=" ",IF(OR(F32=0,G32=0),"",G32-F32),((G32-F32)-L32))) -> 0.052534722 | I32: =IFERROR(IF(L32=" ",(F32+E32),(F32+E32+L32)),"") -> 0.76690972 | L32: 0.022291667 | N32: =IFERROR(E32/H32," ") -> 1.0575017
A33: 45757 | B33: Wholesale Adding Images | C33: 41 | D33: =IFERROR(VLOOKUP($B33,Task!$B$1:$G$67,6,0)," ") -> 0.0013888889 | E33: =IFERROR(D33*C33," ") -> 0.056944444 | F33: 0.38778935 | G33: 0.43996528 | H33: =IF(G33="","", IF(L33=" ",IF(OR(F33=0,G33=0),"",G33-F33),((G33-F33)-L33))) -> 0.052175926 | I33: =IFERROR(IF(L33=" ",(F33+E33),(F33+E33+L33)),"") -> 0.4447338 | N33: =IFERROR(E33/H33," ") -> 1.0913931
A34: 45757 | B34: Nordstrom SQL DATA Dump | C34: 1 | D34: =IFERROR(VLOOKUP($B34,Task!$B$1:$G$67,6,0)," ") -> 0.048611111 | E34: =IFERROR(D34*C34," ") -> 0.048611111 | F34: =G33 -> 0.43996528 | G34: 0.50768519 | H34: =IF(G34="","", IF(L34=" ",IF(OR(F34=0,G34=0),"",G34-F34),((G34-F34)-L34))) -> 0.044513889 | I34: =IFERROR(IF(L34=" ",(F34+E34),(F34+E34+L34)),"") -> 0.51178241 | L34: 0.023206019 | N34: =IFERROR(E34/H34," ") -> 1.0920437
A35: 45757 | B35: Wholesale Data Enrichment Report | C35: 1 | D35: =IFERROR(VLOOKUP($B35,Task!$B$1:$G$67,6,0)," ") -> 0.020833333 | E35: =IFERROR(D35*C35," ") -> 0.020833333 | F35: =G34 -> 0.50768519 | G35: 0.52667824 | H35: =IF(G35="","", IF(L35=" ",IF(OR(F35=0,G35=0),"",G35-F35),((G35-F35)-L35))) -> 0.018993056 | I35: =IFERROR(IF(L35=" ",(F35+E35),(F35+E35+L35)),"") -> 0.52851852 | N35: =IFERROR(E35/H35," ") -> 1.0968921
A36: 45757 | B36: Wholesale Adding Images | C36: 129 | D36: =IFERROR(VLOOKUP($B36,Task!$B$1:$G$67,6,0)," ") -> 0.0013888889 | E36: =IFERROR(D36*C36," ") -> 0.17916667 | F36: =G35 -> 0.52667824 | G36: 0.72503472 | H36: =IF(G36="","", IF(L36=" ",IF(OR(F36=0,G36=0),"",G36-F36),((G36-F36)-L36))) -> 0.1684375 | I36: =IFERROR(IF(L36=" ",(F36+E36),(F36+E36+L36)),"") -> 0.73576389 | L36: 0.029918981 | N36: =IFERROR(E36/H36," ") -> 1.0636982
A37: 45757 | B37: DAM - Image Approval | C37: 16 | D37: =IFERROR(VLOOKUP($B37,Task!$B$1:$G$67,6,0)," ") -> 0.0027777778 | E37: =IFERROR(D37*C37," ") -> 0.044444444 | F37: =G36 -> 0.72503472 | G37: 0.76527091 | H37: =IF(G37="","", IF(L37=" ",IF(OR(F37=0,G37=0),"",G37-F37),((G37-F37)-L37))) -> 0.040236192 | I37: =IFERROR(IF(L37=" ",(F37+E37),(F37+E37+L37)),"") -> 0.76947917 | N37: =IFERROR(E37/H37," ") -> 1.1045887
A38: 45758 | B38: Nordstrom SQL DATA Dump | C38: 1 | D38: =IFERROR(VLOOKUP($B38,Task!$B$1:$G$67,6,0)," ") -> 0.048611111 | E38: =IFERROR(D38*C38," ") -> 0.048611111 | F38: 0.33827546 | G38: 0.38221065 | H38: =IF(G38="","", IF(L38=" ",IF(OR(F38=0,G38=0),"",G38-F38),((G38-F38)-L38))) -> 0.043935185 | I38: =IFERROR(IF(L38=" ",(F38+E38),(F38+E38+L38)),"") -> 0.38688657 | N38: =IFERROR(E38/H38," ") -> 1.1064278
A39: 45758 | B39: OGM - Sizing update | C39: 19 | D39: =IFERROR(VLOOKUP($B39,Task!$B$1:$G$67,6,0)," ") -> 0.0055555556 | E39: =IFERROR(D39*C39," ") -> 0.10555556 | F39: =G38 -> 0.38221065 | G39: 0.52688657 | H39: =IF(G39="","", IF(L39=" ",IF(OR(F39=0,G39=0),"",G39-F39),((G39-F39)-L39))) -> 0.094930556 | I39: =IFERROR(IF(L39=" ",(F39+E39),(F39+E39+L39)),"") -> 0.53751157 | L39: 0.04974537 | N39: =IFERROR(E39/H39," ") -> 1.1119239
A40: 45758 | B40: DAM - Image Approval | C40: 60 | D40: =IFERROR(VLOOKUP($B40,Task!$B$1:$G$67,6,0)," ") -> 0.0027777778 | E40: =IFERROR(D40*C40," ") -> 0.16666667 | F40: =G39 -> 0.52688657 | G40: 0.71527778 | H40: =IF(G40="","", IF(L40=" ",IF(OR(F40=0,G40=0),"",G40-F40),((G40-F40)-L40))) -> 0.15222222 | I40: =IFERROR(IF(L40=" ",(F40+E40),(F40+E40+L40)),"") -> 0.72972222 | L40: 0.036168981 | N40: =IFERROR(E40/H40," ") -> 1.0948905
A41: 45761 | B41: Nordstrom SQL DATA Dump | C41: 2 | D41: =IFERROR(VLOOKUP($B41,Task!$B$1:$G$67,6,0)," ") -> 0.048611111 | E41: =IFERROR(D41*C41," ") -> 0.097222222 | F41: 0.38716435 | G41: 0.4959375 | H41: =IF(G41="","", IF(L41=" ",IF(OR(F41=0,G41=0),"",G41-F41),((G41-F41)-L41))) -> 0.089016204 | I41: =IFERROR(IF(L41=" ",(F41+E41),(F41+E41+L41)),"") -> 0.50414352 | L41: 0.019756944 | N41: =IFERROR(E41/H41," ") -> 1.0921857
A42: 45761 | B42: OGM - Sizing update | C42: 29 | D42: =IFERROR(VLOOKUP($B42,Task!$B$1:$G$67,6,0)," ") -> 0.0055555556 | E42: =IFERROR(D42*C42," ") -> 0.16111111 | F42: =G41 -> 0.4959375 | G42: 0.66563657 | H42: =IF(G42="","", IF(L42=" ",IF(OR(F42=0,G42=0),"",G42-F42),((G42-F42)-L42))) -> 0.15395833 | I42: =IFERROR(IF(L42=" ",(F42+E42),(F42+E42+L42)),"") -> 0.67278935 | L42: 0.015740741 | N42: =IFERROR(E42/H42," ") -> 1.0464592
A43: 45761 | B43: OGM - Sizing update | C43: 16 | D43: =IFERROR(VLOOKUP($B43,Task!$B$1:$G$67,6,0)," ") -> 0.0055555556 | E43: =IFERROR(D43*C43," ") -> 0.088888889 | F43: =G42 -> 0.66563657 | G43: 0.77083333 | H43: =IF(G43="","", IF(L43=" ",IF(OR(F43=0,G43=0),"",G43-F43),((G43-F43)-L43))) -> 0.080590278 | I43: =IFERROR(IF(L43=" ",(F43+E43),(F43+E43+L43)),"") -> 0.77913194 | L43: 0.024606481 | N43: =IFERROR(E43/H43," ") -> 1.1029729
A44: 45762 | B44: Nordstrom SQL DATA Dump | C44: 3 | D44: =IFERROR(VLOOKUP($B44,Task!$B$1:$G$67,6,0)," ") -> 0.048611111 | E44: =IFERROR(D44*C44," ") -> 0.14583333 | F44: 0.37546296 | G44: 0.61847222 | H44: =IF(G44="","", IF(L44=" ",IF(OR(F44=0,G44=0),"",G44-F44),((G44-F44)-L44))) -> 0.13269676 | I44: =IFERROR(IF(L44=" ",(F44+E44),(F44+E44+L44)),"") -> 0.6316088 | L44: 0.1103125 | N44: =IFERROR(E44/H44," ") -> 1.0989969
A45: 45762 | B45: DAM - Image Approval | C45: 40 | D45: =IFERROR(VLOOKUP($B45,Task!$B$1:$G$67,6,0)," ") -> 0.0027777778 | E45: =IFERROR(D45*C45," ") -> 0.11111111 | F45: =G44 -> 0.61847222 | G45: 0.75400476 | H45: =IF(G45="","", IF(L45=" ",IF(OR(F45=0,G45=0),"",G45-F45),((G45-F45)-L45))) -> 0.10299781 | I45: =IFERROR(IF(L45=" ",(F45+E45),(F45+E45+L45)),"") -> 0.76211806 | L45: 0.032534722 | N45: =IFERROR(E45/H45," ") -> 1.0787716
A46: 45763 | B46: Nordstrom SQL DATA Dump | C46: 2 | D46: =IFERROR(VLOOKUP($B46,Task!$B$1:$G$67,6,0)," ") -> 0.048611111 | E46: =IFERROR(D46*C46," ") -> 0.097222222 | F46: 0.3794213 | G46: 0.47240741 | H46: =IF(G46="","", IF(L46=" ",IF(OR(F46=0,G46=0),"",G46-F46),((G46-F46)-L46))) -> 0.088506944 | I46: =IFERROR(IF(L46=" ",(F46+E46),(F46+E46+L46)),"") -> 0.48112269 | L46: 0.0044791667 | N46: =IFERROR(E46/H46," ") -> 1.09847
A47: 45763 | B47: DAM - Image Approval | C47: 13 | D47: =IFERROR(VLOOKUP($B47,Task!$B$1:$G$67,6,0)," ") -> 0.0027777778 | E47: =IFERROR(D47*C47," ") -> 0.036111111 | F47: =G46 -> 0.47240741 | G47: 0.55252315 | H47: =IF(G47="","", IF(L47=" ",IF(OR(F47=0,G47=0),"",G47-F47),((G47-F47)-L47))) -> 0.033946759 | I47: =IFERROR(IF(L47=" ",(F47+E47),(F47+E47+L47)),"") -> 0.5546875 | L47: 0.046168981 | N47: =IFERROR(E47/H47," ") -> 1.0637572
A48: 45763 | B48: Wholesale Data Enrichment Report | C48: 1 | D48: =IFERROR(VLOOKUP($B48,Task!$B$1:$G$67,6,0)," ") -> 0.020833333 | E48: =IFERROR(D48*C48," ") -> 0.020833333 | F48: =G47 -> 0.55252315 | G48: 0.61938657 | H48: =IF(G48="","", IF(L48=" ",IF(OR(F48=0,G48=0),"",G48-F48),((G48-F48)-L48))) -> 0.019178241 | I48: =IFERROR(IF(L48=" ",(F48+E48),(F48+E48+L48)),"") -> 0.62104167 | L48: 0.047685185 | N48: =IFERROR(E48/H48," ") -> 1.0863005
A49: 45763 | B49: DAM - Image Approval | C49: 25 | D49: =IFERROR(VLOOKUP($B49,Task!$B$1:$G$67,6,0)," ") -> 0.0027777778 | E49: =IFERROR(D49*C49," ") -> 0.069444444 | F49: =G48 -> 0.61938657 | G49: 0.76041667 | H49: =IF(G49="","", IF(L49=" ",IF(OR(F49=0,G49=0),"",G49-F49),((G49-F49)-L49))) -> 0.060335648 | I49: =IFERROR(IF(L49=" ",(F49+E49),(F49+E49+L49)),"") -> 0.76952546 | L49: 0.080694444 | M49: New WIP Task | N49: =IFERROR(E49/H49," ") -> 1.1509687
A50: 45764 | B50: Nordstrom SQL DATA Dump | C50: 1 | D50: =IFERROR(VLOOKUP($B50,Task!$B$1:$G$67,6,0)," ") -> 0.048611111 | E50: =IFERROR(D50*C50," ") -> 0.048611111 | F50: 0.38266204 | G50: 0.42700231 | H50: =IF(G50="","", IF(L50=" ",IF(OR(F50=0,G50=0),"",G50-F50),((G50-F50)-L50))) -> 0.044340278 | I50: =IFERROR(IF(L50=" ",(F50+E50),(F50+E50+L50)),"") -> 0.43127315 | N50: =IFERROR(E50/H50," ") -> 1.0963195
A51: 45764 | B51: OGM - Sizing update | C51: 12 | D51: =IFERROR(VLOOKUP($B51,Task!$B$1:$G$67,6,0)," ") -> 0.0055555556 | E51: =IFERROR(D51*C51," ") -> 0.066666667 | F51: =G50 -> 0.42700231 | G51: 0.51163194 | H51: =IF(G51="","", IF(L51=" ",IF(OR(F51=0,G51=0),"",G51-F51),((G51-F51)-L51))) -> 0.061273148 | I51: =IFERROR(IF(L51=" ",(F51+E51),(F51+E51+L51)),"") -> 0.51702546 | L51: 0.023356481 | N51: =IFERROR(E51/H51," ") -> 1.0880242
A52: 45764 | B52: Missing information | C52: 28 | D52: =IFERROR(VLOOKUP($B52,Task!$B$1:$G$67,6,0)," ") -> 0.0083333333 | E52: =IFERROR(D52*C52," ") -> 0.23333333 | F52: =G51 -> 0.51163194 | G52: 0.76041667 | H52: =IF(G52="","", IF(L52=" ",IF(OR(F52=0,G52=0),"",G52-F52),((G52-F52)-L52))) -> 0.211875 | I52: =IFERROR(IF(L52=" ",(F52+E52),(F52+E52+L52)),"") -> 0.781875 | L52: 0.036909722 | N52: =IFERROR(E52/H52," ") -> 1.1012783
A53: 45769 | B53: Missing information | C53: 14 | D53: =IFERROR(VLOOKUP($B53,Task!$B$1:$G$67,6,0)," ") -> 0.0083333333 | E53: =IFERROR(D53*C53," ") -> 0.11666667 | F53: 0.34671296 | G53: 0.48438657 | H53: =IF(G53="","", IF(L53=" ",IF(OR(F53=0,G53=0),"",G53-F53),((G53-F53)-L53))) -> 0.1055787 | I53: =IFERROR(IF(L53=" ",(F53+E53),(F53+E53+L53)),"") -> 0.49547454 | L53: 0.032094907 | N53: =IFERROR(E53/H53," ") -> 1.1050208
A54: 45769 | B54: SQL Data Dump | C54: 2 | D54: =IFERROR(VLOOKUP($B54,Task!$B$1:$G$67,6,0)," ") -> 0.048611111 | E54: =IFERROR(D54*C54," ") -> 0.097222222 | F54: =G53 -> 0.48438657 | G54: 0.57422454 | H54: =IF(G54="","", IF(L54=" ",IF(OR(F54=0,G54=0),"",G54-F54),((G54-F54)-L54))) -> 0.089837963 | I54: =IFERROR(IF(L54=" ",(F54+E54),(F54+E54+L54)),"") -> 0.5816088 | N54: =IFERROR(E54/H54," ") -> 1.0821953
A55: 45769 | B55: Missing information | C55: 16 | D55: =IFERROR(VLOOKUP($B55,Task!$B$1:$G$67,6,0)," ") -> 0.0083333333 | E55: =IFERROR(D55*C55," ") -> 0.13333333 | F55: =G54 -> 0.57422454 | G55: 0.72916667 | H55: =IF(G55="","", IF(L55=" ",IF(OR(F55=0,G55=0),"",G55-F55),((G55-F55)-L55))) -> 0.1184838 | I55: =IFERROR(IF(L55=" ",(F55+E55),(F55+E55+L55)),"") -> 0.7440162 | L55: 0.036458333 | N55: =IFERROR(E55/H55," ") -> 1.1253297
A56: 45769 | B56: D2 Delivery Master sheet | C56: 1 | D56: =IFERROR(VLOOKUP($B56,Task!$B$1:$G$67,6,0)," ") -> 0.010416667 | E56: =IFERROR(D56*C56," ") -> 0.010416667 | F56: 0.66545139 | G56: 0.67508102 | H56: =IF(G56="","", IF(L56=" ",IF(OR(F56=0,G56=0),"",G56-F56),((G56-F56)-L56))) -> 0.0096296296 | I56: =IFERROR(IF(L56=" ",(F56+E56),(F56+E56+L56)),"") -> 0.67586806 | N56: =IFERROR(E56/H56," ") -> 1.0817308
A57: 45770 | B57: Very Invoice Report | C57: 1 | D57: =IFERROR(VLOOKUP($B57,Task!$B$1:$G$67,6,0)," ") -> 0.020833333 | E57: =IFERROR(D57*C57," ") -> 0.020833333 | F57: 0.33107639 | G57: 0.35013889 | H57: =IF(G57="","", IF(L57=" ",IF(OR(F57=0,G57=0),"",G57-F57),((G57-F57)-L57))) -> 0.0190625 | I57: =IFERROR(IF(L57=" ",(F57+E57),(F57+E57+L57)),"") -> 0.35190972 | N57: =IFERROR(E57/H57," ") -> 1.0928962
A58: 45770 | B58: Missing information | C58: 27 | D58: =IFERROR(VLOOKUP($B58,Task!$B$1:$G$67,6,0)," ") -> 0.0083333333 | E58: =IFERROR(D58*C58," ") -> 0.225 | F58: =G57 -> 0.35013889 | G58: 0.60422454 | H58: =IF(G58="","", IF(L58=" ",IF(OR(F58=0,G58=0),"",G58-F58),((G58-F58)-L58))) -> 0.20324074 | I58: =IFERROR(IF(L58=" ",(F58+E58),(F58+E58+L58)),"") -> 0.6259838 | L58: 0.050844907 | N58: =IFERROR(E58/H58," ") -> 1.1070615
A59: 45770 | B59: SQL Data Dump | C59: 2 | D59: =IFERROR(VLOOKUP($B59,Task!$B$1:$G$67,6,0)," ") -> 0.048611111 | E59: =IFERROR(D59*C59," ") -> 0.097222222 | F59: =G58 -> 0.60422454 | G59: 0.70974537 | H59: =IF(G59="","", IF(L59=" ",IF(OR(F59=0,G59=0),"",G59-F59),((G59-F59)-L59))) -> 0.09005787 | I59: =IFERROR(IF(L59=" ",(F59+E59),(F59+E59+L59)),"") -> 0.71690972 | L59: 0.015462963 | N59: =IFERROR(E59/H59," ") -> 1.0795528
A60: 45770 | B60: Wholesale Adding Images | C60: 10 | D60: =IFERROR(VLOOKUP($B60,Task!$B$1:$G$67,6,0)," ") -> 0.0013888889 | E60: =IFERROR(D60*C60," ") -> 0.013888889 | F60: =G59 -> 0.70974537 | G60: 0.72025632 | H60: =IF(G60="","", IF(L60=" ",IF(OR(F60=0,G60=0),"",G60-F60),((G60-F60)-L60))) -> 0.010510949 | I60: =IFERROR(IF(L60=" ",(F60+E60),(F60+E60+L60)),"") -> 0.72363426 | N60: =IFERROR(E60/H60," ") -> 1.3213734
A61: 45771 | B61: OGM - Sizing update | C61: 24 | D61: =IFERROR(VLOOKUP($B61,Task!$B$1:$G$67,6,0)," ") -> 0.0055555556 | E61: =IFERROR(D61*C61," ") -> 0.13333333 | F61: 0.34070602 | G61: 0.49144676 | H61: =IF(G61="","", IF(L61=" ",IF(OR(F61=0,G61=0),"",G61-F61),((G61-F61)-L61))) -> 0.12195602 | I61: =IFERROR(IF(L61=" ",(F61+E61),(F61+E61+L61)),"") -> 0.50282407 | L61: 0.028784722 | N61: =IFERROR(E61/H61," ") -> 1.0932903
A62: 45771 | B62: Wholesale Adding Images | C62: 140 | D62: =IFERROR(VLOOKUP($B62,Task!$B$1:$G$67,6,0)," ") -> 0.0013888889 | E62: =IFERROR(D62*C62," ") -> 0.19444444 | F62: =G61 -> 0.49144676 | G62: 0.7203566 | H62: =IF(G62="","", IF(L62=" ",IF(OR(F62=0,G62=0),"",G62-F62),((G62-F62)-L62))) -> 0.17518299 | I62: =IFERROR(IF(L62=" ",(F62+E62),(F62+E62+L62)),"") -> 0.73961806 | L62: 0.053726852 | N62: =IFERROR(E62/H62," ") -> 1.1099505
A63: 45772 | B63: SQL Data Dump | C63: 2 | D63: =IFERROR(VLOOKUP($B63,Task!$B$1:$G$67,6,0)," ") -> 0.048611111 | E63: =IFERROR(D63*C63," ") -> 0.097222222 | F63: 0.33568287 | G63: 0.45253472 | H63: =IF(G63="","", IF(L63=" ",IF(OR(F63=0,G63=0),"",G63-F63),((G63-F63)-L63))) -> 0.092708333 | I63: =IFERROR(IF(L63=" ",(F63+E63),(F63+E63+L63)),"") -> 0.45704861 | L63: 0.024143519 | N63: =IFERROR(E63/H63," ") -> 1.0486891
A64: 45772 | B64: OGM - Sizing update | C64: 22 | D64: =IFERROR(VLOOKUP($B64,Task!$B$1:$G$67,6,0)," ") -> 0.0055555556 | E64: =IFERROR(D64*C64," ") -> 0.12222222 | F64: =G63 -> 0.45253472 | G64: 0.66771991 | H64: =IF(G64="","", IF(L64=" ",IF(OR(F64=0,G64=0),"",G64-F64),((G64-F64)-L64))) -> 0.10914352 | I64: =IFERROR(IF(L64=" ",(F64+E64),(F64+E64+L64)),"") -> 0.68079861 | L64: 0.10604167 | N64: =IFERROR(E64/H64," ") -> 1.1198303
A65: 45772 | B65: DAM - Image Search | C65: 85 | D65: =IFERROR(VLOOKUP($B65,Task!$B$1:$G$67,6,0)," ") -> 0.00069444444 | E65: =IFERROR(D65*C65," ") -> 0.059027778 | F65: =G64 -> 0.66771991 | G65: 0.72230627 | H65: =IF(G65="","", IF(L65=" ",IF(OR(F65=0,G65=0),"",G65-F65),((G65-F65)-L65))) -> 0.054586366 | I65: =IFERROR(IF(L65=" ",(F65+E65),(F65+E65+L65)),"") -> 0.72674769 | N65: =IFERROR(E65/H65," ") -> 1.0813649
A66: 45775 | B66: SQL Data Dump | C66: 1 | D66: =IFERROR(VLOOKUP($B66,Task!$B$1:$G$67,6,0)," ") -> 0.048611111 | E66: =IFERROR(D66*C66," ") -> 0.048611111 | F66: 0.34332176 | G66: 0.38858796 | H66: =IF(G66="","", IF(L66=" ",IF(OR(F66=0,G66=0),"",G66-F66),((G66-F66)-L66))) -> 0.045266204 | I66: =IFERROR(IF(L66=" ",(F66+E66),(F66+E66+L66)),"") -> 0.39193287 | N66: =IFERROR(E66/H66," ") -> 1.0738941
A67: 45775 | B67: Wholesale Adding Images | C67: 50 | D67: =IFERROR(VLOOKUP($B67,Task!$B$1:$G$67,6,0)," ") -> 0.0013888889 | E67: =IFERROR(D67*C67," ") -> 0.069444444 | F67: =G66 -> 0.38858796 | G67: 0.47366898 | H67: =IF(G67="","", IF(L67=" ",IF(OR(F67=0,G67=0),"",G67-F67),((G67-F67)-L67))) -> 0.063854167 | I67: =IFERROR(IF(L67=" ",(F67+E67),(F67+E67+L67)),"") -> 0.47925926 | L67: 0.021226852 | N67: =IFERROR(E67/H67," ") -> 1.0875476
A68: 45775 | B68: Nordstrom SQL DATA Dump | C68: 1 | D68: =IFERROR(VLOOKUP($B68,Task!$B$1:$G$67,6,0)," ") -> 0.048611111 | E68: =IFERROR(D68*C68," ") -> 0.048611111 | F68: =G67 -> 0.47366898 | G68: 0.52798611 | H68: =IF(G68="","", IF(L68=" ",IF(OR(F68=0,G68=0),"",G68-F68),((G68-F68)-L68))) -> 0.044826389 | I68: =IFERROR(IF(L68=" ",(F68+E68),(F68+E68+L68)),"") -> 0.53177083 | L68: 0.0094907407 | N68: =IFERROR(E68/H68," ") -> 1.0844307
A69: 45775 | B69: Wholesale Adding Images | C69: 47 | D69: =IFERROR(VLOOKUP($B69,Task!$B$1:$G$67,6,0)," ") -> 0.0013888889 | E69: =IFERROR(D69*C69," ") -> 0.065277778 | F69: =G68 -> 0.52798611 | G69: 0.58914352 | H69: =IF(G69="","", IF(L69=" ",IF(OR(F69=0,G69=0),"",G69-F69),((G69-F69)-L69))) -> 0.061157407 | I69: =IFERROR(IF(L69=" ",(F69+E69),(F69+E69+L69)),"") -> 0.59326389 | M69: WIP | N69: =IFERROR(E69/H69," ") -> 1.0673732
A70: 45775 | B70: Wholesale Adding Images | C70: 85 | D70: =IFERROR(VLOOKUP($B70,Task!$B$1:$G$67,6,0)," ") -> 0.0013888889 | E70: =IFERROR(D70*C70," ") -> 0.11805556 | F70: =G69 -> 0.58914352 | G70: 0.7302712 | H70: =IF(G70="","", IF(L70=" ",IF(OR(F70=0,G70=0),"",G70-F70),((G70-F70)-L70))) -> 0.10653278 | I70: =IFERROR(IF(L70=" ",(F70+E70),(F70+E70+L70)),"") -> 0.74179398 | L70: 0.034594907 | N70: =IFERROR(E70/H70," ") -> 1.1081618
A71: 45776 | B71: Nordstrom SQL DATA Dump | C71: 1 | D71: =IFERROR(VLOOKUP($B71,Task!$B$1:$G$67,6,0)," ") -> 0.048611111 | E71: =IFERROR(D71*C71," ") -> 0.048611111 | F71: 0.34165509 | G71: 0.38648148 | H71: =IF(G71="","", IF(L71=" ",IF(OR(F71=0,G71=0),"",G71-F71),((G71-F71)-L71))) -> 0.044826389 | I71: =IFERROR(IF(L71=" ",(F71+E71),(F71+E71+L71)),"") -> 0.3902662 | N71: =IFERROR(E71/H71," ") -> 1.0844307
A72: 45776 | B72: OGM - Sizing update | C72: 9 | D72: =IFERROR(VLOOKUP($B72,Task!$B$1:$G$67,6,0)," ") -> 0.0055555556 | E72: =IFERROR(D72*C72," ") -> 0.05 | F72: 0.3866088 | G72: 0.47265046 | H72: =IF(G72="","", IF(L72=" ",IF(OR(F72=0,G72=0),"",G72-F72),((G72-F72)-L72))) -> 0.045532407 | I72: =IFERROR(IF(L72=" ",(F72+E72),(F72+E72+L72)),"") -> 0.47711806 | L72: 0.040509259 | N72: =IFERROR(E72/H72," ") -> 1.098119
A73: 45776 | B73: DAM - Image Approval | C73: 44 | D73: =IFERROR(VLOOKUP($B73,Task!$B$1:$G$67,6,0)," ") -> 0.0027777778 | E73: =IFERROR(D73*C73," ") -> 0.12222222 | F73: =G72 -> 0.47265046 | G73: 0.58409722 | H73: =IF(G73="","", IF(L73=" ",IF(OR(F73=0,G73=0),"",G73-F73),((G73-F73)-L73))) -> 0.11144676 | I73: =IFERROR(IF(L73=" ",(F73+E73),(F73+E73+L73)),"") -> 0.59487269 | N73: =IFERROR(E73/H73," ") -> 1.0966871
A74: 45776 | B74: DAM - Image Search | C74: 49 | D74: =IFERROR(VLOOKUP($B74,Task!$B$1:$G$67,6,0)," ") -> 0.00069444444 | E74: =IFERROR(D74*C74," ") -> 0.034027778 | F74: =G73 -> 0.58409722 | G74: 0.62074074 | H74: =IF(G74="","", IF(L74=" ",IF(OR(F74=0,G74=0),"",G74-F74),((G74-F74)-L74))) -> 0.031076389 | I74: =IFERROR(IF(L74=" ",(F74+E74),(F74+E74+L74)),"") -> 0.62369213 | L74: 0.0055671296 | N74: =IFERROR(E74/H74," ") -> 1.0949721
A75: 45776 | B75: Wholesale Adding Images | C75: 42 | D75: =IFERROR(VLOOKUP($B75,Task!$B$1:$G$67,6,0)," ") -> 0.0013888889 | E75: =IFERROR(D75*C75," ") -> 0.058333333 | F75: =G74 -> 0.62074074 | G75: 0.67381828 | H75: =IF(G75="","", IF(L75=" ",IF(OR(F75=0,G75=0),"",G75-F75),((G75-F75)-L75))) -> 0.049940961 | I75: =IFERROR(IF(L75=" ",(F75+E75),(F75+E75+L75)),"") -> 0.68221065 | L75: 0.0031365741 | N75: =IFERROR(E75/H75," ") -> 1.1680459
A76: 45776 | B76: Missing information | C76: 1 | D76: =IFERROR(VLOOKUP($B76,Task!$B$1:$G$67,6,0)," ") -> 0.0083333333 | E76: =IFERROR(D76*C76," ") -> 0.0083333333 | F76: =G75 -> 0.67381828 | G76: 0.72202546 | H76: =IF(G76="","", IF(L76=" ",IF(OR(F76=0,G76=0),"",G76-F76),((G76-F76)-L76))) -> 0.0077095023 | I76: =IFERROR(IF(L76=" ",(F76+E76),(F76+E76+L76)),"") -> 0.72264929 | K76: 0.010347222 | L76: 0.040497685 | N76: =IFERROR(E76/H76," ") -> 1.0809172
A77: 45777 | B77: Missing information | C77: 6 | D77: =IFERROR(VLOOKUP($B77,Task!$B$1:$G$67,6,0)," ") -> 0.0083333333 | E77: =IFERROR(D77*C77," ") -> 0.05 | F77: 0.3384375 | G77: 0.40524306 | H77: =IF(G77="","", IF(L77=" ",IF(OR(F77=0,G77=0),"",G77-F77),((G77-F77)-L77))) -> 0.045405093 | I77: =IFERROR(IF(L77=" ",(F77+E77),(F77+E77+L77)),"") -> 0.40983796 | L77: 0.021400463 | N77: =IFERROR(E77/H77," ") -> 1.1011981
A78: 45777 | B78: DAM - Image Search | C78: 34 | D78: =IFERROR(VLOOKUP($B78,Task!$B$1:$G$67,6,0)," ") -> 0.00069444444 | E78: =IFERROR(D78*C78," ") -> 0.023611111 | F78: 0.38273148 | G78: 0.40413194 | H78: =IF(G78="","", IF(L78=" ",IF(OR(F78=0,G78=0),"",G78-F78),((G78-F78)-L78))) -> 0.021400463 | I78: =IFERROR(IF(L78=" ",(F78+E78),(F78+E78+L78)),"") -> 0.40634259 | N78: =IFERROR(E78/H78," ") -> 1.1032991 | O78: =AVERAGEIF(A:A,TODAY(),N:N) -> #DIV/0!
A79: 45777 | B79: Nordstrom SQL DATA Dump | C79: 1 | D79: =IFERROR(VLOOKUP($B79,Task!$B$1:$G$67,6,0)," ") -> 0.048611111 | E79: =IFERROR(D79*C79," ") -> 0.048611111 | F79: 0.40534722 | G79: 0.47908565 | H79: =IF(G79="","", IF(L79=" ",IF(OR(F79=0,G79=0),"",G79-F79),((G79-F79)-L79))) -> 0.044282407 | I79: =IFERROR(IF(L79=" ",(F79+E79),(F79+E79+L79)),"") -> 0.48341435 | L79: 0.029456019 | N79: =IFERROR(E79/H79," ") -> 1.0977522
A80: 45777 | B80: Missing information | C80: 24 | D80: =IFERROR(VLOOKUP($B80,Task!$B$1:$G$67,6,0)," ") -> 0.0083333333 | E80: =IFERROR(D80*C80," ") -> 0.2 | F80: =G79 -> 0.47908565 | G80: 0.71562705 | H80: =IF(G80="","", IF(L80=" ",IF(OR(F80=0,G80=0),"",G80-F80),((G80-F80)-L80))) -> 0.18280297 | I80: =IFERROR(IF(L80=" ",(F80+E80),(F80+E80+L80)),"") -> 0.73282407 | L80: 0.053738426 | N80: =IFERROR(E80/H80," ") -> 1.0940741
D81: =IFERROR(VLOOKUP($B81,Task!$B$1:$G$67,6,0)," ") | E81: =IFERROR(D81*C81," ") | H81: =IF(G81="","", IF(L81=" ",IF(OR(F81=0,G81=0),"",G81-F81),((G81-F81)-L81))) | I81: =IFERROR(IF(L81=" ",(F81+E81),(F81+E81+L81)),"") | N81: =IFERROR(E81/H81," ")
B82: Missing information | C82: 11 | D82: =IFERROR(VLOOKUP($B82,Task!$B$1:$G$67,6,0)," ") -> 0.0083333333 | E82: =IFERROR(D82*C82," ") -> 0.091666667 | H82: =IF(G82="","", IF(L82=" ",IF(OR(F82=0,G82=0),"",G82-F82),((G82-F82)-L82))) | I82: =IFERROR(IF(L82=" ",(F82+E82),(F82+E82+L82)),"") -> 0.091666667 | N82: =IFERROR(E82/H82," ")
D83: =IFERROR(VLOOKUP($B83,Task!$B$1:$G$67,6,0)," ") | E83: =IFERROR(D83*C83," ") | H83: =IF(G83="","", IF(L83=" ",IF(OR(F83=0,G83=0),"",G83-F83),((G83-F83)-L83))) | I83: =IFERROR(IF(L83=" ",(F83+E83),(F83+E83+L83)),"") | N83: =IFERROR(E83/H83," ")
D84: =IFERROR(VLOOKUP($B84,Task!$B$1:$G$67,6,0)," ") | E84: =IFERROR(D84*C84," ") | H84: =IF(G84="","", IF(L84=" ",IF(OR(F84=0,G84=0),"",G84-F84),((G84-F84)-L84))) | I84: =IFERROR(IF(L84=" ",(F84+E84),(F84+E84+L84)),"") | N84: =IFERROR(E84/H84," ")
D85: =IFERROR(VLOOKUP($B85,Task!$B$1:$G$67,6,0)," ") | E85: =IFERROR(D85*C85," ") | H85: =IF(G85="","", IF(L85=" ",IF(OR(F85=0,G85=0),"",G85-F85),((G85-F85)-L85))) | I85: =IFERROR(IF(L85=" ",(F85+E85),(F85+E85+L85)),"") | N85: =IFERROR(E85/H85," ")
D86: =IFERROR(VLOOKUP($B86,Task!$B$1:$G$67,6,0)," ") | E86: =IFERROR(D86*C86," ") | H86: =IF(G86="","", IF(L86=" ",IF(OR(F86=0,G86=0),"",G86-F86),((G86-F86)-L86))) | I86: =IFERROR(IF(L86=" ",(F86+E86),(F86+E86+L86)),"") | N86: =IFERROR(E86/H86," ")
D87: =IFERROR(VLOOKUP($B87,Task!$B$1:$G$67,6,0)," ") | E87: =IFERROR(D87*C87," ") | H87: =IF(G87="","", IF(L87=" ",IF(OR(F87=0,G87=0),"",G87-F87),((G87-F87)-L87))) | I87: =IFERROR(IF(L87=" ",(F87+E87),(F87+E87+L87)),"") | N87: =IFERROR(E87/H87," ")
D88: =IFERROR(VLOOKUP($B88,Task!$B$1:$G$67,6,0)," ") | E88: =IFERROR(D88*C88," ") | H88: =IF(G88="","", IF(L88=" ",IF(OR(F88=0,G88=0),"",G88-F88),((G88-F88)-L88))) | I88: =IFERROR(IF(L88=" ",(F88+E88),(F88+E88+L88)),"") | N88: =IFERROR(E88/H88," ")
D89: =IFERROR(VLOOKUP($B89,Task!$B$1:$G$67,6,0)," ") | E89: =IFERROR(D89*C89," ") | H89: =IF(G89="","", IF(L89=" ",IF(OR(F89=0,G89=0),"",G89-F89),((G89-F89)-L89))) | I89: =IFERROR(IF(L89=" ",(F89+E89),(F89+E89+L89)),"") | N89: =IFERROR(E89/H89," ")
D90: =IFERROR(VLOOKUP($B90,Task!$B$1:$G$67,6,0)," ") | E90: =IFERROR(D90*C90," ") | H90: =IF(G90="","", IF(L90=" ",IF(OR(F90=0,G90=0),"",G90-F90),((G90-F90)-L90))) | I90: =IFERROR(IF(L90=" ",(F90+E90),(F90+E90+L90)),"") | N90: =IFERROR(E90/H90," ")
D91: =IFERROR(VLOOKUP($B91,Task!$B$1:$G$67,6,0)," ") | E91: =IFERROR(D91*C91," ") | H91: =IF(G91="","", IF(L91=" ",IF(OR(F91=0,G91=0),"",G91-F91),((G91-F91)-L91))) | I91: =IFERROR(IF(L91=" ",(F91+E91),(F91+E91+L91)),"") | N91: =IFERROR(E91/H91," ")
D92: =IFERROR(VLOOKUP($B92,Task!$B$1:$G$67,6,0)," ") | E92: =IFERROR(D92*C92," ") | H92: =IF(G92="","", IF(L92=" ",IF(OR(F92=0,G92=0),"",G92-F92),((G92-F92)-L92))) | I92: =IFERROR(IF(L92=" ",(F92+E92),(F92+E92+L92)),"") | N92: =IFERROR(E92/H92," ")
D93: =IFERROR(VLOOKUP($B93,Task!$B$1:$G$67,6,0)," ") | E93: =IFERROR(D93*C93," ") | H93: =IF(G93="","", IF(L93=" ",IF(OR(F93=0,G93=0),"",G93-F93),((G93-F93)-L93))) | I93: =IFERROR(IF(L93=" ",(F93+E93),(F93+E93+L93)),"") | N93: =IFERROR(E93/H93," ")
D94: =IFERROR(VLOOKUP($B94,Task!$B$1:$G$67,6,0)," ") | E94: =IFERROR(D94*C94," ") | H94: =IF(G94="","", IF(L94=" ",IF(OR(F94=0,G94=0),"",G94-F94),((G94-F94)-L94))) | I94: =IFERROR(IF(L94=" ",(F94+E94),(F94+E94+L94)),"") | N94: =IFERROR(E94/H94," ")
... D115: =IFERROR(VLOOKUP($B115,Task!$B$1:$G$67,6,0)," ") | E115: =IFERROR(D115*C115," ") | H115: =IF(G115="","", IF(L115=" ",IF(OR(F115=0,G115=0),"",G115-F115),((G115-F115)-L115))) | I115: =IFERROR(IF(L115=" ",(F115+E115),(F115+E115+L115)),"") | N115: =IFERROR(E115/H115," ")
D116: =IFERROR(VLOOKUP($B116,Task!$B$1:$G$67,6,0)," ") | E116: =IFERROR(D116*C116," ") | H116: =IF(G116="","", IF(L116=" ",IF(OR(F116=0,G116=0),"",G116-F116),((G116-F116)-L116))) | I116: =IFERROR(IF(L116=" ",(F116+E116),(F116+E116+L116)),"") | N116: =IFERROR(E116/H116," ") | O116: =AVERAGEIF(A:A,TODAY(),N:N) -> #DIV/0!
D117: =IFERROR(VLOOKUP($B117,Task!$B$1:$G$67,6,0)," ") | E117: =IFERROR(D117*C117," ") | H117: =IF(G117="","", IF(L117=" ",IF(OR(F117=0,G117=0),"",G117-F117),((G117-F117)-L117))) | I117: =IFERROR(IF(L117=" ",(F117+E117),(F117+E117+L117)),"") | N117: =IFERROR(E117/H117," ")
D118: =IFERROR(VLOOKUP($B118,Task!$B$1:$G$67,6,0)," ") | E118: =IFERROR(D118*C118," ") | H118: =IF(G118="","", IF(L118=" ",IF(OR(F118=0,G118=0),"",G118-F118),((G118-F118)-L118))) | I118: =IFERROR(IF(L118=" ",(F118+E118),(F118+E118+L118)),"") | N118: =IFERROR(E118/H118," ")
D119: =IFERROR(VLOOKUP($B119,Task!$B$1:$G$67,6,0)," ") | E119: =IFERROR(D119*C119," ") | H119: =IF(G119="","", IF(L119=" ",IF(OR(F119=0,G119=0),"",G119-F119),((G119-F119)-L119))) | I119: =IFERROR(IF(L119=" ",(F119+E119),(F119+E119+L119)),"") | N119: =IFERROR(E119/H119," ")
D120: =IFERROR(VLOOKUP($B120,Task!$B$1:$G$67,6,0)," ") | E120: =IFERROR(D120*C120," ") | H120: =IF(G120="","", IF(L120=" ",IF(OR(F120=0,G120=0),"",G120-F120),((G120-F120)-L120))) | I120: =IFERROR(IF(L120=" ",(F120+E120),(F120+E120+L120)),"") | N120: =IFERROR(E120/H120," ")
...

Sheet March 25
A1: Date | B1: Task Name | C1: Quantity | D1: RE | E1: Total RE | F1: Start Time | G1: End Time | H1: Actual Time taken | I1: Actual End Time | J1: Break Start Time | K1: Break End Time | L1: Total Break time | M1: Comment | N1: Productivity | O1: 0.22916667 | P1: Date | Q1: Total RE | R1: Core | S1: Non-Core | T1: Productivity | U1: 0.33333333
A2: 45719 | B2: WH - Wholesale order report | C2: 1 | D2: =IFERROR(VLOOKUP($B2,Task!$B$1:$G$65,6,0)," ") -> 0.034722222 | E2: =IFERROR(D2*C2," ") -> 0.034722222 | F2: 0.31122685 | G2: 0.34273148 | H2: =IF(G2="","", IF(L2=" ",IF(OR(F2=0,G2=0),"",G2-F2),((G2-F2)-L2))) -> 0.03150463 | I2: =IFERROR(IF(L2=" ",(F2+E2),(F2+E2+L2)),"") -> 0.34594907 | N2: =IFERROR(E2/H2," ") -> 1.1021308 | O2: 0.63107639 | P2: =IFERROR(__xludf.DUMMYFUNCTION("UNIQUE($A$2:$A$993)"),45719) -> 45719 | Q2: =SUMIF($A:$A,$P2,$E:$E) -> 0.3375 | R2: =SUMIF($A:$A,$P2,$H:$H) -> 0.3127662 | S2: =IF(OR(R2="",R2>=$U$1)," ",$U$1-R2) -> 0.02056713 | T2: =IFERROR(AVERAGEIF($A:$A,$P2,$N:$N)," ") -> 1.0714575 | U2: =S2-V2 -> 0.012615741 | V2: 0.0079513889
A3: 45719 | B3: WH - Sale Journal | C3: 1 | D3: =IFERROR(VLOOKUP($B3,Task!$B$1:$G$65,6,0)," ") -> 0.0069444444 | E3: =IFERROR(D3*C3," ") -> 0.0069444444 | F3: =G2 -> 0.34273148 | G3: 0.34956019 | H3: =IF(G3="","", IF(L3=" ",IF(OR(F3=0,G3=0),"",G3-F3),((G3-F3)-L3))) -> 0.0068287037 | I3: =IFERROR(IF(L3=" ",(F3+E3),(F3+E3+L3)),"") -> 0.34967593 | N3: =IFERROR(E3/H3," ") -> 1.0169492 | O3: =O2-O1 -> 0.40190972 | P3: =IFERROR(__xludf.DUMMYFUNCTION("""COMPUTED_VALUE"""),45720) -> 45720 | Q3: =IF(SUMIF($A:$A,$P3,$E:$E)=0,"",SUMIF($A:$A,$P3,$E:$E)) -> 0.36388889 | R3: =IF(SUMIF($A:$A,$P3,$H:$H)=0,"",SUMIF($A:$A,$P3,$H:$H)) -> 0.34327897 | S3: =IF(OR(R3="",R3>=$U$1)," ",$U$1-R3) | T3: =IFERROR(AVERAGEIF($A:$A,$P3,$N:$N)," ") -> 1.0714799
A4: 45719 | B4: Nordstrom SQL DATA Dump | C4: 1 | D4: =IFERROR(VLOOKUP($B4,Task!$B$1:$G$65,6,0)," ") -> 0.048611111 | E4: =IFERROR(D4*C4," ") -> 0.048611111 | F4: =G3 -> 0.34956019 | G4: 0.39493056 | H4: =IF(G4="","", IF(L4=" ",IF(OR(F4=0,G4=0),"",G4-F4),((G4-F4)-L4))) -> 0.04537037 | I4: =IFERROR(IF(L4=" ",(F4+E4),(F4+E4+L4)),"") -> 0.3981713 | N4: =IFERROR(E4/H4," ") -> 1.0714286 | P4: =IFERROR(__xludf.DUMMYFUNCTION("""COMPUTED_VALUE"""),45721) -> 45721 | Q4: =IF(SUMIF($A:$A,$P4,$E:$E)=0,"",SUMIF($A:$A,$P4,$E:$E)) -> 0.28194444 | R4: =IF(SUMIF($A:$A,$P4,$H:$H)=0,"",SUMIF($A:$A,$P4,$H:$H)) -> 0.27099537 | S4: =IF(OR(R4="",R4>=$U$1)," ",$U$1-R4) -> 0.062337963 | T4: =IFERROR(AVERAGEIF($A:$A,$P4,$N:$N)," ") -> 1.0625165
A5: 45719 | B5: Wholesale Adding Images | C5: 46 | D5: =IFERROR(VLOOKUP($B5,Task!$B$1:$G$65,6,0)," ") -> 0.0013888889 | E5: =IFERROR(D5*C5," ") -> 0.063888889 | F5: =G4 -> 0.39493056 | G5: 0.45894676 | H5: =IF(G5="","", IF(L5=" ",IF(OR(F5=0,G5=0),"",G5-F5),((G5-F5)-L5))) -> 0.058969907 | I5: =IFERROR(IF(L5=" ",(F5+E5),(F5+E5+L5)),"") -> 0.46386574 | L5: 0.0050462963 | M5: Adding RRP and Cost Price | N5: =IFERROR(E5/H5," ") -> 1.0834151 | P5: =IFERROR(__xludf.DUMMYFUNCTION("""COMPUTED_VALUE"""),45722) -> 45722 | Q5: =IF(SUMIF($A:$A,$P5,$E:$E)=0,"",SUMIF($A:$A,$P5,$E:$E)) -> 0.31736111 | R5: =IF(SUMIF($A:$A,$P5,$H:$H)=0,"",SUMIF($A:$A,$P5,$H:$H)) -> 0.29451389 | S5: =IF(OR(R5="",R5>=$U$1)," ",$U$1-R5) -> 0.038819444 | T5: =IFERROR(AVERAGEIF($A:$A,$P5,$N:$N)," ") -> 1.0712687
A6: 45719 | B6: WH - Fabric Composition | C6: 48 | D6: =IFERROR(VLOOKUP($B6,Task!$B$1:$G$65,6,0)," ") -> 0.0020833333 | E6: =IFERROR(D6*C6," ") -> 0.1 | F6: =G5 -> 0.45894676 | G6: 0.59590278 | H6: =IF(G6="","", IF(L6=" ",IF(OR(F6=0,G6=0),"",G6-F6),((G6-F6)-L6))) -> 0.092384259 | I6: =IFERROR(IF(L6=" ",(F6+E6),(F6+E6+L6)),"") -> 0.60351852 | L6: 0.044571759 | N6: =IFERROR(E6/H6," ") -> 1.0824355 | P6: =IFERROR(__xludf.DUMMYFUNCTION("""COMPUTED_VALUE"""),45726) -> 45726 | Q6: =IF(SUMIF($A:$A,$P6,$E:$E)=0,"",SUMIF($A:$A,$P6,$E:$E)) -> 0.34375 | R6: =IF(SUMIF($A:$A,$P6,$H:$H)=0,"",SUMIF($A:$A,$P6,$H:$H)) -> 0.32394676 | S6: =IF(OR(R6="",R6>=$U$1)," ",$U$1-R6) -> 0.0093865741 | T6: =IFERROR(AVERAGEIF($A:$A,$P6,$N:$N)," ") -> 1.073897
A7: 45719 | B7: DAM - Image Approval | C7: 30 | D7: =IFERROR(VLOOKUP($B7,Task!$B$1:$G$65,6,0)," ") -> 0.0027777778 | E7: =IFERROR(D7*C7," ") -> 0.083333333 | F7: =G6 -> 0.59590278 | G7: 0.67361111 | H7: =IF(G7="","", IF(L7=" ",IF(OR(F7=0,G7=0),"",G7-F7),((G7-F7)-L7))) -> 0.077708333 | I7: =IFERROR(IF(L7=" ",(F7+E7),(F7+E7+L7)),"") -> 0.67923611 | N7: =IFERROR(E7/H7," ") -> 1.0723861 | P7: =IFERROR(__xludf.DUMMYFUNCTION("""COMPUTED_VALUE"""),45727) -> 45727 | Q7: =IF(SUMIF($A:$A,$P7,$E:$E)=0,"",SUMIF($A:$A,$P7,$E:$E)) -> 0.33472222 | R7: =IF(SUMIF($A:$A,$P7,$H:$H)=0,"",SUMIF($A:$A,$P7,$H:$H)) -> 0.31190972 | S7: =IF(OR(R7="",R7>=$U$1)," ",$U$1-R7) -> 0.021423611 | T7: =IFERROR(AVERAGEIF($A:$A,$P7,$N:$N)," ") -> 1.081591
A8: 45720 | B8: Wholesale Adding Images | C8: 32 | D8: =IFERROR(VLOOKUP($B8,Task!$B$1:$G$65,6,0)," ") -> 0.0013888889 | E8: =IFERROR(D8*C8," ") -> 0.044444444 | F8: 0.27956019 | G8: 0.32085648 | H8: =IF(G8="","", IF(L8=" ",IF(OR(F8=0,G8=0),"",G8-F8),((G8-F8)-L8))) -> 0.041296296 | I8: =IFERROR(IF(L8=" ",(F8+E8),(F8+E8+L8)),"") -> 0.32400463 | M8: Adding RRP in AW25 kids tracker | N8: =IFERROR(E8/H8," ") -> 1.0762332 | P8: =IFERROR(__xludf.DUMMYFUNCTION("""COMPUTED_VALUE"""),45728) -> 45728 | Q8: =IF(SUMIF($A:$A,$P8,$E:$E)=0,"",SUMIF($A:$A,$P8,$E:$E)) -> 0.33194444 | R8: =IF(SUMIF($A:$A,$P8,$H:$H)=0,"",SUMIF($A:$A,$P8,$H:$H)) -> 0.30501157 | S8: =IF(OR(R8="",R8>=$U$1)," ",$U$1-R8) -> 0.028321759 | T8: =IFERROR(AVERAGEIF($A:$A,$P8,$N:$N)," ") -> 1.0854446
A9: 45720 | B9: DAM - Image Approval | C9: 32 | D9: =IFERROR(VLOOKUP($B9,Task!$B$1:$G$65,6,0)," ") -> 0.0027777778 | E9: =IFERROR(D9*C9," ") -> 0.088888889 | F9: =G8 -> 0.32085648 | G9: 0.40363426 | H9: =IF(G9="","", IF(L9=" ",IF(OR(F9=0,G9=0),"",G9-F9),((G9-F9)-L9))) -> 0.082777778 | I9: =IFERROR(IF(L9=" ",(F9+E9),(F9+E9+L9)),"") -> 0.40974537 | N9: =IFERROR(E9/H9," ") -> 1.0738255 | P9: =IFERROR(__xludf.DUMMYFUNCTION("""COMPUTED_VALUE"""),45729) -> 45729 | Q9: =IF(SUMIF($A:$A,$P9,$E:$E)=0,"",SUMIF($A:$A,$P9,$E:$E)) -> 0.33472222 | R9: =IF(SUMIF($A:$A,$P9,$H:$H)=0,"",SUMIF($A:$A,$P9,$H:$H)) -> 0.30657407 | S9: =IF(OR(R9="",R9>=$U$1)," ",$U$1-R9) -> 0.026759259 | T9: =IFERROR(AVERAGEIF($A:$A,$P9,$N:$N)," ") -> 1.0910217
A10: 45720 | B10: OGM - Sizing update | C10: 12 | D10: =IFERROR(VLOOKUP($B10,Task!$B$1:$G$65,6,0)," ") -> 0.0055555556 | E10: =IFERROR(D10*C10," ") -> 0.066666667 | F10: =G9 -> 0.40363426 | G10: 0.46658565 | H10: =IF(G10="","", IF(L10=" ",IF(OR(F10=0,G10=0),"",G10-F10),((G10-F10)-L10))) -> 0.062951389 | I10: =IFERROR(IF(L10=" ",(F10+E10),(F10+E10+L10)),"") -> 0.47030093 | N10: =IFERROR(E10/H10," ") -> 1.0590182 | P10: =IFERROR(__xludf.DUMMYFUNCTION("""COMPUTED_VALUE"""),45730) -> 45730 | Q10: =IF(SUMIF($A:$A,$P10,$E:$E)=0,"",SUMIF($A:$A,$P10,$E:$E)) -> 0.33333333 | R10: =IF(SUMIF($A:$A,$P10,$H:$H)=0,"",SUMIF($A:$A,$P10,$H:$H)) -> 0.30512731 | S10: =IF(OR(R10="",R10>=$U$1)," ",$U$1-R10) -> 0.028206019 | T10: =IFERROR(AVERAGEIF($A:$A,$P10,$N:$N)," ") -> 1.0838207
A11: 45720 | B11: DAM - Image Search | C11: 22 | D11: =IFERROR(VLOOKUP($B11,Task!$B$1:$G$65,6,0)," ") -> 0.00069444444 | E11: =IFERROR(D11*C11," ") -> 0.015277778 | F11: =G10 -> 0.46658565 | G11: 0.48054398 | H11: =IF(G11="","", IF(L11=" ",IF(OR(F11=0,G11=0),"",G11-F11),((G11-F11)-L11))) -> 0.013958333 | I11: =IFERROR(IF(L11=" ",(F11+E11),(F11+E11+L11)),"") -> 0.48186343 | N11: =IFERROR(E11/H11," ") -> 1.0945274 | P11: =IFERROR(__xludf.DUMMYFUNCTION("""COMPUTED_VALUE"""),45733) -> 45733 | Q11: =IF(SUMIF($A:$A,$P11,$E:$E)=0,"",SUMIF($A:$A,$P11,$E:$E)) -> 0.33888889 | R11: =IF(SUMIF($A:$A,$P11,$H:$H)=0,"",SUMIF($A:$A,$P11,$H:$H)) -> 0.30549769 | S11: =IF(OR(R11="",R11>=$U$1)," ",$U$1-R11) -> 0.027835648 | T11: =IFERROR(AVERAGEIF($A:$A,$P11,$N:$N)," ") -> 1.0902257
A12: 45720 | B12: DAM - Image Approval | C12: 46 | D12: =IFERROR(VLOOKUP($B12,Task!$B$1:$G$65,6,0)," ") -> 0.0027777778 | E12: =IFERROR(D12*C12," ") -> 0.12777778 | F12: =G11 -> 0.48054398 | G12: 0.67136925 | H12: =IF(G12="","", IF(L12=" ",IF(OR(F12=0,G12=0),"",G12-F12),((G12-F12)-L12))) -> 0.12314008 | I12: =IFERROR(IF(L12=" ",(F12+E12),(F12+E12+L12)),"") -> 0.67600694 | L12: 0.067685185 | N12: =IFERROR(E12/H12," ") -> 1.037662 | P12: =IFERROR(__xludf.DUMMYFUNCTION("""COMPUTED_VALUE"""),45734) -> 45734 | Q12: =IF(SUMIF($A:$A,$P12,$E:$E)=0,"",SUMIF($A:$A,$P12,$E:$E)) -> 0.33194444 | R12: =IF(SUMIF($A:$A,$P12,$H:$H)=0,"",SUMIF($A:$A,$P12,$H:$H)) -> 0.29756944 | S12: =IF(OR(R12="",R12>=$U$1)," ",$U$1-R12) -> 0.035763889 | T12: =IFERROR(AVERAGEIF($A:$A,$P12,$N:$N)," ") -> 1.1130825
A13: 45720 | B13: Trade Report | C13: 1 | D13: =IFERROR(VLOOKUP($B13,Task!$B$1:$G$65,6,0)," ") -> 0.020833333 | E13: =IFERROR(D13*C13," ") -> 0.020833333 | F13: 0.51003472 | G13: 0.52918981 | H13: =IF(G13="","", IF(L13=" ",IF(OR(F13=0,G13=0),"",G13-F13),((G13-F13)-L13))) -> 0.019155093 | I13: =IFERROR(IF(L13=" ",(F13+E13),(F13+E13+L13)),"") -> 0.53086806 | N13: =IFERROR(E13/H13," ") -> 1.0876133 | P13: =IFERROR(__xludf.DUMMYFUNCTION("""COMPUTED_VALUE"""),45735) -> 45735 | Q13: =IF(SUMIF($A:$A,$P13,$E:$E)=0,"",SUMIF($A:$A,$P13,$E:$E)) -> 0.32916667 | R13: =IF(SUMIF($A:$A,$P13,$H:$H)=0,"",SUMIF($A:$A,$P13,$H:$H)) -> 0.29291667 | S13: =IF(OR(R13="",R13>=$U$1)," ",$U$1-R13) -> 0.040416667 | T13: =IFERROR(AVERAGEIF($A:$A,$P13,$N:$N)," ") -> 1.1243204
A14: 45721 | B14: Nordstrom SQL DATA Dump | C14: 1 | D14: =IFERROR(VLOOKUP($B14,Task!$B$1:$G$65,6,0)," ") -> 0.048611111 | E14: =IFERROR(D14*C14," ") -> 0.048611111 | F14: 0.31210648 | G14: 0.3565625 | H14: =IF(G14="","", IF(L14=" ",IF(OR(F14=0,G14=0),"",G14-F14),((G14-F14)-L14))) -> 0.044456019 | I14: =IFERROR(IF(L14=" ",(F14+E14),(F14+E14+L14)),"") -> 0.36071759 | N14: =IFERROR(E14/H14," ") -> 1.0934652 | P14: =IFERROR(__xludf.DUMMYFUNCTION("""COMPUTED_VALUE"""),45736) -> 45736 | Q14: =IF(SUMIF($A:$A,$P14,$E:$E)=0,"",SUMIF($A:$A,$P14,$E:$E)) -> 0.30694444 | R14: =IF(SUMIF($A:$A,$P14,$H:$H)=0,"",SUMIF($A:$A,$P14,$H:$H)) -> 0.27071682 | S14: =IF(OR(R14="",R14>=$U$1)," ",$U$1-R14) -> 0.062616516 | T14: =IFERROR(AVERAGEIF($A:$A,$P14,$N:$N)," ") -> 1.1038928
A15: 45721 | B15: Franchise Adding Images | C15: 48 | D15: =IFERROR(VLOOKUP($B15,Task!$B$1:$G$65,6,0)," ") -> 0.0013888889 | E15: =IFERROR(D15*C15," ") -> 0.066666667 | F15: =G14 -> 0.3565625 | G15: 0.41804398 | H15: =IF(G15="","", IF(L15=" ",IF(OR(F15=0,G15=0),"",G15-F15),((G15-F15)-L15))) -> 0.061481481 | I15: =IFERROR(IF(L15=" ",(F15+E15),(F15+E15+L15)),"") -> 0.42322917 | N15: =IFERROR(E15/H15," ") -> 1.0843373 | P15: =IFERROR(__xludf.DUMMYFUNCTION("""COMPUTED_VALUE"""),45740) -> 45740 | Q15: =IF(SUMIF($A:$A,$P15,$E:$E)=0,"",SUMIF($A:$A,$P15,$E:$E)) -> 0.31597222 | R15: =IF(SUMIF($A:$A,$P15,$H:$H)=0,"",SUMIF($A:$A,$P15,$H:$H)) -> 0.2816369 | S15: =IF(OR(R15="",R15>=$U$1)," ",$U$1-R15) -> 0.051696435 | T15: =IFERROR(AVERAGEIF($A:$A,$P15,$N:$N)," ") -> 1.1088079
A16: 45721 | B16: DAM - Image Approval | C16: 60 | D16: =IFERROR(VLOOKUP($B16,Task!$B$1:$G$65,6,0)," ") -> 0.0027777778 | E16: =IFERROR(D16*C16," ") -> 0.16666667 | F16: =G15 -> 0.41804398 | G16: 0.6875 | H16: =IF(G16="","", IF(L16=" ",IF(OR(F16=0,G16=0),"",G16-F16),((G16-F16)-L16))) -> 0.16505787 | I16: =IFERROR(IF(L16=" ",(F16+E16),(F16+E16+L16)),"") -> 0.6891088 | L16: 0.10439815 | N16: =IFERROR(E16/H16," ") -> 1.0097469 | P16: =IFERROR(__xludf.DUMMYFUNCTION("""COMPUTED_VALUE"""),45741) -> 45741 | Q16: =IF(SUMIF($A:$A,$P16,$E:$E)=0,"",SUMIF($A:$A,$P16,$E:$E)) -> 0.35416667 | R16: =IF(SUMIF($A:$A,$P16,$H:$H)=0,"",SUMIF($A:$A,$P16,$H:$H)) -> 0.31216435 | S16: =IF(OR(R16="",R16>=$U$1)," ",$U$1-R16) -> 0.021168981 | T16: =IFERROR(AVERAGEIF($A:$A,$P16,$N:$N)," ") -> 1.1284497
A17: 45722 | B17: WH - Wholesale order report | C17: 1 | D17: =IFERROR(VLOOKUP($B17,Task!$B$1:$G$65,6,0)," ") -> 0.034722222 | E17: =IFERROR(D17*C17," ") -> 0.034722222 | F17: 0.31076389 | G17: 0.34416667 | H17: =IF(G17="","", IF(L17=" ",IF(OR(F17=0,G17=0),"",G17-F17),((G17-F17)-L17))) -> 0.033402778 | I17: =IFERROR(IF(L17=" ",(F17+E17),(F17+E17+L17)),"") -> 0.34548611 | N17: =IFERROR(E17/H17," ") -> 1.039501 | P17: =IFERROR(__xludf.DUMMYFUNCTION("""COMPUTED_VALUE"""),45742) -> 45742 | Q17: =IF(SUMIF($A:$A,$P17,$E:$E)=0,"",SUMIF($A:$A,$P17,$E:$E)) -> 0.31111111 | R17: =IF(SUMIF($A:$A,$P17,$H:$H)=0,"",SUMIF($A:$A,$P17,$H:$H)) -> 0.27681713 | S17: =IF(OR(R17="",R17>=$U$1)," ",$U$1-R17) -> 0.056516204 | T17: =IFERROR(AVERAGEIF($A:$A,$P17,$N:$N)," ") -> 1.1245924
A18: 45722 | B18: WH - Sale Journal | C18: 1 | D18: =IFERROR(VLOOKUP($B18,Task!$B$1:$G$65,6,0)," ") -> 0.0069444444 | E18: =IFERROR(D18*C18," ") -> 0.0069444444 | F18: =G17 -> 0.34416667 | G18: 0.35063657 | H18: =IF(G18="","", IF(L18=" ",IF(OR(F18=0,G18=0),"",G18-F18),((G18-F18)-L18))) -> 0.0064699074 | I18: =IFERROR(IF(L18=" ",(F18+E18),(F18+E18+L18)),"") -> 0.35111111 | N18: =IFERROR(E18/H18," ") -> 1.0733453 | P18: =IFERROR(__xludf.DUMMYFUNCTION("""COMPUTED_VALUE"""),45743) -> 45743 | Q18: =IF(SUMIF($A:$A,$P18,$E:$E)=0,"",SUMIF($A:$A,$P18,$E:$E)) -> 0.34861111 | R18: =IF(SUMIF($A:$A,$P18,$H:$H)=0,"",SUMIF($A:$A,$P18,$H:$H)) -> 0.31484954 | S18: =IF(OR(R18="",R18>=$U$1)," ",$U$1-R18) -> 0.018483796 | T18: =IFERROR(AVERAGEIF($A:$A,$P18,$N:$N)," ") -> 1.1090796
A19: 45722 | B19: Nordstrom SQL DATA Dump | C19: 1 | D19: =IFERROR(VLOOKUP($B19,Task!$B$1:$G$65,6,0)," ") -> 0.048611111 | E19: =IFERROR(D19*C19," ") -> 0.048611111 | F19: =G18 -> 0.35063657 | G19: 0.39478009 | H19: =IF(G19="","", IF(L19=" ",IF(OR(F19=0,G19=0),"",G19-F19),((G19-F19)-L19))) -> 0.044143519 | I19: =IFERROR(IF(L19=" ",(F19+E19),(F19+E19+L19)),"") -> 0.39924769 | N19: =IFERROR(E19/H19," ") -> 1.1012061 | Q19: =IF(SUMIF($A:$A,$P19,$E:$E)=0,"",SUMIF($A:$A,$P19,$E:$E)) | R19: =IF(SUMIF($A:$A,$P19,$H:$H)=0,"",SUMIF($A:$A,$P19,$H:$H)) | S19: =IF(R19=""," ",$U$1-R19) | T19: =IFERROR(AVERAGEIF($A:$A,$P19,$N:$N)," ")
A20: 45722 | B20: WH - Fabric Composition | C20: 19 | D20: =IFERROR(VLOOKUP($B20,Task!$B$1:$G$65,6,0)," ") -> 0.0020833333 | E20: =IFERROR(D20*C20," ") -> 0.039583333 | F20: =G19 -> 0.39478009 | G20: 0.43253472 | H20: =IF(G20="","", IF(L20=" ",IF(OR(F20=0,G20=0),"",G20-F20),((G20-F20)-L20))) -> 0.03775463 | I20: =IFERROR(IF(L20=" ",(F20+E20),(F20+E20+L20)),"") -> 0.43436343 | N20: =IFERROR(E20/H20," ") -> 1.0484365 | Q20: =IF(SUMIF($A:$A,$P20,$E:$E)=0,"",SUMIF($A:$A,$P20,$E:$E)) | R20: =IF(SUMIF($A:$A,$P20,$H:$H)=0,"",SUMIF($A:$A,$P20,$H:$H)) | S20: =IF(R20=""," ",$U$1-R20) | T20: =IFERROR(AVERAGEIF($A:$A,$P20,$N:$N)," ")
A21: 45722 | B21: DAM - Image Approval | C21: 18 | D21: =IFERROR(VLOOKUP($B21,Task!$B$1:$G$65,6,0)," ") -> 0.0027777778 | E21: =IFERROR(D21*C21," ") -> 0.05 | F21: =G20 -> 0.43253472 | G21: 0.50027778 | H21: =IF(G21="","", IF(L21=" ",IF(OR(F21=0,G21=0),"",G21-F21),((G21-F21)-L21))) -> 0.04681713 | I21: =IFERROR(IF(L21=" ",(F21+E21),(F21+E21+L21)),"") -> 0.50346065 | L21: 0.020925926 | N21: =IFERROR(E21/H21," ") -> 1.0679852 | Q21: =IF(SUMIF($A:$A,$P21,$E:$E)=0,"",SUMIF($A:$A,$P21,$E:$E)) | R21: =IF(SUMIF($A:$A,$P21,$H:$H)=0,"",SUMIF($A:$A,$P21,$H:$H)) | S21: =IF(R21=""," ",$U$1-R21) | T21: =IFERROR(AVERAGEIF($A:$A,$P21,$N:$N)," ")
A22: 45722 | B22: WH - EAN Update | C22: 18 | D22: =IFERROR(VLOOKUP($B22,Task!$B$1:$G$65,6,0)," ") -> 0.0013888889 | E22: =IFERROR(D22*C22," ") -> 0.025 | F22: =G21 -> 0.50027778 | G22: 0.52359954 | H22: =IF(G22="","", IF(L22=" ",IF(OR(F22=0,G22=0),"",G22-F22),((G22-F22)-L22))) -> 0.023321759 | I22: =IFERROR(IF(L22=" ",(F22+E22),(F22+E22+L22)),"") -> 0.52527778 | N22: =IFERROR(E22/H22," ") -> 1.0719603 | Q22: =IF(SUMIF($A:$A,$P22,$E:$E)=0,"",SUMIF($A:$A,$P22,$E:$E)) | R22: =IF(SUMIF($A:$A,$P22,$H:$H)=0,"",SUMIF($A:$A,$P22,$H:$H)) | S22: =IF(R22=""," ",$U$1-R22) | T22: =IFERROR(AVERAGEIF($A:$A,$P22,$N:$N)," ")
A23: 45722 | B23: WH - Wash Care update | C23: 54 | D23: =IFERROR(VLOOKUP($B23,Task!$B$1:$G$65,6,0)," ") -> 0.0020833333 | E23: =IFERROR(D23*C23," ") -> 0.1125 | F23: =G22 -> 0.52359954 | G23: 0.6875 | H23: =IF(G23="","", IF(L23=" ",IF(OR(F23=0,G23=0),"",G23-F23),((G23-F23)-L23))) -> 0.10260417 | I23: =IFERROR(IF(L23=" ",(F23+E23),(F23+E23+L23)),"") -> 0.69739583 | L23: 0.061296296 | N23: =IFERROR(E23/H23," ") -> 1.0964467 | Q23: =IF(SUMIF($A:$A,$P23,$E:$E)=0,"",SUMIF($A:$A,$P23,$E:$E)) | R23: =IF(SUMIF($A:$A,$P23,$H:$H)=0,"",SUMIF($A:$A,$P23,$H:$H)) | S23: =IF(R23=""," ",$U$1-R23) | T23: =IFERROR(AVERAGEIF($A:$A,$P23,$N:$N)," ")
A24: 45726 | B24: WH - Wholesale order report | C24: 1 | D24: =IFERROR(VLOOKUP($B24,Task!$B$1:$G$65,6,0)," ") -> 0.034722222 | E24: =IFERROR(D24*C24," ") -> 0.034722222 | F24: 0.30642361 | G24: 0.33719907 | H24: =IF(G24="","", IF(L24=" ",IF(OR(F24=0,G24=0),"",G24-F24),((G24-F24)-L24))) -> 0.030775463 | I24: =IFERROR(IF(L24=" ",(F24+E24),(F24+E24+L24)),"") -> 0.34114583 | N24: =IFERROR(E24/H24," ") -> 1.1282437
A25: 45726 | B25: WH - Sale Journal | C25: 1 | D25: =IFERROR(VLOOKUP($B25,Task!$B$1:$G$65,6,0)," ") -> 0.0069444444 | E25: =IFERROR(D25*C25," ") -> 0.0069444444 | F25: =G24 -> 0.33719907 | G25: 0.34364583 | H25: =IF(G25="","", IF(L25=" ",IF(OR(F25=0,G25=0),"",G25-F25),((G25-F25)-L25))) -> 0.0064467593 | I25: =IFERROR(IF(L25=" ",(F25+E25),(F25+E25+L25)),"") -> 0.34414352 | N25: =IFERROR(E25/H25," ") -> 1.0771993
A26: 45726 | B26: Nordstrom SQL DATA Dump | C26: 1 | D26: =IFERROR(VLOOKUP($B26,Task!$B$1:$G$65,6,0)," ") -> 0.048611111 | E26: =IFERROR(D26*C26," ") -> 0.048611111 | F26: =G25 -> 0.34364583 | G26: 0.38811343 | H26: =IF(G26="","", IF(L26=" ",IF(OR(F26=0,G26=0),"",G26-F26),((G26-F26)-L26))) -> 0.044467593 | I26: =IFERROR(IF(L26=" ",(F26+E26),(F26+E26+L26)),"") -> 0.39225694 | N26: =IFERROR(E26/H26," ") -> 1.0931806
A27: 45726 | B27: OGM - Sizing update | C27: 7 | D27: =IFERROR(VLOOKUP($B27,Task!$B$1:$G$65,6,0)," ") -> 0.0055555556 | E27: =IFERROR(D27*C27," ") -> 0.038888889 | F27: =G26 -> 0.38811343 | G27: 0.42392361 | H27: =IF(G27="","", IF(L27=" ",IF(OR(F27=0,G27=0),"",G27-F27),((G27-F27)-L27))) -> 0.035810185 | I27: =IFERROR(IF(L27=" ",(F27+E27),(F27+E27+L27)),"") -> 0.42700231 | N27: =IFERROR(E27/H27," ") -> 1.0859729
A28: 45726 | B28: WH - Fabric Composition | C28: 3 | D28: =IFERROR(VLOOKUP($B28,Task!$B$1:$G$65,6,0)," ") -> 0.0020833333 | E28: =IFERROR(D28*C28," ") -> 0.00625 | F28: =G27 -> 0.42392361 | G28: 0.4297338 | H28: =IF(G28="","", IF(L28=" ",IF(OR(F28=0,G28=0),"",G28-F28),((G28-F28)-L28))) -> 0.0058101852 | I28: =IFERROR(IF(L28=" ",(F28+E28),(F28+E28+L28)),"") -> 0.43017361 | M28: Adding Country of Dispatch details | N28: =IFERROR(E28/H28," ") -> 1.0756972
A29: 45726 | B29: WH - Wash Care update | C29: 55 | D29: =IFERROR(VLOOKUP($B29,Task!$B$1:$G$65,6,0)," ") -> 0.0020833333 | E29: =IFERROR(D29*C29," ") -> 0.11458333 | F29: =G28 -> 0.4297338 | G29: 0.59015046 | H29: =IF(G29="","", IF(L29=" ",IF(OR(F29=0,G29=0),"",G29-F29),((G29-F29)-L29))) -> 0.11081019 | I29: =IFERROR(IF(L29=" ",(F29+E29),(F29+E29+L29)),"") -> 0.59392361 | L29: 0.049606481 | N29: =IFERROR(E29/H29," ") -> 1.0340506
A30: 45726 | B30: WH - Wash Care update | C30: =72-C29 -> 17 | D30: =IFERROR(VLOOKUP($B30,Task!$B$1:$G$65,6,0)," ") -> 0.0020833333 | E30: =IFERROR(D30*C30," ") -> 0.035416667 | F30: =G29 -> 0.59015046 | G30: 0.63237269 | H30: =IF(G30="","", IF(L30=" ",IF(OR(F30=0,G30=0),"",G30-F30),((G30-F30)-L30))) -> 0.03443287 | I30: =IFERROR(IF(L30=" ",(F30+E30),(F30+E30+L30)),"") -> 0.63335648 | L30: 0.0077893519 | N30: =IFERROR(E30/H30," ") -> 1.0285714
A31: 45726 | B31: DAM - Image Search | C31: 4 | D31: =IFERROR(VLOOKUP($B31,Task!$B$1:$G$65,6,0)," ") -> 0.00069444444 | E31: =IFERROR(D31*C31," ") -> 0.0027777778 | F31: =G30 -> 0.63237269 | G31: 0.63491898 | H31: =IF(G31="","", IF(L31=" ",IF(OR(F31=0,G31=0),"",G31-F31),((G31-F31)-L31))) -> 0.0025462963 | I31: =IFERROR(IF(L31=" ",(F31+E31),(F31+E31+L31)),"") -> 0.63515046 | N31: =IFERROR(E31/H31," ") -> 1.0909091
A32: 45726 | B32: DAM - Image Approval | C32: 20 | D32: =IFERROR(VLOOKUP($B32,Task!$B$1:$G$65,6,0)," ") -> 0.0027777778 | E32: =IFERROR(D32*C32," ") -> 0.055555556 | F32: =G31 -> 0.63491898 | G32: 0.6877662 | H32: =IF(G32="","", IF(L32=" ",IF(OR(F32=0,G32=0),"",G32-F32),((G32-F32)-L32))) -> 0.052847222 | I32: =IFERROR(IF(L32=" ",(F32+E32),(F32+E32+L32)),"") -> 0.69047454 | N32: =IFERROR(E32/H32," ") -> 1.0512484
A33: 45727 | B33: Nordstrom SQL DATA Dump | C33: 1 | D33: =IFERROR(VLOOKUP($B33,Task!$B$1:$G$65,6,0)," ") -> 0.048611111 | E33: =IFERROR(D33*C33," ") -> 0.048611111 | F33: 0.29738426 | G33: 0.34962963 | H33: =IF(G33="","", IF(L33=" ",IF(OR(F33=0,G33=0),"",G33-F33),((G33-F33)-L33))) -> 0.04443287 | I33: =IFERROR(IF(L33=" ",(F33+E33),(F33+E33+L33)),"") -> 0.35380787 | L33: 0.0078125 | N33: =IFERROR(E33/H33," ") -> 1.0940349
A34: 45727 | B34: Nordstrom SQL DATA Dump | C34: 1 | D34: =IFERROR(VLOOKUP($B34,Task!$B$1:$G$65,6,0)," ") -> 0.048611111 | E34: =IFERROR(D34*C34," ") -> 0.048611111 | F34: =G33 -> 0.34962963 | G34: 0.40001157 | H34: =IF(G34="","", IF(L34=" ",IF(OR(F34=0,G34=0),"",G34-F34),((G34-F34)-L34))) -> 0.047488426 | I34: =IFERROR(IF(L34=" ",(F34+E34),(F34+E34+L34)),"") -> 0.40113426 | L34: 0.0028935185 | M34: New DAVID JONES SQL data dump | N34: =IFERROR(E34/H34," ") -> 1.0236412
A35: 45727 | B35: OGM - Sizing update | C35: 4 | D35: =IFERROR(VLOOKUP($B35,Task!$B$1:$G$65,6,0)," ") -> 0.0055555556 | E35: =IFERROR(D35*C35," ") -> 0.022222222 | F35: =G34 -> 0.40001157 | G35: 0.42082176 | H35: =IF(G35="","", IF(L35=" ",IF(OR(F35=0,G35=0),"",G35-F35),((G35-F35)-L35))) -> 0.020810185 | I35: =IFERROR(IF(L35=" ",(F35+E35),(F35+E35+L35)),"") -> 0.4222338 | M35: F37766 | N35: =IFERROR(E35/H35," ") -> 1.0678532
A36: 45727 | B36: DAM - Image Approval | C36: 47 | D36: =IFERROR(VLOOKUP($B36,Task!$B$1:$G$65,6,0)," ") -> 0.0027777778 | E36: =IFERROR(D36*C36," ") -> 0.13055556 | F36: =G35 -> 0.42082176 | G36: 0.61690972 | H36: =IF(G36="","", IF(L36=" ",IF(OR(F36=0,G36=0),"",G36-F36),((G36-F36)-L36))) -> 0.12335648 | I36: =IFERROR(IF(L36=" ",(F36+E36),(F36+E36+L36)),"") -> 0.6241088 | L36: 0.072731481 | N36: =IFERROR(E36/H36," ") -> 1.0583599
A37: 45727 | B37: Trade Report | C37: 1 | D37: =IFERROR(VLOOKUP($B37,Task!$B$1:$G$65,6,0)," ") -> 0.020833333 | E37: =IFERROR(D37*C37," ") -> 0.020833333 | F37: 0.51009259 | G37: 0.52921296 | H37: =IF(G37="","", IF(L37=" ",IF(OR(F37=0,G37=0),"",G37-F37),((G37-F37)-L37))) -> 0.01912037 | I37: =IFERROR(IF(L37=" ",(F37+E37),(F37+E37+L37)),"") -> 0.53092593 | M37: Very Invoice | N37: =IFERROR(E37/H37," ") -> 1.0895884
A38: 45727 | B38: Image upload to Very/John Lewis | C38: 9 | D38: =IFERROR(VLOOKUP($B38,Task!$B$1:$G$65,6,0)," ") -> 0.0027777778 | E38: =IFERROR(D38*C38," ") -> 0.025 | F38: =G36 -> 0.61690972 | G38: 0.64017361 | H38: =IF(G38="","", IF(L38=" ",IF(OR(F38=0,G38=0),"",G38-F38),((G38-F38)-L38))) -> 0.023263889 | I38: =IFERROR(IF(L38=" ",(F38+E38),(F38+E38+L38)),"") -> 0.64190972 | N38: =IFERROR(E38/H38," ") -> 1.0746269
A39: 45727 | B39: OGM - Sizing update | C39: 7 | D39: =IFERROR(VLOOKUP($B39,Task!$B$1:$G$65,6,0)," ") -> 0.0055555556 | E39: =IFERROR(D39*C39," ") -> 0.038888889 | F39: =G38 -> 0.64017361 | G39: 0.67361111 | H39: =IF(G39="","", IF(L39=" ",IF(OR(F39=0,G39=0),"",G39-F39),((G39-F39)-L39))) -> 0.0334375 | I39: =IFERROR(IF(L39=" ",(F39+E39),(F39+E39+L39)),"") -> 0.6790625 | N39: =IFERROR(E39/H39," ") -> 1.1630322
A40: 45728 | B40: Nordstrom SQL DATA Dump | C40: 1 | D40: =IFERROR(VLOOKUP($B40,Task!$B$1:$G$65,6,0)," ") -> 0.048611111 | E40: =IFERROR(D40*C40," ") -> 0.048611111 | F40: 0.31135417 | G40: 0.36185185 | H40: =IF(G40="","", IF(L40=" ",IF(OR(F40=0,G40=0),"",G40-F40),((G40-F40)-L40))) -> 0.043587963 | I40: =IFERROR(IF(L40=" ",(F40+E40),(F40+E40+L40)),"") -> 0.366875 | L40: 0.0069097222 | N40: =IFERROR(E40/H40," ") -> 1.1152416
A41: 45728 | B41: OGM - Sizing update | C41: 26 | D41: =IFERROR(VLOOKUP($B41,Task!$B$1:$G$65,6,0)," ") -> 0.0055555556 | E41: =IFERROR(D41*C41," ") -> 0.14444444 | F41: =G40 -> 0.36185185 | G41: 0.49349537 | H41: =IF(G41="","", IF(L41=" ",IF(OR(F41=0,G41=0),"",G41-F41),((G41-F41)-L41))) -> 0.13164352 | I41: =IFERROR(IF(L41=" ",(F41+E41),(F41+E41+L41)),"") -> 0.5062963 | N41: =IFERROR(E41/H41," ") -> 1.0972393
A42: 45728 | B42: OGM - Sizing update | C42: 16 | D42: =IFERROR(VLOOKUP($B42,Task!$B$1:$G$65,6,0)," ") -> 0.0055555556 | E42: =IFERROR(D42*C42," ") -> 0.088888889 | F42: =G41 -> 0.49349537 | G42: 0.63958333 | H42: =IF(G42="","", IF(L42=" ",IF(OR(F42=0,G42=0),"",G42-F42),((G42-F42)-L42))) -> 0.081863426 | I42: =IFERROR(IF(L42=" ",(F42+E42),(F42+E42+L42)),"") -> 0.6466088 | L42: 0.064224537 | N42: =IFERROR(E42/H42," ") -> 1.0858193
A43: 45728 | B43: OGM - Sizing update | C43: 9 | D43: =IFERROR(VLOOKUP($B43,Task!$B$1:$G$65,6,0)," ") -> 0.0055555556 | E43: =IFERROR(D43*C43," ") -> 0.05 | F43: =G42 -> 0.63958333 | G43: 0.6875 | H43: =IF(G43="","", IF(L43=" ",IF(OR(F43=0,G43=0),"",G43-F43),((G43-F43)-L43))) -> 0.047916667 | I43: =IFERROR(IF(L43=" ",(F43+E43),(F43+E43+L43)),"") -> 0.68958333 | N43: =IFERROR(E43/H43," ") -> 1.0434783
A44: 45729 | B44: WH - Wholesale order report | C44: 1 | D44: =IFERROR(VLOOKUP($B44,Task!$B$1:$G$65,6,0)," ") -> 0.034722222 | E44: =IFERROR(D44*C44," ") -> 0.034722222 | F44: 0.2944213 | G44: 0.32474537 | H44: =IF(G44="","", IF(L44=" ",IF(OR(F44=0,G44=0),"",G44-F44),((G44-F44)-L44))) -> 0.030324074 | I44: =IFERROR(IF(L44=" ",(F44+E44),(F44+E44+L44)),"") -> 0.32914352 | N44: =IFERROR(E44/H44," ") -> 1.1450382
A45: 45729 | B45: WH - Sale Journal | C45: 1 | D45: =IFERROR(VLOOKUP($B45,Task!$B$1:$G$65,6,0)," ") -> 0.0069444444 | E45: =IFERROR(D45*C45," ") -> 0.0069444444 | F45: =G44 -> 0.32474537 | G45: 0.33140046 | H45: =IF(G45="","", IF(L45=" ",IF(OR(F45=0,G45=0),"",G45-F45),((G45-F45)-L45))) -> 0.0066550926 | I45: =IFERROR(IF(L45=" ",(F45+E45),(F45+E45+L45)),"") -> 0.33168981 | N45: =IFERROR(E45/H45," ") -> 1.0434783
A46: 45729 | B46: Nordstrom SQL DATA Dump | C46: 1 | D46: =IFERROR(VLOOKUP($B46,Task!$B$1:$G$65,6,0)," ") -> 0.048611111 | E46: =IFERROR(D46*C46," ") -> 0.048611111 | F46: =G45 -> 0.33140046 | G46: 0.38216435 | H46: =IF(G46="","", IF(L46=" ",IF(OR(F46=0,G46=0),"",G46-F46),((G46-F46)-L46))) -> 0.043969907 | I46: =IFERROR(IF(L46=" ",(F46+E46),(F46+E46+L46)),"") -> 0.38680556 | L46: 0.0067939815 | N46: =IFERROR(E46/H46," ") -> 1.1055541
A47: 45729 | B47: OGM - Sizing update | C47: 18 | D47: =IFERROR(VLOOKUP($B47,Task!$B$1:$G$65,6,0)," ") -> 0.0055555556 | E47: =IFERROR(D47*C47," ") -> 0.1 | F47: =G46 -> 0.38216435 | G47: 0.47622685 | H47: =IF(G47="","", IF(L47=" ",IF(OR(F47=0,G47=0),"",G47-F47),((G47-F47)-L47))) -> 0.0940625 | I47: =IFERROR(IF(L47=" ",(F47+E47),(F47+E47+L47)),"") -> 0.48216435 | N47: =IFERROR(E47/H47," ") -> 1.0631229
A48: 45729 | B48: OGM - Sizing update | C48: 26 | D48: =IFERROR(VLOOKUP($B48,Task!$B$1:$G$65,6,0)," ") -> 0.0055555556 | E48: =IFERROR(D48*C48," ") -> 0.14444444 | F48: =G47 -> 0.47622685 | G48: 0.67361111 | H48: =IF(G48="","", IF(L48=" ",IF(OR(F48=0,G48=0),"",G48-F48),((G48-F48)-L48))) -> 0.1315625 | I48: =IFERROR(IF(L48=" ",(F48+E48),(F48+E48+L48)),"") -> 0.68649306 | L48: 0.065821759 | N48: =IFERROR(E48/H48," ") -> 1.097915
A49: 45730 | B49: WH - EAN Update | C49: 130 | D49: =IFERROR(VLOOKUP($B49,Task!$B$1:$G$65,6,0)," ") -> 0.0013888889 | E49: =IFERROR(D49*C49," ") -> 0.18055556 | F49: 0.31173611 | G49: 0.51789352 | H49: =IF(G49="","", IF(L49=" ",IF(OR(F49=0,G49=0),"",G49-F49),((G49-F49)-L49))) -> 0.16758102 | I49: =IFERROR(IF(L49=" ",(F49+E49),(F49+E49+L49)),"") -> 0.53086806 | L49: 0.038576389 | N49: =IFERROR(E49/H49," ") -> 1.0774225
A50: 45730 | B50: WH - Fabric Composition | C50: 8 | D50: =IFERROR(VLOOKUP($B50,Task!$B$1:$G$65,6,0)," ") -> 0.0020833333 | E50: =IFERROR(D50*C50," ") -> 0.016666667 | F50: =G49 -> 0.51789352 | G50: 0.53332176 | H50: =IF(G50="","", IF(L50=" ",IF(OR(F50=0,G50=0),"",G50-F50),((G50-F50)-L50))) -> 0.015428241 | I50: =IFERROR(IF(L50=" ",(F50+E50),(F50+E50+L50)),"") -> 0.53456019 | N50: =IFERROR(E50/H50," ") -> 1.0802701
A51: 45730 | B51: WH - Wash Care update | C51: 8 | D51: =IFERROR(VLOOKUP($B51,Task!$B$1:$G$65,6,0)," ") -> 0.0020833333 | E51: =IFERROR(D51*C51," ") -> 0.016666667 | F51: =G50 -> 0.53332176 | G51: 0.54885417 | H51: =IF(G51="","", IF(L51=" ",IF(OR(F51=0,G51=0),"",G51-F51),((G51-F51)-L51))) -> 0.015532407 | I51: =IFERROR(IF(L51=" ",(F51+E51),(F51+E51+L51)),"") -> 0.54998843 | N51: =IFERROR(E51/H51," ") -> 1.0730253
A52: 45730 | B52: DAM - Image Approval | C52: 8 | D52: =IFERROR(VLOOKUP($B52,Task!$B$1:$G$65,6,0)," ") -> 0.0027777778 | E52: =IFERROR(D52*C52," ") -> 0.022222222 | F52: =G51 -> 0.54885417 | G52: 0.60346065 | H52: =IF(G52="","", IF(L52=" ",IF(OR(F52=0,G52=0),"",G52-F52),((G52-F52)-L52))) -> 0.021157407 | I52: =IFERROR(IF(L52=" ",(F52+E52),(F52+E52+L52)),"") -> 0.60452546 | L52: 0.033449074 | N52: =IFERROR(E52/H52," ") -> 1.0503282
A53: 45730 | B53: Nordstrom SQL DATA Dump | C53: 2 | D53: =IFERROR(VLOOKUP($B53,Task!$B$1:$G$65,6,0)," ") -> 0.048611111 | E53: =IFERROR(D53*C53," ") -> 0.097222222 | F53: =G52 -> 0.60346065 | G53: 0.68888889 | H53: =IF(G53="","", IF(L53=" ",IF(OR(F53=0,G53=0),"",G53-F53),((G53-F53)-L53))) -> 0.085428241 | I53: =IFERROR(IF(L53=" ",(F53+E53),(F53+E53+L53)),"") -> 0.70068287 | N53: =IFERROR(E53/H53," ") -> 1.1380572
A54: 45733 | B54: WH - Sale Journal | C54: 1 | D54: =IFERROR(VLOOKUP($B54,Task!$B$1:$G$65,6,0)," ") -> 0.0069444444 | E54: =IFERROR(D54*C54," ") -> 0.0069444444 | F54: 0.30081019 | G54: 0.30760417 | H54: =IF(G54="","", IF(L54=" ",IF(OR(F54=0,G54=0),"",G54-F54),((G54-F54)-L54))) -> 0.0067939815 | I54: =IFERROR(IF(L54=" ",(F54+E54),(F54+E54+L54)),"") -> 0.30775463 | N54: =IFERROR(E54/H54," ") -> 1.0221465
A55: 45733 | B55: WH - Wholesale order report | C55: 1 | D55: =IFERROR(VLOOKUP($B55,Task!$B$1:$G$65,6,0)," ") -> 0.034722222 | E55: =IFERROR(D55*C55," ") -> 0.034722222 | F55: =G54 -> 0.30760417 | G55: 0.34032407 | H55: =IF(G55="","", IF(L55=" ",IF(OR(F55=0,G55=0),"",G55-F55),((G55-F55)-L55))) -> 0.032719907 | I55: =IFERROR(IF(L55=" ",(F55+E55),(F55+E55+L55)),"") -> 0.34232639 | N55: =IFERROR(E55/H55," ") -> 1.0611956
A56: 45733 | B56: Nordstrom SQL DATA Dump | C56: 1 | D56: =IFERROR(VLOOKUP($B56,Task!$B$1:$G$65,6,0)," ") -> 0.048611111 | E56: =IFERROR(D56*C56," ") -> 0.048611111 | F56: =G55 -> 0.34032407 | G56: 0.39663194 | H56: =IF(G56="","", IF(L56=" ",IF(OR(F56=0,G56=0),"",G56-F56),((G56-F56)-L56))) -> 0.04400463 | I56: =IFERROR(IF(L56=" ",(F56+E56),(F56+E56+L56)),"") -> 0.40123843 | L56: 0.012303241 | N56: =IFERROR(E56/H56," ") -> 1.1046817
A57: 45733 | B57: WH - EAN Update | C57: 57 | D57: =IFERROR(VLOOKUP($B57,Task!$B$1:$G$65,6,0)," ") -> 0.0013888889 | E57: =IFERROR(D57*C57," ") -> 0.079166667 | F57: =G56 -> 0.39663194 | G57: 0.47247685 | H57: =IF(G57="","", IF(L57=" ",IF(OR(F57=0,G57=0),"",G57-F57),((G57-F57)-L57))) -> 0.070925926 | I57: =IFERROR(IF(L57=" ",(F57+E57),(F57+E57+L57)),"") -> 0.48071759 | L57: 0.0049189815 | N57: =IFERROR(E57/H57," ") -> 1.116188
A58: 45733 | B58: WH - Country of Origin/ Custom Tarrif | C58: 40 | D58: =IFERROR(VLOOKUP($B58,Task!$B$1:$G$65,6,0)," ") -> 0.0017361111 | E58: =IFERROR(D58*C58," ") -> 0.069444444 | F58: =G57 -> 0.47247685 | G58: 0.54107639 | H58: =IF(G58="","", IF(L58=" ",IF(OR(F58=0,G58=0),"",G58-F58),((G58-F58)-L58))) -> 0.06318287 | I58: =IFERROR(IF(L58=" ",(F58+E58),(F58+E58+L58)),"") -> 0.54733796 | L58: 0.0054166667 | N58: =IFERROR(E58/H58," ") -> 1.0991024
A59: 45733 | B59: OGM - Sizing update | C59: 18 | D59: =IFERROR(VLOOKUP($B59,Task!$B$1:$G$65,6,0)," ") -> 0.0055555556 | E59: =IFERROR(D59*C59," ") -> 0.1 | F59: =G58 -> 0.54107639 | G59: 0.67708333 | H59: =IF(G59="","", IF(L59=" ",IF(OR(F59=0,G59=0),"",G59-F59),((G59-F59)-L59))) -> 0.08787037 | I59: =IFERROR(IF(L59=" ",(F59+E59),(F59+E59+L59)),"") -> 0.68921296 | L59: 0.048136574 | N59: =IFERROR(E59/H59," ") -> 1.13804
A60: 45734 | B60: Nordstrom SQL DATA Dump | C60: 1 | D60: =IFERROR(VLOOKUP($B60,Task!$B$1:$G$65,6,0)," ") -> 0.048611111 | E60: =IFERROR(D60*C60," ") -> 0.048611111 | F60: 0.29947917 | G60: 0.34407407 | H60: =IF(G60="","", IF(L60=" ",IF(OR(F60=0,G60=0),"",G60-F60),((G60-F60)-L60))) -> 0.044594907 | I60: =IFERROR(IF(L60=" ",(F60+E60),(F60+E60+L60)),"") -> 0.34809028 | N60: =IFERROR(E60/H60," ") -> 1.0900597
A61: 45734 | B61: WH - Wash Care update | C61: 40 | D61: =IFERROR(VLOOKUP($B61,Task!$B$1:$G$65,6,0)," ") -> 0.0020833333 | E61: =IFERROR(D61*C61," ") -> 0.083333333 | F61: =G60 -> 0.34407407 | G61: 0.43177083 | H61: =IF(G61="","", IF(L61=" ",IF(OR(F61=0,G61=0),"",G61-F61),((G61-F61)-L61))) -> 0.076967593 | I61: =IFERROR(IF(L61=" ",(F61+E61),(F61+E61+L61)),"") -> 0.43813657 | L61: 0.010729167 | N61: =IFERROR(E61/H61," ") -> 1.0827068
A62: 45734 | B62: Missing information | C62: 16 | D62: =IFERROR(VLOOKUP($B62,Task!$B$1:$G$65,6,0)," ") -> 0.0083333333 | E62: =IFERROR(D62*C62," ") -> 0.13333333 | F62: =G61 -> 0.43177083 | G62: 0.59636574 | H62: =IF(G62="","", IF(L62=" ",IF(OR(F62=0,G62=0),"",G62-F62),((G62-F62)-L62))) -> 0.11803241 | I62: =IFERROR(IF(L62=" ",(F62+E62),(F62+E62+L62)),"") -> 0.61166667 | L62: 0.0465625 | N62: =IFERROR(E62/H62," ") -> 1.1296333
A63: 45734 | B63: Missing information | C63: 8 | D63: =IFERROR(VLOOKUP($B63,Task!$B$1:$G$65,6,0)," ") -> 0.0083333333 | E63: =IFERROR(D63*C63," ") -> 0.066666667 | F63: =G62 -> 0.59636574 | G63: 0.67361111 | H63: =IF(G63="","", IF(L63=" ",IF(OR(F63=0,G63=0),"",G63-F63),((G63-F63)-L63))) -> 0.057974537 | I63: =IFERROR(IF(L63=" ",(F63+E63),(F63+E63+L63)),"") -> 0.68230324 | L63: 0.019270833 | N63: =IFERROR(E63/H63," ") -> 1.1499301
A64: 45735 | B64: WH - Fabric Composition | C64: 40 | D64: =IFERROR(VLOOKUP($B64,Task!$B$1:$G$65,6,0)," ") -> 0.0020833333 | E64: =IFERROR(D64*C64," ") -> 0.083333333 | F64: 0.29329861 | G64: 0.366875 | H64: =IF(G64="","", IF(L64=" ",IF(OR(F64=0,G64=0),"",G64-F64),((G64-F64)-L64))) -> 0.073576389 | I64: =IFERROR(IF(L64=" ",(F64+E64),(F64+E64+L64)),"") -> 0.37663194 | N64: =IFERROR(E64/H64," ") -> 1.1326097
A65: 45735 | B65: SQL Data Dump | C65: 3 | D65: =IFERROR(VLOOKUP($B65,Task!$B$1:$G$65,6,0)," ") -> 0.048611111 | E65: =IFERROR(D65*C65," ") -> 0.14583333 | F65: =G64 -> 0.366875 | G65: 0.53322917 | H65: =IF(G65="","", IF(L65=" ",IF(OR(F65=0,G65=0),"",G65-F65),((G65-F65)-L65))) -> 0.12980324 | I65: =IFERROR(IF(L65=" ",(F65+E65),(F65+E65+L65)),"") -> 0.54925926 | L65: 0.036550926 | N65: =IFERROR(E65/H65," ") -> 1.1234953
A66: 45735 | B66: Missing information | C66: 12 | D66: =IFERROR(VLOOKUP($B66,Task!$B$1:$G$65,6,0)," ") -> 0.0083333333 | E66: =IFERROR(D66*C66," ") -> 0.1 | F66: =G65 -> 0.53322917 | G66: 0.67013889 | H66: =IF(G66="","", IF(L66=" ",IF(OR(F66=0,G66=0),"",G66-F66),((G66-F66)-L66))) -> 0.089537037 | I66: =IFERROR(IF(L66=" ",(F66+E66),(F66+E66+L66)),"") -> 0.68060185 | L66: 0.047372685 | N66: =IFERROR(E66/H66," ") -> 1.1168563
A67: 45736 | B67: WH - Wholesale order report | C67: 1 | D67: =IFERROR(VLOOKUP($B67,Task!$B$1:$G$65,6,0)," ") -> 0.034722222 | E67: =IFERROR(D67*C67," ") -> 0.034722222 | F67: 0.30857639 | G67: 0.33994213 | H67: =IF(G67="","", IF(L67=" ",IF(OR(F67=0,G67=0),"",G67-F67),((G67-F67)-L67))) -> 0.031365741 | I67: =IFERROR(IF(L67=" ",(F67+E67),(F67+E67+L67)),"") -> 0.34329861 | N67: =IFERROR(E67/H67," ") -> 1.1070111
A68: 45736 | B68: WH - Sale Journal | C68: 1 | D68: =IFERROR(VLOOKUP($B68,Task!$B$1:$G$65,6,0)," ") -> 0.0069444444 | E68: =IFERROR(D68*C68," ") -> 0.0069444444 | F68: =G67 -> 0.33994213 | G68: 0.34636574 | H68: =IF(G68="","", IF(L68=" ",IF(OR(F68=0,G68=0),"",G68-F68),((G68-F68)-L68))) -> 0.0064236111 | I68: =IFERROR(IF(L68=" ",(F68+E68),(F68+E68+L68)),"") -> 0.34688657 | N68: =IFERROR(E68/H68," ") -> 1.0810811
A69: 45736 | B69: Nordstrom SQL DATA Dump | C69: 1 | D69: =IFERROR(VLOOKUP($B69,Task!$B$1:$G$65,6,0)," ") -> 0.048611111 | E69: =IFERROR(D69*C69," ") -> 0.048611111 | F69: =G68 -> 0.34636574 | G69: 0.39096065 | H69: =IF(G69="","", IF(L69=" ",IF(OR(F69=0,G69=0),"",G69-F69),((G69-F69)-L69))) -> 0.044594907 | I69: =IFERROR(IF(L69=" ",(F69+E69),(F69+E69+L69)),"") -> 0.39497685 | N69: =IFERROR(E69/H69," ") -> 1.0900597
A70: 45736 | B70: Missing information | C70: 7 | D70: =IFERROR(VLOOKUP($B70,Task!$B$1:$G$65,6,0)," ") -> 0.0083333333 | E70: =IFERROR(D70*C70," ") -> 0.058333333 | F70: 0.39096065 | G70: 0.5025463 | H70: =IF(G70="","", IF(L70=" ",IF(OR(F70=0,G70=0),"",G70-F70),((G70-F70)-L70))) -> 0.052256944 | I70: =IFERROR(IF(L70=" ",(F70+E70),(F70+E70+L70)),"") -> 0.50862269 | L70: 0.059328704 | N70: =IFERROR(E70/H70," ") -> 1.1162791
A71: 45736 | B71: DAM - Image Approval | C71: 5 | D71: =IFERROR(VLOOKUP($B71,Task!$B$1:$G$65,6,0)," ") -> 0.0027777778 | E71: =IFERROR(D71*C71," ") -> 0.013888889 | F71: =G70 -> 0.5025463 | G71: 0.51572917 | H71: =IF(G71="","", IF(L71=" ",IF(OR(F71=0,G71=0),"",G71-F71),((G71-F71)-L71))) -> 0.01318287 | I71: =IFERROR(IF(L71=" ",(F71+E71),(F71+E71+L71)),"") -> 0.51643519 | N71: =IFERROR(E71/H71," ") -> 1.0535558
A72: 45736 | B72: OGM - Sizing update | C72: 26 | D72: =IFERROR(VLOOKUP($B72,Task!$B$1:$G$65,6,0)," ") -> 0.0055555556 | E72: =IFERROR(D72*C72," ") -> 0.14444444 | F72: =G71 -> 0.51572917 | G72: 0.68931635 | H72: =IF(G72="","", IF(L72=" ",IF(OR(F72=0,G72=0),"",G72-F72),((G72-F72)-L72))) -> 0.12289274 | I72: =IFERROR(IF(L72=" ",(F72+E72),(F72+E72+L72)),"") -> 0.71086806 | L72: 0.050694444 | N72: =IFERROR(E72/H72," ") -> 1.17537
A73: 45740 | B73: DAM - Image Search | C73: 95 | D73: =IFERROR(VLOOKUP($B73,Task!$B$1:$G$65,6,0)," ") -> 0.00069444444 | E73: =IFERROR(D73*C73," ") -> 0.065972222 | F73: 0.30564815 | G73: 0.37432208 | H73: =IF(G73="","", IF(L73=" ",IF(OR(F73=0,G73=0),"",G73-F73),((G73-F73)-L73))) -> 0.056139213 | I73: =IFERROR(IF(L73=" ",(F73+E73),(F73+E73+L73)),"") -> 0.38415509 | L73: 0.012534722 | N73: =IFERROR(E73/H73," ") -> 1.175154
A74: 45740 | B74: WH - Sale Journal | C74: 1 | D74: =IFERROR(VLOOKUP($B74,Task!$B$1:$G$65,6,0)," ") -> 0.0069444444 | E74: =IFERROR(D74*C74," ") -> 0.0069444444 | F74: 0.4005787 | G74: 0.40725694 | H74: =IF(G74="","", IF(L74=" ",IF(OR(F74=0,G74=0),"",G74-F74),((G74-F74)-L74))) -> 0.0066782407 | I74: =IFERROR(IF(L74=" ",(F74+E74),(F74+E74+L74)),"") -> 0.40752315 | N74: =IFERROR(E74/H74," ") -> 1.0398614
A75: 45740 | B75: WH - Wholesale order report | C75: 1 | D75: =IFERROR(VLOOKUP($B75,Task!$B$1:$G$65,6,0)," ") -> 0.034722222 | E75: =IFERROR(D75*C75," ") -> 0.034722222 | F75: =G74 -> 0.40725694 | G75: 0.44996528 | H75: =IF(G75="","", IF(L75=" ",IF(OR(F75=0,G75=0),"",G75-F75),((G75-F75)-L75))) -> 0.031296296 | I75: =IFERROR(IF(L75=" ",(F75+E75),(F75+E75+L75)),"") -> 0.4533912 | L75: 0.011412037 | N75: =IFERROR(E75/H75," ") -> 1.1094675
A76: 45740 | B76: Nordstrom SQL DATA Dump | C76: 2 | D76: =IFERROR(VLOOKUP($B76,Task!$B$1:$G$65,6,0)," ") -> 0.048611111 | E76: =IFERROR(D76*C76," ") -> 0.097222222 | F76: =G75 -> 0.44996528 | G76: 0.54003472 | H76: =IF(G76="","", IF(L76=" ",IF(OR(F76=0,G76=0),"",G76-F76),((G76-F76)-L76))) -> 0.090069444 | I76: =IFERROR(IF(L76=" ",(F76+E76),(F76+E76+L76)),"") -> 0.5471875 | N76: =IFERROR(E76/H76," ") -> 1.079414
A77: 45740 | B77: OGM - Sizing update | C77: 20 | D77: =IFERROR(VLOOKUP($B77,Task!$B$1:$G$65,6,0)," ") -> 0.0055555556 | E77: =IFERROR(D77*C77," ") -> 0.11111111 | F77: =G76 -> 0.54003472 | G77: 0.6875 | H77: =IF(G77="","", IF(L77=" ",IF(OR(F77=0,G77=0),"",G77-F77),((G77-F77)-L77))) -> 0.097453704 | I77: =IFERROR(IF(L77=" ",(F77+E77),(F77+E77+L77)),"") -> 0.70115741 | L77: 0.050011574 | N77: =IFERROR(E77/H77," ") -> 1.1401425
A78: 45741 | B78: Nordstrom SQL DATA Dump | C78: 3 | D78: =IFERROR(VLOOKUP($B78,Task!$B$1:$G$65,6,0)," ") -> 0.048611111 | E78: =IFERROR(D78*C78," ") -> 0.14583333 | F78: 0.31570602 | G78: 0.45019676 | H78: =IF(G78="","", IF(L78=" ",IF(OR(F78=0,G78=0),"",G78-F78),((G78-F78)-L78))) -> 0.13449074 | I78: =IFERROR(IF(L78=" ",(F78+E78),(F78+E78+L78)),"") -> 0.46153935 | N78: =IFERROR(E78/H78," ") -> 1.0843373
A79: 45741 | B79: Missing information | C79: 25 | D79: =IFERROR(VLOOKUP($B79,Task!$B$1:$G$65,6,0)," ") -> 0.0083333333 | E79: =IFERROR(D79*C79," ") -> 0.20833333 | F79: =G78 -> 0.45019676 | G79: 0.69444444 | H79: =IF(G79="","", IF(L79=" ",IF(OR(F79=0,G79=0),"",G79-F79),((G79-F79)-L79))) -> 0.17767361 | I79: =IFERROR(IF(L79=" ",(F79+E79),(F79+E79+L79)),"") -> 0.72510417 | L79: 0.066574074 | N79: =IFERROR(E79/H79," ") -> 1.172562
A80: 45742 | B80: Missing information | C80: 5 | D80: =IFERROR(VLOOKUP($B80,Task!$B$1:$G$65,6,0)," ") -> 0.0083333333 | E80: =IFERROR(D80*C80," ") -> 0.041666667 | F80: 0.31626157 | G80: 0.35342593 | H80: =IF(G80="","", IF(L80=" ",IF(OR(F80=0,G80=0),"",G80-F80),((G80-F80)-L80))) -> 0.037164352 | I80: =IFERROR(IF(L80=" ",(F80+E80),(F80+E80+L80)),"") -> 0.35792824 | N80: =IFERROR(E80/H80," ") -> 1.1211461
A81: 45742 | B81: Nordstrom SQL DATA Dump | C81: 1 | D81: =IFERROR(VLOOKUP($B81,Task!$B$1:$G$65,6,0)," ") -> 0.048611111 | E81: =IFERROR(D81*C81," ") -> 0.048611111 | F81: =G80 -> 0.35342593 | G81: 0.39724537 | H81: =IF(G81="","", IF(L81=" ",IF(OR(F81=0,G81=0),"",G81-F81),((G81-F81)-L81))) -> 0.043819444 | I81: =IFERROR(IF(L81=" ",(F81+E81),(F81+E81+L81)),"") -> 0.40203704 | N81: =IFERROR(E81/H81," ") -> 1.1093502
A82: 45742 | B82: Franchise Adding Images | C82: 95 | D82: =IFERROR(VLOOKUP($B82,Task!$B$1:$G$65,6,0)," ") -> 0.0013888889 | E82: =IFERROR(D82*C82," ") -> 0.13194444 | F82: =G81 -> 0.39724537 | G82: 0.53700231 | H82: =IF(G82="","", IF(L82=" ",IF(OR(F82=0,G82=0),"",G82-F82),((G82-F82)-L82))) -> 0.119375 | I82: =IFERROR(IF(L82=" ",(F82+E82),(F82+E82+L82)),"") -> 0.54957176 | L82: 0.020381944 | N82: =IFERROR(E82/H82," ") -> 1.1052938
A83: 45742 | B83: OGM - Sizing update | C83: 16 | D83: =IFERROR(VLOOKUP($B83,Task!$B$1:$G$65,6,0)," ") -> 0.0055555556 | E83: =IFERROR(D83*C83," ") -> 0.088888889 | F83: =G82 -> 0.53700231 | G83: 0.69444444 | H83: =IF(G83="","", IF(L83=" ",IF(OR(F83=0,G83=0),"",G83-F83),((G83-F83)-L83))) -> 0.076458333 | I83: =IFERROR(IF(L83=" ",(F83+E83),(F83+E83+L83)),"") -> 0.706875 | L83: 0.080983796 | N83: =IFERROR(E83/H83," ") -> 1.1625795
A84: 45743 | B84: Nordstrom SQL DATA Dump | C84: 1 | D84: =IFERROR(VLOOKUP($B84,Task!$B$1:$G$65,6,0)," ") -> 0.048611111 | E84: =IFERROR(D84*C84," ") -> 0.048611111 | F84: 0.36059028 | G84: 0.40422454 | H84: =IF(G84="","", IF(L84=" ",IF(OR(F84=0,G84=0),"",G84-F84),((G84-F84)-L84))) -> 0.043634259 | I84: =IFERROR(IF(L84=" ",(F84+E84),(F84+E84+L84)),"") -> 0.40920139 | N84: =IFERROR(E84/H84," ") -> 1.1140584
A85: 45743 | B85: OGM - Sizing update | C85: 18 | D85: =IFERROR(VLOOKUP($B85,Task!$B$1:$G$65,6,0)," ") -> 0.0055555556 | E85: =IFERROR(D85*C85," ") -> 0.1 | F85: =G84 -> 0.40422454 | G85: 0.49478009 | H85: =IF(G85="","", IF(L85=" ",IF(OR(F85=0,G85=0),"",G85-F85),((G85-F85)-L85))) -> 0.090555556 | I85: =IFERROR(IF(L85=" ",(F85+E85),(F85+E85+L85)),"") -> 0.50422454 | N85: =IFERROR(E85/H85," ") -> 1.1042945
A86: 45743 | B86: Trade Report | C86: 4 | D86: =IFERROR(VLOOKUP($B86,Task!$B$1:$G$65,6,0)," ") -> 0.020833333 | E86: =IFERROR(D86*C86," ") -> 0.083333333 | F86: =G85 -> 0.49478009 | G86: 0.61793956 | H86: =IF(G86="","", IF(L86=" ",IF(OR(F86=0,G86=0),"",G86-F86),((G86-F86)-L86))) -> 0.074409468 | I86: =IFERROR(IF(L86=" ",(F86+E86),(F86+E86+L86)),"") -> 0.62686343 | L86: 0.04875 | N86: =IFERROR(E86/H86," ") -> 1.1199292
A87: 45743 | B87: OGM - Sizing update | C87: 21 | D87: =IFERROR(VLOOKUP($B87,Task!$B$1:$G$65,6,0)," ") -> 0.0055555556 | E87: =IFERROR(D87*C87," ") -> 0.11666667 | F87: =G86 -> 0.61793956 | G87: 0.73611111 | H87: =IF(G87="","", IF(L87=" ",IF(OR(F87=0,G87=0),"",G87-F87),((G87-F87)-L87))) -> 0.10625025 | I87: =IFERROR(IF(L87=" ",(F87+E87),(F87+E87+L87)),"") -> 0.74652752 | L87: 0.011921296 | N87: =IFERROR(E87/H87," ") -> 1.0980366
D88: =IFERROR(VLOOKUP($B88,Task!$B$1:$G$65,6,0)," ") | E88: =IFERROR(D88*C88," ") | H88: =IF(G88="","", IF(L88=" ",IF(OR(F88=0,G88=0),"",G88-F88),((G88-F88)-L88))) | I88: =IFERROR(IF(L88=" ",(F88+E88),(F88+E88+L88)),"") | N88: =IFERROR(E88/H88," ")
D89: =IFERROR(VLOOKUP($B89,Task!$B$1:$G$65,6,0)," ") | E89: =IFERROR(D89*C89," ") | H89: =IF(G89="","", IF(L89=" ",IF(OR(F89=0,G89=0),"",G89-F89),((G89-F89)-L89))) | I89: =IFERROR(IF(L89=" ",(F89+E89),(F89+E89+L89)),"") | N89: =IFERROR(E89/H89," ") | O89: =AVERAGEIF(A:A,TODAY(),N:N) -> #DIV/0!
D90: =IFERROR(VLOOKUP($B90,Task!$B$1:$G$65,6,0)," ") | E90: =IFERROR(D90*C90," ") | H90: =IF(G90="","", IF(L90=" ",IF(OR(F90=0,G90=0),"",G90-F90),((G90-F90)-L90))) | I90: =IFERROR(IF(L90=" ",(F90+E90),(F90+E90+L90)),"") | N90: =IFERROR(E90/H90," ")
D91: =IFERROR(VLOOKUP($B91,Task!$B$1:$G$65,6,0)," ") | E91: =IFERROR(D91*C91," ") | H91: =IF(G91="","", IF(L91=" ",IF(OR(F91=0,G91=0),"",G91-F91),((G91-F91)-L91))) | I91: =IFERROR(IF(L91=" ",(F91+E91),(F91+E91+L91)),"") | N91: =IFERROR(E91/H91," ")
D92: =IFERROR(VLOOKUP($B92,Task!$B$1:$G$65,6,0)," ") | E92: =IFERROR(D92*C92," ") | H92: =IF(G92="","", IF(L92=" ",IF(OR(F92=0,G92=0),"",G92-F92),((G92-F92)-L92))) | I92: =IFERROR(IF(L92=" ",(F92+E92),(F92+E92+L92)),"") | N92: =IFERROR(E92/H92," ")
D93: =IFERROR(VLOOKUP($B93,Task!$B$1:$G$65,6,0)," ") | E93: =IFERROR(D93*C93," ") | H93: =IF(G93="","", IF(L93=" ",IF(OR(F93=0,G93=0),"",G93-F93),((G93-F93)-L93))) | I93: =IFERROR(IF(L93=" ",(F93+E93),(F93+E93+L93)),"") | N93: =IFERROR(E93/H93," ")
D94: =IFERROR(VLOOKUP($B94,Task!$B$1:$G$65,6,0)," ") | E94: =IFERROR(D94*C94," ") | H94: =IF(G94="","", IF(L94=" ",IF(OR(F94=0,G94=0),"",G94-F94),((G94-F94)-L94))) | I94: =IFERROR(IF(L94=" ",(F94+E94),(F94+E94+L94)),"") | N94: =IFERROR(E94/H94," ")
D95: =IFERROR(VLOOKUP($B95,Task!$B$1:$G$65,6,0)," ") | E95: =IFERROR(D95*C95," ") | H95: =IF(G95="","", IF(L95=" ",IF(OR(F95=0,G95=0),"",G95-F95),((G95-F95)-L95))) | I95: =IFERROR(IF(L95=" ",(F95+E95),(F95+E95+L95)),"") | N95: =IFERROR(E95/H95," ")
D96: =IFERROR(VLOOKUP($B96,Task!$B$1:$G$65,6,0)," ") | E96: =IFERROR(D96*C96," ") | H96: =IF(G96="","", IF(L96=" ",IF(OR(F96=0,G96=0),"",G96-F96),((G96-F96)-L96))) | I96: =IFERROR(IF(L96=" ",(F96+E96),(F96+E96+L96)),"") | N96: =IFERROR(E96/H96," ")
D97: =IFERROR(VLOOKUP($B97,Task!$B$1:$G$65,6,0)," ") | E97: =IFERROR(D97*C97," ") | H97: =IF(G97="","", IF(L97=" ",IF(OR(F97=0,G97=0),"",G97-F97),((G97-F97)-L97))) | I97: =IFERROR(IF(L97=" ",(F97+E97),(F97+E97+L97)),"") | N97: =IFERROR(E97/H97," ")
D98: =IFERROR(VLOOKUP($B98,Task!$B$1:$G$65,6,0)," ") | E98: =IFERROR(D98*C98," ") | H98: =IF(G98="","", IF(L98=" ",IF(OR(F98=0,G98=0),"",G98-F98),((G98-F98)-L98))) | I98: =IFERROR(IF(L98=" ",(F98+E98),(F98+E98+L98)),"") | N98: =IFERROR(E98/H98," ")
D99: =IFERROR(VLOOKUP($B99,Task!$B$1:$G$65,6,0)," ") | E99: =IFERROR(D99*C99," ") | H99: =IF(G99="","", IF(L99=" ",IF(OR(F99=0,G99=0),"",G99-F99),((G99-F99)-L99))) | I99: =IFERROR(IF(L99=" ",(F99+E99),(F99+E99+L99)),"") | N99: =IFERROR(E99/H99," ")
D100: =IFERROR(VLOOKUP($B100,Task!$B$1:$G$65,6,0)," ") | E100: =IFERROR(D100*C100," ") | H100: =IF(G100="","", IF(L100=" ",IF(OR(F100=0,G100=0),"",G100-F100),((G100-F100)-L100))) | I100: =IFERROR(IF(L100=" ",(F100+E100),(F100+E100+L100)),"") | N100: =IFERROR(E100/H100," ")
...

Sheet Feb 25
A1: Date | B1: Task Name | C1: Quantity | D1: RE | E1: Total RE | F1: Start Time | G1: End Time | H1: Actual Time taken | I1: Actual End Time | J1: Break Start Time | K1: Break End Time | L1: Total Break time | M1: Comment | N1: Productivity | O1: 0.22916667 | P1: Date | Q1: Total RE | R1: Core | S1: Non-Core | T1: Productivity | U1: 0.33333333
A2: 45691 | B2: WH - Wholesale order report | C2: 1 | D2: =IFERROR(VLOOKUP($B2,Task!$B$1:$G$65,6,0)," ") -> 0.034722222 | E2: =IFERROR(D2*C2," ") -> 0.034722222 | F2: 0.37659722 | G2: 0.40811343 | H2: =IF(G2="","", IF(L2=" ",IF(OR(F2=0,G2=0),"",G2-F2),((G2-F2)-L2))) -> 0.031516204 | I2: =IFERROR(IF(L2=" ",(F2+E2),(F2+E2+L2)),"") -> 0.41131944 | N2: =IFERROR(E2/H2," ") -> 1.101726 | O2: 0.61469907 | P2: =IFERROR(__xludf.DUMMYFUNCTION("UNIQUE($A$2:$A$993)"),45691) -> 45691 | Q2: =SUMIF($A:$A,$P2,$E:$E) -> 0.34375 | R2: =SUMIF($A:$A,$P2,$H:$H) -> 0.3290162 | S2: =IF(OR(R2="",R2>=$U$1)," ",$U$1-R2) -> 0.0043171296 | T2: =IFERROR(AVERAGEIF($A:$A,$P2,$N:$N)," ") -> 1.0644296
A3: 45691 | B3: WH - Sale Journal | C3: 1 | D3: =IFERROR(VLOOKUP($B3,Task!$B$1:$G$65,6,0)," ") -> 0.0069444444 | E3: =IFERROR(D3*C3," ") -> 0.0069444444 | F3: =G2 -> 0.40811343 | G3: 0.41453704 | H3: =IF(G3="","", IF(L3=" ",IF(OR(F3=0,G3=0),"",G3-F3),((G3-F3)-L3))) -> 0.0064236111 | I3: =IFERROR(IF(L3=" ",(F3+E3),(F3+E3+L3)),"") -> 0.41505787 | N3: =IFERROR(E3/H3," ") -> 1.0810811 | O3: =O2-O1 -> 0.38553241 | P3: =IFERROR(__xludf.DUMMYFUNCTION("""COMPUTED_VALUE"""),45692) -> 45692 | Q3: =IF(SUMIF($A:$A,$P3,$E:$E)=0,"",SUMIF($A:$A,$P3,$E:$E)) -> 0.33055556 | R3: =IF(SUMIF($A:$A,$P3,$H:$H)=0,"",SUMIF($A:$A,$P3,$H:$H)) -> 0.31247363 | S3: =IF(OR(R3="",R3>=$U$1)," ",$U$1-R3) -> 0.020859699 | T3: =IFERROR(AVERAGEIF($A:$A,$P3,$N:$N)," ") -> 1.055776
A4: 45691 | B4: Nordstrom SQL DATA Dump | C4: 1 | D4: =IFERROR(VLOOKUP($B4,Task!$B$1:$G$65,6,0)," ") -> 0.048611111 | E4: =IFERROR(D4*C4," ") -> 0.048611111 | F4: =G3 -> 0.41453704 | G4: 0.45997685 | H4: =IF(G4="","", IF(L4=" ",IF(OR(F4=0,G4=0),"",G4-F4),((G4-F4)-L4))) -> 0.045439815 | I4: =IFERROR(IF(L4=" ",(F4+E4),(F4+E4+L4)),"") -> 0.46314815 | N4: =IFERROR(E4/H4," ") -> 1.0697911 | P4: =IFERROR(__xludf.DUMMYFUNCTION("""COMPUTED_VALUE"""),45693) -> 45693 | Q4: =IF(SUMIF($A:$A,$P4,$E:$E)=0,"",SUMIF($A:$A,$P4,$E:$E)) -> 0.35138889 | R4: =IF(SUMIF($A:$A,$P4,$H:$H)=0,"",SUMIF($A:$A,$P4,$H:$H)) -> 0.33048611 | S4: =IF(OR(R4="",R4>=$U$1)," ",$U$1-R4) -> 0.0028472222 | T4: =IFERROR(AVERAGEIF($A:$A,$P4,$N:$N)," ") -> 1.0793418
A5: 45691 | B5: Nordstrom Assets | C5: 115 | D5: =IFERROR(VLOOKUP($B5,Task!$B$1:$G$65,6,0)," ") -> 0.0013888889 | E5: =IFERROR(D5*C5," ") -> 0.15972222 | F5: =G4 -> 0.45997685 | G5: 0.65040509 | H5: =IF(G5="","", IF(L5=" ",IF(OR(F5=0,G5=0),"",G5-F5),((G5-F5)-L5))) -> 0.15596065 | I5: =IFERROR(IF(L5=" ",(F5+E5),(F5+E5+L5)),"") -> 0.65416667 | L5: 0.034467593 | M5: 27 Nordstrom Assets | N5: =IFERROR(E5/H5," ") -> 1.0241187 | P5: =IFERROR(__xludf.DUMMYFUNCTION("""COMPUTED_VALUE"""),45694) -> 45694 | Q5: =IF(SUMIF($A:$A,$P5,$E:$E)=0,"",SUMIF($A:$A,$P5,$E:$E)) -> 0.31527778 | R5: =IF(SUMIF($A:$A,$P5,$H:$H)=0,"",SUMIF($A:$A,$P5,$H:$H)) -> 0.30510417 | S5: =IF(OR(R5="",R5>=$U$1)," ",$U$1-R5) -> 0.028229167 | T5: =IFERROR(AVERAGEIF($A:$A,$P5,$N:$N)," ") -> 1.0427248
A6: 45691 | B6: WH - Fabric Composition | C6: 45 | D6: =IFERROR(VLOOKUP($B6,Task!$B$1:$G$65,6,0)," ") -> 0.0020833333 | E6: =IFERROR(D6*C6," ") -> 0.09375 | F6: =G5 -> 0.65040509 | G6: 0.75347222 | H6: =IF(G6="","", IF(L6=" ",IF(OR(F6=0,G6=0),"",G6-F6),((G6-F6)-L6))) -> 0.089675926 | I6: =IFERROR(IF(L6=" ",(F6+E6),(F6+E6+L6)),"") -> 0.7575463 | L6: 0.013391204 | N6: =IFERROR(E6/H6," ") -> 1.0454311 | P6: =IFERROR(__xludf.DUMMYFUNCTION("""COMPUTED_VALUE"""),45695) -> 45695 | Q6: =IF(SUMIF($A:$A,$P6,$E:$E)=0,"",SUMIF($A:$A,$P6,$E:$E)) -> 0.32986111 | R6: =IF(SUMIF($A:$A,$P6,$H:$H)=0,"",SUMIF($A:$A,$P6,$H:$H)) -> 0.30982639 | S6: =IF(OR(R6="",R6>=$U$1)," ",$U$1-R6) -> 0.023506944 | T6: =IFERROR(AVERAGEIF($A:$A,$P6,$N:$N)," ") -> 1.0548963
A7: 45692 | B7: Nordstrom SQL DATA Dump | C7: 1 | D7: =IFERROR(VLOOKUP($B7,Task!$B$1:$G$65,6,0)," ") -> 0.048611111 | E7: =IFERROR(D7*C7," ") -> 0.048611111 | F7: 0.37458333 | G7: 0.42402778 | H7: =IF(G7="","", IF(L7=" ",IF(OR(F7=0,G7=0),"",G7-F7),((G7-F7)-L7))) -> 0.049444444 | I7: =IFERROR(IF(L7=" ",(F7+E7),(F7+E7+L7)),"") -> 0.42319444 | N7: =IFERROR(E7/H7," ") -> 0.98314607 | P7: =IFERROR(__xludf.DUMMYFUNCTION("""COMPUTED_VALUE"""),45698) -> 45698 | Q7: =IF(SUMIF($A:$A,$P7,$E:$E)=0,"",SUMIF($A:$A,$P7,$E:$E)) -> 0.32638889 | R7: =IF(SUMIF($A:$A,$P7,$H:$H)=0,"",SUMIF($A:$A,$P7,$H:$H)) -> 0.30366898 | S7: =IF(OR(R7="",R7>=$U$1)," ",$U$1-R7) -> 0.029664352 | T7: =IFERROR(AVERAGEIF($A:$A,$P7,$N:$N)," ") -> 1.0754125
A8: 45692 | B8: Nordstrom Assets | C8: 47 | D8: =IFERROR(VLOOKUP($B8,Task!$B$1:$G$65,6,0)," ") -> 0.0013888889 | E8: =IFERROR(D8*C8," ") -> 0.065277778 | F8: =G7 -> 0.42402778 | G8: 0.48304398 | H8: =IF(G8="","", IF(L8=" ",IF(OR(F8=0,G8=0),"",G8-F8),((G8-F8)-L8))) -> 0.059016204 | I8: =IFERROR(IF(L8=" ",(F8+E8),(F8+E8+L8)),"") -> 0.48930556 | M8: 27 Nordstrom Assets | N8: =IFERROR(E8/H8," ") -> 1.1060992 | P8: =IFERROR(__xludf.DUMMYFUNCTION("""COMPUTED_VALUE"""),45699) -> 45699 | Q8: =IF(SUMIF($A:$A,$P8,$E:$E)=0,"",SUMIF($A:$A,$P8,$E:$E)) -> 0.29652778 | R8: =IF(SUMIF($A:$A,$P8,$H:$H)=0,"",SUMIF($A:$A,$P8,$H:$H)) -> 0.28773697 | S8: =IF(OR(R8="",R8>=$U$1)," ",$U$1-R8) -> 0.045596366 | T8: =IFERROR(AVERAGEIF($A:$A,$P8,$N:$N)," ") -> 1.0253634
A9: 45692 | B9: WH - Fabric Composition | C9: 29 | D9: =IFERROR(VLOOKUP($B9,Task!$B$1:$G$65,6,0)," ") -> 0.0020833333 | E9: =IFERROR(D9*C9," ") -> 0.060416667 | F9: =G8 -> 0.48304398 | G9: 0.57208333 | H9: =IF(G9="","", IF(L9=" ",IF(OR(F9=0,G9=0),"",G9-F9),((G9-F9)-L9))) -> 0.057650463 | I9: =IFERROR(IF(L9=" ",(F9+E9),(F9+E9+L9)),"") -> 0.57484954 | L9: 0.031388889 | N9: =IFERROR(E9/H9," ") -> 1.0479823 | P9: =IFERROR(__xludf.DUMMYFUNCTION("""COMPUTED_VALUE"""),45701) -> 45701 | Q9: =IF(SUMIF($A:$A,$P9,$E:$E)=0,"",SUMIF($A:$A,$P9,$E:$E)) -> 0.32430556 | R9: =IF(SUMIF($A:$A,$P9,$H:$H)=0,"",SUMIF($A:$A,$P9,$H:$H)) -> 0.30419656 | S9: =IF(OR(R9="",R9>=$U$1)," ",$U$1-R9) -> 0.029136771 | T9: =IFERROR(AVERAGEIF($A:$A,$P9,$N:$N)," ") -> 1.0853731
A10: 45692 | B10: WH - Country of Origin/ Custom Tarrif | C10: 55 | D10: =IFERROR(VLOOKUP($B10,Task!$B$1:$G$65,6,0)," ") -> 0.0017361111 | E10: =IFERROR(D10*C10," ") -> 0.095486111 | F10: =G9 -> 0.57208333 | G10: 0.70800926 | H10: =IF(G10="","", IF(L10=" ",IF(OR(F10=0,G10=0),"",G10-F10),((G10-F10)-L10))) -> 0.090347222 | I10: =IFERROR(IF(L10=" ",(F10+E10),(F10+E10+L10)),"") -> 0.71314815 | L10: 0.045578704 | N10: =IFERROR(E10/H10," ") -> 1.0568793 | P10: =IFERROR(__xludf.DUMMYFUNCTION("""COMPUTED_VALUE"""),45702) -> 45702 | Q10: =IF(SUMIF($A:$A,$P10,$E:$E)=0,"",SUMIF($A:$A,$P10,$E:$E)) -> 0.31666667 | R10: =IF(SUMIF($A:$A,$P10,$H:$H)=0,"",SUMIF($A:$A,$P10,$H:$H)) -> 0.30382186 | S10: =IF(OR(R10="",R10>=$U$1)," ",$U$1-R10) -> 0.02951147 | T10: =IFERROR(AVERAGEIF($A:$A,$P10,$N:$N)," ") -> 1.0531728
A11: 45692 | B11: WH - Country of Origin/ Custom Tarrif | C11: 35 | D11: =IFERROR(VLOOKUP($B11,Task!$B$1:$G$65,6,0)," ") -> 0.0017361111 | E11: =IFERROR(D11*C11," ") -> 0.060763889 | F11: =G10 -> 0.70800926 | G11: 0.76402456 | H11: =IF(G11="","", IF(L11=" ",IF(OR(F11=0,G11=0),"",G11-F11),((G11-F11)-L11))) -> 0.056015301 | I11: =IFERROR(IF(L11=" ",(F11+E11),(F11+E11+L11)),"") -> 0.76877315 | N11: =IFERROR(E11/H11," ") -> 1.0847731 | P11: =IFERROR(__xludf.DUMMYFUNCTION("""COMPUTED_VALUE"""),45705) -> 45705 | Q11: =IF(SUMIF($A:$A,$P11,$E:$E)=0,"",SUMIF($A:$A,$P11,$E:$E)) -> 0.34583333 | R11: =IF(SUMIF($A:$A,$P11,$H:$H)=0,"",SUMIF($A:$A,$P11,$H:$H)) -> 0.31865741 | S11: =IF(OR(R11="",R11>=$U$1)," ",$U$1-R11) -> 0.014675926 | T11: =IFERROR(AVERAGEIF($A:$A,$P11,$N:$N)," ") -> 1.0888168
A12: 45693 | B12: Nordstrom SQL DATA Dump | C12: 1 | D12: =IFERROR(VLOOKUP($B12,Task!$B$1:$G$65,6,0)," ") -> 0.048611111 | E12: =IFERROR(D12*C12," ") -> 0.048611111 | F12: 0.38030093 | G12: 0.42546296 | H12: =IF(G12="","", IF(L12=" ",IF(OR(F12=0,G12=0),"",G12-F12),((G12-F12)-L12))) -> 0.045162037 | I12: =IFERROR(IF(L12=" ",(F12+E12),(F12+E12+L12)),"") -> 0.42891204 | M12: ss25 | N12: =IFERROR(E12/H12," ") -> 1.0763711 | P12: =IFERROR(__xludf.DUMMYFUNCTION("""COMPUTED_VALUE"""),45706) -> 45706 | Q12: =IF(SUMIF($A:$A,$P12,$E:$E)=0,"",SUMIF($A:$A,$P12,$E:$E)) -> 0.31319444 | R12: =IF(SUMIF($A:$A,$P12,$H:$H)=0,"",SUMIF($A:$A,$P12,$H:$H)) -> 0.30130749 | S12: =IF(OR(R12="",R12>=$U$1)," ",$U$1-R12) -> 0.032025845 | T12: =IFERROR(AVERAGEIF($A:$A,$P12,$N:$N)," ") -> 1.0625953
A13: 45693 | B13: OGM - Sizing update | C13: 4 | D13: =IFERROR(VLOOKUP($B13,Task!$B$1:$G$65,6,0)," ") -> 0.0055555556 | E13: =IFERROR(D13*C13," ") -> 0.022222222 | F13: =G12 -> 0.42546296 | G13: 0.4459838 | H13: =IF(G13="","", IF(L13=" ",IF(OR(F13=0,G13=0),"",G13-F13),((G13-F13)-L13))) -> 0.020520833 | I13: =IFERROR(IF(L13=" ",(F13+E13),(F13+E13+L13)),"") -> 0.44768519 | N13: =IFERROR(E13/H13," ") -> 1.0829103 | P13: =IFERROR(__xludf.DUMMYFUNCTION("""COMPUTED_VALUE"""),45707) -> 45707 | Q13: =IF(SUMIF($A:$A,$P13,$E:$E)=0,"",SUMIF($A:$A,$P13,$E:$E)) -> 0.19583333 | R13: =IF(SUMIF($A:$A,$P13,$H:$H)=0,"",SUMIF($A:$A,$P13,$H:$H)) -> 0.18295139 | S13: =IF(OR(R13="",R13>=$U$1)," ",$U$1-R13) -> 0.15038194 | T13: =IFERROR(AVERAGEIF($A:$A,$P13,$N:$N)," ") -> 1.0724314
A14: 45693 | B14: WH - Country of Origin/ Custom Tarrif | C14: 68 | D14: =IFERROR(VLOOKUP($B14,Task!$B$1:$G$65,6,0)," ") -> 0.0017361111 | E14: =IFERROR(D14*C14," ") -> 0.11805556 | F14: =G13 -> 0.4459838 | G14: 0.57981481 | H14: =IF(G14="","", IF(L14=" ",IF(OR(F14=0,G14=0),"",G14-F14),((G14-F14)-L14))) -> 0.11076389 | I14: =IFERROR(IF(L14=" ",(F14+E14),(F14+E14+L14)),"") -> 0.58710648 | L14: 0.02306713 | N14: =IFERROR(E14/H14," ") -> 1.0658307 | P14: =IFERROR(__xludf.DUMMYFUNCTION("""COMPUTED_VALUE"""),45708) -> 45708 | Q14: =IF(SUMIF($A:$A,$P14,$E:$E)=0,"",SUMIF($A:$A,$P14,$E:$E)) -> 0.25416667 | R14: =IF(SUMIF($A:$A,$P14,$H:$H)=0,"",SUMIF($A:$A,$P14,$H:$H)) -> 0.23662037 | S14: =IF(OR(R14="",R14>=$U$1)," ",$U$1-R14) -> 0.096712963 | T14: =IFERROR(AVERAGEIF($A:$A,$P14,$N:$N)," ") -> 1.0751535
A15: 45693 | B15: Image upload to Very/John Lewis | C15: 3 | D15: =IFERROR(VLOOKUP($B15,Task!$B$1:$G$65,6,0)," ") -> 0.0027777778 | E15: =IFERROR(D15*C15," ") -> 0.0083333333 | F15: =G14 -> 0.57981481 | G15: 0.58725694 | H15: =IF(G15="","", IF(L15=" ",IF(OR(F15=0,G15=0),"",G15-F15),((G15-F15)-L15))) -> 0.0074421296 | I15: =IFERROR(IF(L15=" ",(F15+E15),(F15+E15+L15)),"") -> 0.58814815 | N15: =IFERROR(E15/H15," ") -> 1.1197512 | P15: =IFERROR(__xludf.DUMMYFUNCTION("""COMPUTED_VALUE"""),45709) -> 45709 | Q15: =IF(SUMIF($A:$A,$P15,$E:$E)=0,"",SUMIF($A:$A,$P15,$E:$E)) -> 0.34166667 | R15: =IF(SUMIF($A:$A,$P15,$H:$H)=0,"",SUMIF($A:$A,$P15,$H:$H)) -> 0.31555556 | S15: =IF(OR(R15="",R15>=$U$1)," ",$U$1-R15) -> 0.017777778 | T15: =IFERROR(AVERAGEIF($A:$A,$P15,$N:$N)," ") -> 1.0921114
A16: 45693 | B16: Wholesale Adding Images | C16: 9 | D16: =IFERROR(VLOOKUP($B16,Task!$B$1:$G$65,6,0)," ") -> 0.0013888889 | E16: =IFERROR(D16*C16," ") -> 0.0125 | F16: =G15 -> 0.58725694 | G16: 0.59880787 | H16: =IF(G16="","", IF(L16=" ",IF(OR(F16=0,G16=0),"",G16-F16),((G16-F16)-L16))) -> 0.011550926 | I16: =IFERROR(IF(L16=" ",(F16+E16),(F16+E16+L16)),"") -> 0.59975694 | M16: Nordstrom - imagery not available on DAM | N16: =IFERROR(E16/H16," ") -> 1.0821643 | P16: =IFERROR(__xludf.DUMMYFUNCTION("""COMPUTED_VALUE"""),45712) -> 45712 | Q16: =IF(SUMIF($A:$A,$P16,$E:$E)=0,"",SUMIF($A:$A,$P16,$E:$E)) -> 0.34861111 | R16: =IF(SUMIF($A:$A,$P16,$H:$H)=0,"",SUMIF($A:$A,$P16,$H:$H)) -> 0.32798797 | S16: =IF(OR(R16="",R16>=$U$1)," ",$U$1-R16) -> 0.0053453588 | T16: =IFERROR(AVERAGEIF($A:$A,$P16,$N:$N)," ") -> 1.0748907
A17: 45693 | B17: WH - Fabric Composition | C17: 68 | D17: =IFERROR(VLOOKUP($B17,Task!$B$1:$G$65,6,0)," ") -> 0.0020833333 | E17: =IFERROR(D17*C17," ") -> 0.14166667 | F17: =G16 -> 0.59880787 | G17: 0.76041667 | H17: =IF(G17="","", IF(L17=" ",IF(OR(F17=0,G17=0),"",G17-F17),((G17-F17)-L17))) -> 0.1350463 | I17: =IFERROR(IF(L17=" ",(F17+E17),(F17+E17+L17)),"") -> 0.76703704 | L17: 0.0265625 | N17: =IFERROR(E17/H17," ") -> 1.049023 | P17: =IFERROR(__xludf.DUMMYFUNCTION("""COMPUTED_VALUE"""),45713) -> 45713 | Q17: =IF(SUMIF($A:$A,$P17,$E:$E)=0,"",SUMIF($A:$A,$P17,$E:$E)) -> 0.34236111 | R17: =IF(SUMIF($A:$A,$P17,$H:$H)=0,"",SUMIF($A:$A,$P17,$H:$H)) -> 0.3178588 | S17: =IF(OR(R17="",R17>=$U$1)," ",$U$1-R17) -> 0.015474537 | T17: =IFERROR(AVERAGEIF($A:$A,$P17,$N:$N)," ") -> 1.0745648
A18: 45694 | B18: WH - Wholesale order report | C18: 1 | D18: =IFERROR(VLOOKUP($B18,Task!$B$1:$G$65,6,0)," ") -> 0.034722222 | E18: =IFERROR(D18*C18," ") -> 0.034722222 | F18: 0.38099537 | G18: 0.42350694 | H18: =IF(G18="","", IF(L18=" ",IF(OR(F18=0,G18=0),"",G18-F18),((G18-F18)-L18))) -> 0.031527778 | I18: =IFERROR(IF(L18=" ",(F18+E18),(F18+E18+L18)),"") -> 0.42670139 | L18: 0.010983796 | N18: =IFERROR(E18/H18," ") -> 1.1013216 | P18: =IFERROR(__xludf.DUMMYFUNCTION("""COMPUTED_VALUE"""),45714) -> 45714 | Q18: =IF(SUMIF($A:$A,$P18,$E:$E)=0,"",SUMIF($A:$A,$P18,$E:$E)) -> 0.32222222 | R18: =IF(SUMIF($A:$A,$P18,$H:$H)=0,"",SUMIF($A:$A,$P18,$H:$H)) -> 0.29908565 | S18: =IF(OR(R18="",R18>=$U$1)," ",$U$1-R18) -> 0.034247685 | T18: =IFERROR(AVERAGEIF($A:$A,$P18,$N:$N)," ") -> 1.0760694
A19: 45694 | B19: WH - Sale Journal | C19: 1 | D19: =IFERROR(VLOOKUP($B19,Task!$B$1:$G$65,6,0)," ") -> 0.0069444444 | E19: =IFERROR(D19*C19," ") -> 0.0069444444 | F19: =G18 -> 0.42350694 | G19: 0.43011574 | H19: =IF(G19="","", IF(L19=" ",IF(OR(F19=0,G19=0),"",G19-F19),((G19-F19)-L19))) -> 0.0066087963 | I19: =IFERROR(IF(L19=" ",(F19+E19),(F19+E19+L19)),"") -> 0.43045139 | N19: =IFERROR(E19/H19," ") -> 1.0507881 | P19: =IFERROR(__xludf.DUMMYFUNCTION("""COMPUTED_VALUE"""),45715) -> 45715 | Q19: =IF(SUMIF($A:$A,$P19,$E:$E)=0,"",SUMIF($A:$A,$P19,$E:$E)) -> 0.27986111 | R19: =IF(SUMIF($A:$A,$P19,$H:$H)=0,"",SUMIF($A:$A,$P19,$H:$H)) -> 0.27290509 | S19: =IF(R19=""," ",$U$1-R19) -> 0.060428241 | T19: =IFERROR(AVERAGEIF($A:$A,$P19,$N:$N)," ") -> 1.0803711
A20: 45694 | B20: Nordstrom SQL DATA Dump | C20: 1 | D20: =IFERROR(VLOOKUP($B20,Task!$B$1:$G$65,6,0)," ") -> 0.048611111 | E20: =IFERROR(D20*C20," ") -> 0.048611111 | F20: =G19 -> 0.43011574 | G20: 0.48857639 | H20: =IF(G20="","", IF(L20=" ",IF(OR(F20=0,G20=0),"",G20-F20),((G20-F20)-L20))) -> 0.047592593 | I20: =IFERROR(IF(L20=" ",(F20+E20),(F20+E20+L20)),"") -> 0.48959491 | L20: 0.010868056 | N20: =IFERROR(E20/H20," ") -> 1.0214008 | P20: =IFERROR(__xludf.DUMMYFUNCTION("""COMPUTED_VALUE"""),45716) -> 45716 | Q20: =IF(SUMIF($A:$A,$P20,$E:$E)=0,"",SUMIF($A:$A,$P20,$E:$E)) -> 0.048611111 | R20: =IF(SUMIF($A:$A,$P20,$H:$H)=0,"",SUMIF($A:$A,$P20,$H:$H)) -> 0.043298611 | S20: =IF(R20=""," ",$U$1-R20) -> 0.29003472 | T20: =IFERROR(AVERAGEIF($A:$A,$P20,$N:$N)," ") -> 1.1226945
A21: 45694 | B21: OGM - Sizing update | C21: 15 | D21: =IFERROR(VLOOKUP($B21,Task!$B$1:$G$65,6,0)," ") -> 0.0055555556 | E21: =IFERROR(D21*C21," ") -> 0.083333333 | F21: =G20 -> 0.48857639 | G21: 0.59673611 | H21: =IF(G21="","", IF(L21=" ",IF(OR(F21=0,G21=0),"",G21-F21),((G21-F21)-L21))) -> 0.083194444 | I21: =IFERROR(IF(L21=" ",(F21+E21),(F21+E21+L21)),"") -> 0.596875 | L21: 0.024965278 | N21: =IFERROR(E21/H21," ") -> 1.0016694 | Q21: =IF(SUMIF($A:$A,$P21,$E:$E)=0,"",SUMIF($A:$A,$P21,$E:$E)) | R21: =IF(SUMIF($A:$A,$P21,$H:$H)=0,"",SUMIF($A:$A,$P21,$H:$H)) | S21: =IF(R21=""," ",$U$1-R21) | T21: =IFERROR(AVERAGEIF($A:$A,$P21,$N:$N)," ")
A22: 45694 | B22: WH - Fabric Composition | C22: 38 | D22: =IFERROR(VLOOKUP($B22,Task!$B$1:$G$65,6,0)," ") -> 0.0020833333 | E22: =IFERROR(D22*C22," ") -> 0.079166667 | F22: =G21 -> 0.59673611 | G22: 0.70049769 | H22: =IF(G22="","", IF(L22=" ",IF(OR(F22=0,G22=0),"",G22-F22),((G22-F22)-L22))) -> 0.076261574 | I22: =IFERROR(IF(L22=" ",(F22+E22),(F22+E22+L22)),"") -> 0.70340278 | L22: 0.0275 | N22: =IFERROR(E22/H22," ") -> 1.0380938 | Q22: =IF(SUMIF($A:$A,$P22,$E:$E)=0,"",SUMIF($A:$A,$P22,$E:$E)) | R22: =IF(SUMIF($A:$A,$P22,$H:$H)=0,"",SUMIF($A:$A,$P22,$H:$H)) | S22: =IF(R22=""," ",$U$1-R22) | T22: =IFERROR(AVERAGEIF($A:$A,$P22,$N:$N)," ")
A23: 45694 | B23: WH - Fabric Composition | C23: 30 | D23: =IFERROR(VLOOKUP($B23,Task!$B$1:$G$65,6,0)," ") -> 0.0020833333 | E23: =IFERROR(D23*C23," ") -> 0.0625 | F23: =G22 -> 0.70049769 | G23: 0.76041667 | H23: =IF(G23="","", IF(L23=" ",IF(OR(F23=0,G23=0),"",G23-F23),((G23-F23)-L23))) -> 0.059918981 | I23: =IFERROR(IF(L23=" ",(F23+E23),(F23+E23+L23)),"") -> 0.76299769 | N23: =IFERROR(E23/H23," ") -> 1.0430751 | Q23: =IF(SUMIF($A:$A,$P23,$E:$E)=0,"",SUMIF($A:$A,$P23,$E:$E)) | R23: =IF(SUMIF($A:$A,$P23,$H:$H)=0,"",SUMIF($A:$A,$P23,$H:$H)) | S23: =IF(R23=""," ",$U$1-R23) | T23: =IFERROR(AVERAGEIF($A:$A,$P23,$N:$N)," ")
A24: 45695 | B24: Nordstrom Assets | C24: 60 | D24: =IFERROR(VLOOKUP($B24,Task!$B$1:$G$65,6,0)," ") -> 0.0013888889 | E24: =IFERROR(D24*C24," ") -> 0.083333333 | F24: 0.36597222 | G24: 0.44797454 | H24: =IF(G24="","", IF(L24=" ",IF(OR(F24=0,G24=0),"",G24-F24),((G24-F24)-L24))) -> 0.082002315 | I24: =IFERROR(IF(L24=" ",(F24+E24),(F24+E24+L24)),"") -> 0.44930556 | N24: =IFERROR(E24/H24," ") -> 1.0162315
A25: 45695 | B25: Nordstrom SQL DATA Dump | C25: 1 | D25: =IFERROR(VLOOKUP($B25,Task!$B$1:$G$65,6,0)," ") -> 0.048611111 | E25: =IFERROR(D25*C25," ") -> 0.048611111 | F25: =G24 -> 0.44797454 | G25: 0.4931713 | H25: =IF(G25="","", IF(L25=" ",IF(OR(F25=0,G25=0),"",G25-F25),((G25-F25)-L25))) -> 0.045196759 | I25: =IFERROR(IF(L25=" ",(F25+E25),(F25+E25+L25)),"") -> 0.49658565 | N25: =IFERROR(E25/H25," ") -> 1.0755442
